Workbook

Sheet Notes
B1: To do
A5: PENDING | B5: Sensitivity/Scenario page
B6: Flip churn rate into Retention rate - Anwar to share the steep link.
A26: Anwar previous build notes - completed
A28: DONE | B28: Usability idea - autofeed all overheads onto one page so month end recs become faster
A29: DONE | B29: IT & ES - split out
A30: DONE | B30: Build a traffic % YoY change row in the D2C Model tabs
A31: KPIs | B31: Total number of subscriber base
A32: KPIs | B32: Total number of new customers
A33: DONE | B33: Need to think how we view in territory & function on same workflow
A34: DONE | B34: Need P&L Grouping (all functions) into EE, CE, UK and OTHER
A35: For fulfilment I would look at just using % assumptions on revenue same with COGs for CM1 but here is some revenue and overhead information that may help.
A37: B2B: Follow same phasing as this year
A38: Year 25/26 - £9.2m Minimal NPD - Growing what we have with some NPD -15% YOY
A39: Year 26/27 - 30% growth - £11.9m - New NPD and retail strategy in motion
A40: Year 27/28 - 30% Growth YOY - £15.5m
A42: Amazon: Follow same phasing as this year
A44: Year 25/26 - £3.5m - 15% Growth
A45: Year 26/27 - 30% growth - £4.55m - New NPD
A46: Year 27/28 - 30% Growth YOY - £5.9m
A48: DTC - Will use new DTC Model
A50: Overhead assumptions
A52: This year forecast is: £4.1m
... A58: Mainly driven by staff, office and relative increase to other overhead.

Sheet KPI Tracker
A1: KPI Tracker
A4: KPI | B4: 45689 | C4: 45717 | D4: 45748 | E4: 45778 | F4: 45809 | G4: 45839 | H4: 45870 | I4: 45901 | J4: 45931 | K4: 45962 | L4: 45992 | M4: 46023 | P4: Data source
A5: Total number of subscriber base | B5: 4640 | C5: 4492 | D5: 4668 | E5: 4562 | F5: 4204 | G5: 4481 | H5: 4274 | P5: https://web.steep.app/iJCBj22SsI2B/metrics/LM86etumQc29?chart=bar&from=2025-02-01&grain=auto&period=custom&tab=explore&to=2025-08-31
A6: of which adv+ | B6: 632 | C6: 579 | D6: 555 | E6: 549 | F6: 538 | G6: 753 | H6: 826 | P6: https://web.steep.app/iJCBj22SsI2B/metrics/LM86etumQc29?chart=bar&dim-8-kWIW2rwbcz=10-HB_PREMVIT&from=2025-02-01&grain=auto&period=custom&tab=explore&to=2025-08-31
A7: Total number of new customers | B7: 7369 | C7: 15233 | D7: 16122 | E7: 13374 | F7: 9633 | G7: 19530 | H7: 8210 | P7: https://web.steep.app/iJCBj22SsI2B/metrics/GOLeJLLE_shJ?chart=bar&from=2025-02-01&grain=auto&period=custom&tab=explore&to=2025-08-31
A12: Operating model | B12: FY25/26 | C12: FY25/26 | E12: FY26/27 | F12: FY26/27 | H12: FY27/28 | I12: FY27/28
B13: Ideal | C13: Forecast | E13: Ideal | F13: Forecast | H13: Ideal | I13: Forecast
A14: Sales | B14: 20.3 | C14: ='Combined P&L'!Q12/1000000 -> 18.027702 | E14: 27 | F14: ='Combined P&L'!AF12/1000000 -> 23.399235 | H14: 40.5 | I14: ='Combined P&L'!AU12/1000000 -> 34.315419
A16: COGS% | B16: 0.26 | C16: =C17/C14 -> 0.25921856 | E16: 0.26 | F16: =F17/F14 -> 0.24416794 | H16: 0.26 | I16: =I17/I14 -> 0.23657478
A17: COGS£ | B17: =B16*B14 -> 5.278 | C17: =-'Combined P&L'!Q21/1000000 -> 4.673115 | E17: =E16*E14 -> 7.02 | F17: =-'Combined P&L'!AF21/1000000 -> 5.7133429 | H17: =H16*H14 -> 10.53 | I17: =-'Combined P&L'!AU21/1000000 -> 8.1181627
A19: Ops & Fulfilment % | B19: 0.17 | C19: =C20/C14 -> 0.18898521 | E19: 0.17 | F19: =F20/F14 -> 0.17993976 | H19: 0.16 | I19: =I20/I14 -> 0.17174308
A20: Ops & Fulfilment £ | B20: =B19*B14 -> 3.451 | C20: =-'Combined P&L'!Q43/1000000 -> 3.406969 | E20: =E19*E14 -> 4.59 | F20: =-'Combined P&L'!AF43/1000000 -> 4.2104527 | H20: =H19*H14 -> 6.48 | I20: =-'Combined P&L'!AU43/1000000 -> 5.8934356
A22: Marketing % | B22: 0.28 | C22: =C23/C14 -> 0.29363193 | E22: 0.27 | F22: =F23/F14 -> 0.31740135 | H22: 0.27 | I22: =I23/I14 -> 0.2966971
A23: Marketing £ | B23: =B22*B14 -> 5.684 | C23: =-'Combined P&L'!Q71/1000000 -> 5.293509 | E23: =E22*E14 -> 7.29 | F23: =-'Combined P&L'!AF71/1000000 -> 7.4269488 | H23: =H22*H14 -> 10.935 | I23: =-'Combined P&L'!AU71/1000000 -> 10.181285
A25: Overhead % | B25: 0.2 | C25: =C27/C14 -> 0.22738603 | E25: 0.19 | F25: =F27/F14 -> 0.20693765 | H25: 0.18 | I25: =I27/I14 -> 0.16228031
A26: Of which people | B26: 0.147 | C26: =C28/C14 -> 0.15779454 | E26: 0.13 | F26: =F28/F14 -> 0.15035789 | H26: 0.11 | I26: =I28/I14 -> 0.10388373
A27: Overhead £ | B27: =B25*B14 -> 4.06 | C27: =-'Combined P&L'!Q99/1000000 -> 4.0992475 | E27: =E25*E14 -> 5.13 | F27: =-'Combined P&L'!AF99/1000000 -> 4.8421827 | H27: =H25*H14 -> 7.29 | I27: =-'Combined P&L'!AU99/1000000 -> 5.5687168
A28: Of which people £ | B28: =B26*B14 -> 2.9841 | C28: =-('Combined P&L'!Q89+'Combined P&L'!Q90)/1000000 -> 2.844673 | E28: =E26*E14 -> 3.51 | F28: =-('Combined P&L'!AF89+'Combined P&L'!AF90)/1000000 -> 3.5182596 | H28: =H26*H14 -> 4.455 | I28: =-('Combined P&L'!AU89+'Combined P&L'!AU90)/1000000 -> 3.5648137
A30: EBITDA % | B30: 0.09 | C30: =C31/C14 -> 0.030808373 | E30: 0.11 | F30: =F31/F14 -> 0.0061491279 | H30: 0.13 | I30: =I31/I14 -> 0.13270473
A31: EBITDA £M | B31: =B30*B14 -> 1.827 | C31: ='Combined P&L'!Q101/1000000 -> 0.55540417 | E31: =E30*E14 -> 2.97 | F31: ='Combined P&L'!T101/1000000 -> 0.14388489 | H31: =H30*H14 -> 5.265 | I31: ='Combined P&L'!AU101/1000000 -> 4.5538185

Sheet FY26-FY27 Summary
A2: Territory | B2: Revenue FY25/26 | C2: Revenue FY26/27 | D2: YoY % | F2: CM3 FY25/26 | G2: CM3% FY25/26 | H2: CM3 FY26/27 | I2: CM3% FY26/27 | J2: YoY %
A3: UK | B3: ='UK P&L'!Q12 -> 8107166.5 | C3: ='UK P&L'!AF12 -> 11362149 | D3: =(C3-B3)/B3 -> 0.40149452 | F3: ='UK P&L'!Q77 -> 1731349.6 | G3: ='UK P&L'!Q83 -> 0.21355792 | H3: ='UK P&L'!AF77 -> 2575624.8 | I3: ='UK P&L'!AF83 -> 0.22668464 | J3: =(H3-F3)/F3 -> 0.48763994
A4: CE | B4: ='CE P&L'!Q12 -> 3001838 | C4: ='CE P&L'!AF12 -> 4302007.5 | D4: =(C4-B4)/B4 -> 0.43312449 | F4: ='CE P&L'!Q77 -> 1051452.5 | G4: ='CE P&L'!Q83 -> 0.35026957 | H4: ='CE P&L'!AF77 -> 1261552 | I4: ='CE P&L'!AF83 -> 0.29324728 | J4: =(H4-F4)/F4 -> 0.19981835
A5: EE | B5: ='EE P&L'!Q12 -> 5593663 | C5: ='EE P&L'!AF12 -> 6840161.7 | D5: =(C5-B5)/B5 -> 0.22284122 | F5: ='EE P&L'!Q77 -> 1745507 | G5: ='EE P&L'!Q83 -> 0.3120508 | H5: ='EE P&L'!AF77 -> 2042799.9 | I5: ='EE P&L'!AF83 -> 0.29864789 | J5: =(H5-F5)/F5 -> 0.17031894
A6: ROW | B6: ='ROW P&L'!Q13 -> 1324326 | C6: ='ROW P&L'!AF13 -> 894916.07 | D6: =(C6-B6)/B6 -> -0.32424791 | F6: ='ROW P&L'!Q78 -> 614598 | G6: ='ROW P&L'!Q84 -> 0.46408362 | H6: ='ROW P&L'!AF78 -> 468513.56 | I6: ='ROW P&L'!AF84 -> 0.52352794 | J6: =(H6-F6)/F6 -> -0.23769104
A8: HU | B8: ='HU P&L'!Q12 -> 1566840.7 | C8: ='HU P&L'!AF12 -> 1837229.3 | D8: =(C8-B8)/B8 -> 0.17256931 | F8: ='HU P&L'!Q77 -> 477648.89 | G8: ='HU P&L'!Q83 -> 0.30484841 | H8: ='HU P&L'!AF77 -> 557044.66 | I8: ='HU P&L'!AF83 -> 0.30319823 | J8: =(H8-F8)/F8 -> 0.16622203
A9: IT | B9: ='IT P&L'!Q11 -> 953134.99 | C9: ='IT P&L'!AF11 -> 1367809.7 | D9: =(C9-B9)/B9 -> 0.43506395 | F9: ='IT P&L'!Q76 -> 327049.54 | G9: ='IT P&L'!Q82 -> 0.34313035 | H9: ='IT P&L'!AF76 -> 453219.16 | I9: ='IT P&L'!AF82 -> 0.33134666 | J9: =(H9-F9)/F9 -> 0.38578138
A10: SK | B10: ='SK P&L'!Q12 -> 1506094.1 | C10: ='SK P&L'!AF12 -> 1607823.1 | D10: =(C10-B10)/B10 -> 0.067544941 | F10: ='SK P&L'!Q77 -> 485906.66 | G10: ='SK P&L'!Q83 -> 0.32262703 | H10: ='SK P&L'!AF77 -> 525768.8 | I10: ='SK P&L'!AF83 -> 0.32700661 | J10: =(H10-F10)/F10 -> 0.082036616
A11: CZ | B11: ='CZ P&L'!Q11 -> 1663108.5 | C11: ='CZ P&L'!AF11 -> 2218111.4 | D11: =(C11-B11)/B11 -> 0.33371422 | F11: ='CZ P&L'!Q75 -> 578894.26 | G11: ='CZ P&L'!Q81 -> 0.34807968 | H11: ='CZ P&L'!AF75 -> 777869.53 | I11: ='CZ P&L'!AF81 -> 0.35069002 | J11: =(H11-F11)/F11 -> 0.3437161
A12: RO | B12: ='RO P&L'!Q12 -> 857524.78 | C12: ='RO P&L'!AF12 -> 1068497.9 | D12: =(C12-B12)/B12 -> 0.24602563 | F12: ='RO P&L'!Q77 -> 201551.43 | G12: ='RO P&L'!Q83 -> 0.23503861 | H12: ='RO P&L'!AF77 -> 309885.62 | I12: ='RO P&L'!AF83 -> 0.29001988 | J12: =(H12-F12)/F12 -> 0.53750147
A13: ES | B13: ='ES P&L'!Q12 -> 1038036.3 | C13: ='ES P&L'!AF12 -> 1417747.9 | D13: =(C13-B13)/B13 -> 0.36579793 | F13: ='ES P&L'!Q77 -> 308059.29 | G13: ='ES P&L'!Q83 -> 0.29677121 | H13: ='ES P&L'!AF77 -> 328708.42 | I13: ='ES P&L'!AF83 -> 0.23185252 | J13: =(H13-F13)/F13 -> 0.067029716

Sheet Scenario
A1: P&L Scenario Planner | B1: FY27 | U1: FY28
B2: UK | E2: CE | H2: EE | K2: ROW | N2: Non Rev | Q2: Combined | U2: UK | X2: CE | AA2: EE | AD2: ROW | AG2: Non Rev | AJ2: Combined
B3: FY27 | C3: Change | D3: New | E3: FY27 | F3: Change | G3: New | H3: FY27 | I3: Change | J3: New | K3: FY27 | L3: Change | M3: New | N3: FY27 | O3: Change | P3: New | Q3: FY27 | R3: Change | S3: New | U3: FY28 | V3: Change | W3: New | X3: FY28 | Y3: Change | Z3: New | AA3: FY28 | AB3: Change | AC3: New | AD3: FY28 | AE3: Change | AF3: New | AG3: FY28 | AH3: Change | AI3: New | AJ3: FY28 | AK3: Change | AL3: New
A4: Revenue
A6: DTC Revenue | B6: ='UK P&L'!AF7 -> 4837985.8 | C6: 0 | D6: =B6+C6 -> 4837985.8 | E6: ='CE P&L'!AF7 -> 1666198.3 | F6: 0 | G6: =E6+F6 -> 1666198.3 | H6: ='EE P&L'!AF7 -> 6022814.5 | I6: 0 | J6: =H6+I6 -> 6022814.5 | K6: ='ROW P&L'!AF8 -> 0 | L6: 0 | M6: =K6+L6 -> 0 | O6: 0 | P6: =N6+O6 -> 0 | Q6: =B6+E6+H6+K6+N6 -> 12526999 | R6: 0 | S6: =Q6+R6 -> 12526999 | U6: ='UK P&L'!AU7 -> 11107766 | V6: 0 | W6: =U6+V6 -> 11107766 | X6: ='CE P&L'!AU7 -> 3483235.2 | Y6: 0 | Z6: =X6+Y6 -> 3483235.2 | AA6: ='EE P&L'!AU7 -> 6936063.2 | AB6: 0 | AC6: =AA6+AB6 -> 6936063.2 | AD6: ='ROW P&L'!AU8 -> 0 | AE6: 0 | AF6: =AD6+AE6 -> 0 | AH6: 0 | AJ6: =U6+X6+AA6+AD6+AG6 -> 21527065 | AK6: 0 | AL6: =AJ6+AK6 -> 21527065
A7: B2B Revenue | B7: ='UK P&L'!AF8 -> 4178100.8 | C7: 0 | D7: =B7+C7 -> 4178100.8 | E7: ='CE P&L'!AF8 -> 1803733.2 | F7: 0 | G7: =E7+F7 -> 1803733.2 | H7: ='EE P&L'!AF8 -> 817347.16 | I7: 0 | J7: =H7+I7 -> 817347.16 | K7: ='ROW P&L'!AF9 -> 768617.31 | L7: 0 | M7: =K7+L7 -> 768617.31 | O7: 0 | P7: =N7+O7 -> 0 | Q7: =B7+E7+H7+K7+N7 -> 7567798.5 | R7: 0 | S7: =Q7+R7 -> 7567798.5 | U7: ='UK P&L'!AU8 -> 4971270.3 | V7: 0 | W7: =U7+V7 -> 4971270.3 | X7: ='CE P&L'!AU8 -> 2592839.9 | Y7: 0 | Z7: =X7+Y7 -> 2592839.9 | AA7: ='EE P&L'!AU8 -> 925414.52 | AB7: 0 | AC7: =AA7+AB7 -> 925414.52 | AD7: ='ROW P&L'!AU9 -> 795421.62 | AE7: 0 | AF7: =AD7+AE7 -> 795421.62 | AH7: 0 | AJ7: =U7+X7+AA7+AD7+AG7 -> 9284946.4 | AK7: 0 | AL7: =AJ7+AK7 -> 9284946.4
A8: Marketplace Revenue | B8: ='UK P&L'!AF9 -> 2346062.8 | C8: 0 | D8: =B8+C8 -> 2346062.8 | E8: ='CE P&L'!AF9 -> 832076.01 | F8: 0 | G8: =E8+F8 -> 832076.01 | H8: ='EE P&L'!AF9 -> 0 | I8: 0 | J8: =H8+I8 -> 0 | K8: ='ROW P&L'!AF10 -> 126298.76 | L8: 0 | M8: =K8+L8 -> 126298.76 | O8: 0 | P8: =N8+O8 -> 0 | Q8: =B8+E8+H8+K8+N8 -> 3304437.5 | R8: 0 | S8: =Q8+R8 -> 3304437.5 | U8: ='UK P&L'!AU9 -> 2369523.4 | V8: 0 | W8: =U8+V8 -> 2369523.4 | X8: ='CE P&L'!AU9 -> 1007585.8 | Y8: 0 | Z8: =X8+Y8 -> 1007585.8 | AA8: ='EE P&L'!AU9 -> 0 | AB8: 0 | AC8: =AA8+AB8 -> 0 | AD8: ='ROW P&L'!AU10 -> 126298.76 | AE8: 0 | AF8: =AD8+AE8 -> 126298.76 | AH8: 0 | AJ8: =U8+X8+AA8+AD8+AG8 -> 3503407.9 | AK8: 0 | AL8: =AJ8+AK8 -> 3503407.9
A9: TikTok Revenue | B9: ='UK P&L'!AF10 -> 0 | C9: 0 | D9: =B9+C9 -> 0 | E9: ='CE P&L'!AF10 -> 0 | F9: 0 | G9: =E9+F9 -> 0 | H9: ='EE P&L'!AF10 -> 0 | I9: 0 | J9: =H9+I9 -> 0 | K9: ='ROW P&L'!AF11 -> 0 | L9: 0 | M9: =K9+L9 -> 0 | O9: 0 | P9: =N9+O9 -> 0 | Q9: =B9+E9+H9+K9+N9 -> 0 | R9: 0 | S9: =Q9+R9 -> 0 | U9: ='UK P&L'!AU10 -> 0 | V9: 0 | W9: =U9+V9 -> 0 | X9: ='CE P&L'!AU10 -> 0 | Y9: 0 | Z9: =X9+Y9 -> 0 | AA9: ='EE P&L'!AU10 -> 0 | AB9: 0 | AC9: =AA9+AB9 -> 0 | AD9: ='ROW P&L'!AU11 -> 0 | AE9: 0 | AF9: =AD9+AE9 -> 0 | AH9: 0 | AJ9: =U9+X9+AA9+AD9+AG9 -> 0 | AK9: 0 | AL9: =AJ9+AK9 -> 0
A11: Total Revenue | B11: ='UK P&L'!AF12 -> 11362149 | C11: =SUM(C6:C9) -> 0 | D11: =B11+C11 -> 11362149 | E11: ='CE P&L'!AF12 -> 4302007.5 | F11: =SUM(F6:F9) -> 0 | G11: =E11+F11 -> 4302007.5 | H11: ='EE P&L'!AF12 -> 6840161.7 | I11: =SUM(I6:I9) -> 0 | J11: =H11+I11 -> 6840161.7 | K11: ='ROW P&L'!AF13 -> 894916.07 | L11: =SUM(L6:L9) -> 0 | M11: =K11+L11 -> 894916.07 | O11: =SUM(O6:O9) -> 0 | P11: =N11+O11 -> 0 | Q11: =B11+E11+H11+K11+N11 -> 23399235 | R11: =SUM(R6:R9) -> 0 | S11: =Q11+R11 -> 23399235 | U11: ='UK P&L'!AU12 -> 18448560 | V11: =SUM(V6:V9) -> 0 | W11: =U11+V11 -> 18448560 | X11: ='CE P&L'!AU12 -> 7083660.9 | Y11: =SUM(Y6:Y9) -> 0 | Z11: =X11+Y11 -> 7083660.9 | AA11: ='EE P&L'!AU12 -> 7861477.7 | AB11: =SUM(AB6:AB9) -> 0 | AC11: =AA11+AB11 -> 7861477.7 | AD11: ='ROW P&L'!AU13 -> 921720.38 | AE11: =SUM(AE6:AE9) -> 0 | AF11: =AD11+AE11 -> 921720.38 | AG11: ='Non Rev P&L'!AU7 -> 0 | AH11: =SUM(AH6:AH9) -> 0 | AI11: =AG11+AH11 -> 0 | AJ11: =U11+X11+AA11+AD11+AG11 -> 34315419 | AK11: =SUM(AK6:AK9) -> 0 | AL11: =AJ11+AK11 -> 34315419
A13: Cost of Goods Sold (CoGS)
A15: DTC CoGS | B15: ='UK P&L'!AF16 -> -1015977 | C15: 0 | D15: =B15+C15 -> -1015977 | E15: ='CE P&L'!AF16 -> -399887.59 | F15: 0 | G15: =E15+F15 -> -399887.59 | H15: ='EE P&L'!AF16 -> -1445475.5 | I15: 0 | J15: =H15+I15 -> -1445475.5 | K15: ='ROW P&L'!AF17 -> 0 | L15: 0 | M15: =K15+L15 -> 0 | O15: 0 | P15: =N15+O15 -> 0 | Q15: =B15+E15+H15+K15+N15 -> -2861340.1 | R15: 300000 | S15: =Q15+R15 -> -2561340.1 | U15: ='UK P&L'!AU16 -> -2221553.3 | V15: 0 | W15: =U15+V15 -> -2221553.3 | X15: ='CE P&L'!AU16 -> -835976.45 | Y15: 0 | Z15: =X15+Y15 -> -835976.45 | AA15: ='EE P&L'!AU16 -> -1664655.2 | AB15: 0 | AC15: =AA15+AB15 -> -1664655.2 | AD15: ='ROW P&L'!AU17 -> 0 | AE15: 0 | AF15: =AD15+AE15 -> 0 | AH15: 0 | AJ15: =U15+X15+AA15+AD15+AG15 -> -4722184.9 | AK15: 0 | AL15: =AJ15+AK15 -> -4722184.9
A16: B2B CoGS | B16: ='UK P&L'!AF17 -> -1066251.3 | C16: 0 | D16: =B16+C16 -> -1066251.3 | E16: ='CE P&L'!AF17 -> -577194.63 | F16: 0 | G16: =E16+F16 -> -577194.63 | H16: ='EE P&L'!AF17 -> -326938.87 | I16: 0 | J16: =H16+I16 -> -326938.87 | K16: ='ROW P&L'!AF18 -> -286819.27 | L16: 0 | M16: =K16+L16 -> -286819.27 | O16: 0 | P16: =N16+O16 -> 0 | Q16: =B16+E16+H16+K16+N16 -> -2257204.1 | R16: 0 | S16: =Q16+R16 -> -2257204.1 | U16: ='UK P&L'!AU17 -> -1268668.2 | V16: 0 | W16: =U16+V16 -> -1268668.2 | X16: ='CE P&L'!AU17 -> -829708.77 | Y16: 0 | Z16: =X16+Y16 -> -829708.77 | AA16: ='EE P&L'!AU17 -> -370165.81 | AB16: 0 | AC16: =AA16+AB16 -> -370165.81 | AD16: ='ROW P&L'!AU18 -> -296821.64 | AE16: 0 | AF16: =AD16+AE16 -> -296821.64 | AH16: 0 | AJ16: =U16+X16+AA16+AD16+AG16 -> -2765364.4 | AK16: 0 | AL16: =AJ16+AK16 -> -2765364.4
A17: Marketplace CoGS | B17: ='UK P&L'!AF18 -> -422291.3 | C17: 0 | D17: =B17+C17 -> -422291.3 | E17: ='CE P&L'!AF18 -> -149773.68 | F17: 0 | G17: =E17+F17 -> -149773.68 | H17: ='EE P&L'!AF18 -> 0 | I17: 0 | J17: =H17+I17 -> 0 | K17: ='ROW P&L'!AF19 -> -22733.777 | L17: 0 | M17: =K17+L17 -> -22733.777 | O17: 0 | P17: =N17+O17 -> 0 | Q17: =B17+E17+H17+K17+N17 -> -594798.76 | R17: 0 | S17: =Q17+R17 -> -594798.76 | U17: ='UK P&L'!AU18 -> -426514.21 | V17: 0 | W17: =U17+V17 -> -426514.21 | X17: ='CE P&L'!AU18 -> -181365.44 | Y17: 0 | Z17: =X17+Y17 -> -181365.44 | AA17: ='EE P&L'!AU18 -> 0 | AB17: 0 | AC17: =AA17+AB17 -> 0 | AD17: ='ROW P&L'!AU19 -> -22733.777 | AE17: 0 | AF17: =AD17+AE17 -> -22733.777 | AH17: 0 | AJ17: =U17+X17+AA17+AD17+AG17 -> -630613.43 | AK17: 0 | AL17: =AJ17+AK17 -> -630613.43
A18: TikTok CoGS | B18: ='UK P&L'!AF19 -> 0 | C18: 0 | D18: =B18+C18 -> 0 | E18: ='CE P&L'!AF19 -> 0 | F18: 0 | G18: =E18+F18 -> 0 | H18: ='EE P&L'!AF19 -> 0 | I18: 0 | J18: =H18+I18 -> 0 | K18: ='ROW P&L'!AF20 -> 0 | L18: 0 | M18: =K18+L18 -> 0 | O18: 0 | P18: =N18+O18 -> 0 | Q18: =B18+E18+H18+K18+N18 -> 0 | R18: 0 | S18: =Q18+R18 -> 0 | U18: ='UK P&L'!AU19 -> 0 | V18: 0 | W18: =U18+V18 -> 0 | X18: ='CE P&L'!AU19 -> 0 | Y18: 0 | Z18: =X18+Y18 -> 0 | AA18: ='EE P&L'!AU19 -> 0 | AB18: 0 | AC18: =AA18+AB18 -> 0 | AD18: ='ROW P&L'!AU20 -> 0 | AE18: 0 | AF18: =AD18+AE18 -> 0 | AH18: 0 | AJ18: =U18+X18+AA18+AD18+AG18 -> 0 | AK18: 0 | AL18: =AJ18+AK18 -> 0
A20: Total CoGS | B20: ='UK P&L'!AF21 -> -2504519.6 | C20: =SUM(C15:C18) -> 0 | D20: =B20+C20 -> -2504519.6 | E20: ='CE P&L'!AF21 -> -1126855.9 | F20: =SUM(F15:F18) -> 0 | G20: =E20+F20 -> -1126855.9 | H20: ='EE P&L'!AF21 -> -1772414.3 | I20: =SUM(I15:I18) -> 0 | J20: =H20+I20 -> -1772414.3 | K20: ='ROW P&L'!AF22 -> -309553.05 | L20: =SUM(L15:L18) -> 0 | M20: =K20+L20 -> -309553.05 | N20: ='Non Rev P&L'!AF12 -> 0 | O20: =SUM(O15:O18) -> 0 | P20: =N20+O20 -> 0 | Q20: =B20+E20+H20+K20+N20 -> -5713342.9 | R20: =SUM(R15:R18) -> 300000 | S20: =Q20+R20 -> -5413342.9 | U20: ='UK P&L'!AU21 -> -3916735.7 | V20: =SUM(V15:V18) -> 0 | W20: =U20+V20 -> -3916735.7 | X20: ='CE P&L'!AU21 -> -1847050.7 | Y20: =SUM(Y15:Y18) -> 0 | Z20: =X20+Y20 -> -1847050.7 | AA20: ='EE P&L'!AU21 -> -2034821 | AB20: =SUM(AB15:AB18) -> 0 | AC20: =AA20+AB20 -> -2034821 | AD20: ='ROW P&L'!AU22 -> -319555.41 | AE20: =SUM(AE15:AE18) -> 0 | AF20: =AD20+AE20 -> -319555.41 | AG20: ='Non Rev P&L'!AU12 -> 0 | AH20: =SUM(AH15:AH18) -> 0 | AI20: =AG20+AH20 -> 0 | AJ20: =U20+X20+AA20+AD20+AG20 -> -8118162.7 | AK20: =SUM(AK15:AK18) -> 0 | AL20: =AJ20+AK20 -> -8118162.7
A22: DTC CM1 | B22: ='UK P&L'!AF23 -> 3822008.8 | E22: ='UK P&L'!AI23 -> 554524.82 | H22: ='UK P&L'!AL23 -> 667945.7 | K22: ='UK P&L'!AO23 -> 780594.42 | N22: ='UK P&L'!AR23 -> 908294.21 | Q22: ='UK P&L'!AU23 -> 8886213 | U22: ='UK P&L'!AY23 -> 0 | X22: ='UK P&L'!BB23 -> 0 | AA22: ='UK P&L'!BE23 -> 0 | AD22: ='UK P&L'!BH23 -> 0 | AG22: ='UK P&L'!BK23 -> 0 | AJ22: ='UK P&L'!BN23 -> 0
A23: B2B CM1 | B23: ='UK P&L'!AF24 -> 3111849.5 | E23: ='UK P&L'!AI24 -> 225085.8 | H23: ='UK P&L'!AL24 -> 262000.55 | K23: ='UK P&L'!AO24 -> 726888.5 | N23: ='UK P&L'!AR24 -> 295527.84 | Q23: ='UK P&L'!AU24 -> 3702602.1 | U23: ='UK P&L'!AY24 -> 0 | X23: ='UK P&L'!BB24 -> 0 | AA23: ='UK P&L'!BE24 -> 0 | AD23: ='UK P&L'!BH24 -> 0 | AG23: ='UK P&L'!BK24 -> 0 | AJ23: ='UK P&L'!BN24 -> 0
A24: Marketplace CM1 | B24: ='UK P&L'!AF25 -> 1923771.5 | E24: ='UK P&L'!AI25 -> 157016.78 | H24: ='UK P&L'!AL25 -> 149512.67 | K24: ='UK P&L'!AO25 -> 160613.71 | N24: ='UK P&L'!AR25 -> 191028.94 | Q24: ='UK P&L'!AU25 -> 1943009.2 | U24: ='UK P&L'!AY25 -> 0 | X24: ='UK P&L'!BB25 -> 0 | AA24: ='UK P&L'!BE25 -> 0 | AD24: ='UK P&L'!BH25 -> 0 | AG24: ='UK P&L'!BK25 -> 0 | AJ24: ='UK P&L'!BN25 -> 0
A25: TikTok CM1 | B25: ='UK P&L'!AF26 -> 0 | E25: ='UK P&L'!AI26 -> 0 | H25: ='UK P&L'!AL26 -> 0 | K25: ='UK P&L'!AO26 -> 0 | N25: ='UK P&L'!AR26 -> 0 | Q25: ='UK P&L'!AU26 -> 0 | U25: ='UK P&L'!AY26 -> 0 | X25: ='UK P&L'!BB26 -> 0 | AA25: ='UK P&L'!BE26 -> 0 | AD25: ='UK P&L'!BH26 -> 0 | AG25: ='UK P&L'!BK26 -> 0 | AJ25: ='UK P&L'!BN26 -> 0
A26: Total CM1 | B26: ='UK P&L'!AF27 -> 8857629.8 | E26: ='UK P&L'!AI27 -> 936627.41 | H26: ='UK P&L'!AL27 -> 1079458.9 | K26: ='UK P&L'!AO27 -> 1668096.6 | N26: ='UK P&L'!AR27 -> 1394851 | Q26: ='UK P&L'!AU27 -> 14531824 | U26: ='UK P&L'!AY27 -> 0 | X26: ='UK P&L'!BB27 -> 0 | AA26: ='UK P&L'!BE27 -> 0 | AD26: ='UK P&L'!BH27 -> 0 | AG26: ='UK P&L'!BK27 -> 0 | AJ26: ='UK P&L'!BN27 -> 0
A28: DTC CM1% | B28: ='UK P&L'!AF29 -> 0.79 | E28: ='UK P&L'!AI29 -> 0.8 | H28: ='UK P&L'!AL29 -> 0.8 | K28: ='UK P&L'!AO29 -> 0.8 | N28: ='UK P&L'!AR29 -> 0.8 | Q28: ='UK P&L'!AU29 -> 0.8 | U28: ='UK P&L'!AY29 -> 0 | X28: ='UK P&L'!BB29 -> 0 | AA28: ='UK P&L'!BE29 -> 0 | AD28: ='UK P&L'!BH29 -> 0 | AG28: ='UK P&L'!BK29 -> 0 | AJ28: ='UK P&L'!BN29 -> 0
A29: B2B CM1% | B29: ='UK P&L'!AF30 -> 0.7448 | E29: ='UK P&L'!AI30 -> 0.7448 | H29: ='UK P&L'!AL30 -> 0.7448 | K29: ='UK P&L'!AO30 -> 0.7448 | N29: ='UK P&L'!AR30 -> 0.7448 | Q29: ='UK P&L'!AU30 -> 0.7448 | U29: ='UK P&L'!AY30 -> 0 | X29: ='UK P&L'!BB30 -> 0 | AA29: ='UK P&L'!BE30 -> 0 | AD29: ='UK P&L'!BH30 -> 0 | AG29: ='UK P&L'!BK30 -> 0 | AJ29: ='UK P&L'!BN30 -> 0
A30: Marketplace CM1% | B30: ='UK P&L'!AF31 -> 0.82 | E30: ='UK P&L'!AI31 -> 0.82 | H30: ='UK P&L'!AL31 -> 0.82 | K30: ='UK P&L'!AO31 -> 0.82 | N30: ='UK P&L'!AR31 -> 0.82 | Q30: ='UK P&L'!AU31 -> 0.82 | U30: ='UK P&L'!AY31 -> 0 | X30: ='UK P&L'!BB31 -> 0 | AA30: ='UK P&L'!BE31 -> 0 | AD30: ='UK P&L'!BH31 -> 0 | AG30: ='UK P&L'!BK31 -> 0 | AJ30: ='UK P&L'!BN31 -> 0
A31: TikTok CM1% | B31: ='UK P&L'!AF32 -> 0 | E31: ='UK P&L'!AI32 -> 0 | H31: ='UK P&L'!AL32 -> 0 | K31: ='UK P&L'!AO32 -> 0 | N31: ='UK P&L'!AR32 -> 0 | Q31: ='UK P&L'!AU32 -> 0 | U31: ='UK P&L'!AY32 -> 0 | X31: ='UK P&L'!BB32 -> 0 | AA31: ='UK P&L'!BE32 -> 0 | AD31: ='UK P&L'!BH32 -> 0 | AG31: ='UK P&L'!BK32 -> 0 | AJ31: ='UK P&L'!BN32 -> 0
A32: Total CM1% | B32: ='UK P&L'!AF33 -> 0.77957343 | E32: ='UK P&L'!AI33 -> 0.78917108 | H32: ='UK P&L'!AL33 -> 0.78848007 | K32: ='UK P&L'!AO33 -> 0.77673872 | N32: ='UK P&L'!AR33 -> 0.79023098 | Q32: ='UK P&L'!AU33 -> 0.78769423 | U32: ='UK P&L'!AY33 -> 0 | X32: ='UK P&L'!BB33 -> 0 | AA32: ='UK P&L'!BE33 -> 0 | AD32: ='UK P&L'!BH33 -> 0 | AG32: ='UK P&L'!BK33 -> 0 | AJ32: ='UK P&L'!BN33 -> 0
A34: Fulfilment
A36: Central | B36: ='UK P&L'!AF37 -> 0 | E36: ='CE P&L'!AF37 -> 0 | F36: 75000 | H36: ='EE P&L'!AF37 -> 0 | K36: ='ROW P&L'!AF38 -> 0 | N36: ='Non Rev P&L'!AF19 -> -300000 | O36: 0 | P36: =N36+O36 -> -300000 | Q36: =B36+E36+H36+K36+N36 -> -300000 | R36: 30000 | U36: ='UK P&L'!AU37 -> 0 | X36: ='CE P&L'!AU37 -> 0 | AA36: ='EE P&L'!AU37 -> 0 | AD36: ='ROW P&L'!AU38 -> 0 | AG36: ='Non Rev P&L'!AU19 -> -300000 | AJ36: =U36+X36+AA36+AD36+AG36 -> -300000 | AL36: =AJ36+AK36 -> -300000
A37: DTC Fulfilment | B37: ='UK P&L'!AF38 -> -660990.96 | C37: 0 | D37: =B37+C37 -> -660990.96 | E37: ='CE P&L'!AF38 -> -322094.41 | F37: 0 | G37: =E37+F37 -> -322094.41 | H37: ='EE P&L'!AF38 -> -1164276.1 | I37: 0 | J37: =H37+I37 -> -1164276.1 | K37: ='ROW P&L'!AF39 -> 0 | L37: 0 | M37: =K37+L37 -> 0 | N37: ='Non Rev P&L'!AF20 -> 0 | O37: 0 | P37: =N37+O37 -> 0 | Q37: =B37+E37+H37+K37+N37 -> -2147361.5 | R37: 0 | S37: =Q37+R37 -> -2147361.5 | U37: ='UK P&L'!AU38 -> -1517601.2 | V37: 0 | W37: =U37+V37 -> -1517601.2 | X37: ='CE P&L'!AU38 -> -673347.58 | Y37: 0 | Z37: =X37+Y37 -> -673347.58 | AA37: ='EE P&L'!AU38 -> -1340817.1 | AB37: 0 | AC37: =AA37+AB37 -> -1340817.1 | AD37: ='ROW P&L'!AU39 -> 0 | AE37: 0 | AF37: =AD37+AE37 -> 0 | AG37: ='Non Rev P&L'!AU20 -> 0 | AH37: 0 | AI37: =AG37+AH37 -> 0 | AJ37: =U37+X37+AA37+AD37+AG37 -> -3531765.9 | AK37: 0 | AL37: =AJ37+AK37 -> -3531765.9
A38: B2B Fulfilment | B38: ='UK P&L'!AF39 -> -217872.6 | C38: 0 | D38: =B38+C38 -> -217872.6 | E38: ='CE P&L'!AF39 -> -125712.74 | F38: 0 | G38: =E38+F38 -> -125712.74 | H38: ='EE P&L'!AF39 -> -49040.83 | I38: 0 | J38: =H38+I38 -> -49040.83 | K38: ='ROW P&L'!AF40 -> 0 | L38: 0 | M38: =K38+L38 -> 0 | N38: ='Non Rev P&L'!AF21 -> 0 | O38: 0 | P38: =N38+O38 -> 0 | Q38: =B38+E38+H38+K38+N38 -> -392626.17 | R38: 0 | S38: =Q38+R38 -> -392626.17 | U38: ='UK P&L'!AU39 -> -259233.47 | V38: 0 | W38: =U38+V38 -> -259233.47 | X38: ='CE P&L'!AU39 -> -180710.21 | Y38: 0 | Z38: =X38+Y38 -> -180710.21 | AA38: ='EE P&L'!AU39 -> -55524.871 | AB38: 0 | AC38: =AA38+AB38 -> -55524.871 | AD38: ='ROW P&L'!AU40 -> -110065.2 | AE38: 0 | AF38: =AD38+AE38 -> -110065.2 | AG38: ='Non Rev P&L'!AU21 -> 0 | AH38: 0 | AI38: =AG38+AH38 -> 0 | AJ38: =U38+X38+AA38+AD38+AG38 -> -605533.76 | AK38: 0 | AL38: =AJ38+AK38 -> -605533.76
A39: Marketplace Fulfilment | B39: ='UK P&L'!AF40 -> -955288.1 | C39: 0 | D39: =B39+C39 -> -955288.1 | E39: ='CE P&L'!AF40 -> -360868.49 | F39: 0 | G39: =E39+F39 -> -360868.49 | H39: ='EE P&L'!AF40 -> 0 | I39: 0 | J39: =H39+I39 -> 0 | K39: ='ROW P&L'!AF41 -> -54308.467 | L39: 0 | M39: =K39+L39 -> -54308.467 | N39: ='Non Rev P&L'!AF22 -> 0 | O39: 0 | P39: =N39+O39 -> 0 | Q39: =B39+E39+H39+K39+N39 -> -1370465.1 | R39: 0 | S39: =Q39+R39 -> -1370465.1 | U39: ='UK P&L'!AU40 -> -964840.99 | V39: 0 | W39: =U39+V39 -> -964840.99 | X39: ='CE P&L'!AU40 -> -436986.47 | Y39: 0 | Z39: =X39+Y39 -> -436986.47 | AA39: ='EE P&L'!AU40 -> 0 | AB39: 0 | AC39: =AA39+AB39 -> 0 | AD39: ='ROW P&L'!AU41 -> -54308.467 | AE39: 0 | AF39: =AD39+AE39 -> -54308.467 | AG39: ='Non Rev P&L'!AU22 -> 0 | AH39: 0 | AI39: =AG39+AH39 -> 0 | AJ39: =U39+X39+AA39+AD39+AG39 -> -1456135.9 | AK39: 0 | AL39: =AJ39+AK39 -> -1456135.9
A40: TikTok Fulfilment | B40: ='UK P&L'!AF41 -> 0 | C40: 0 | D40: =B40+C40 -> 0 | E40: ='CE P&L'!AF41 -> 0 | F40: 0 | G40: =E40+F40 -> 0 | H40: ='EE P&L'!AF41 -> 0 | I40: 0 | J40: =H40+I40 -> 0 | K40: ='ROW P&L'!AF42 -> 0 | L40: 0 | M40: =K40+L40 -> 0 | N40: ='Non Rev P&L'!AF23 -> 0 | O40: 0 | P40: =N40+O40 -> 0 | Q40: =B40+E40+H40+K40+N40 -> 0 | R40: 0 | S40: =Q40+R40 -> 0 | U40: ='UK P&L'!AU41 -> 0 | V40: 0 | W40: =U40+V40 -> 0 | X40: ='CE P&L'!AU41 -> 0 | Y40: 0 | Z40: =X40+Y40 -> 0 | AA40: ='EE P&L'!AU41 -> 0 | AB40: 0 | AC40: =AA40+AB40 -> 0 | AD40: ='ROW P&L'!AU42 -> 0 | AE40: 0 | AF40: =AD40+AE40 -> 0 | AG40: ='Non Rev P&L'!AU23 -> 0 | AH40: 0 | AI40: =AG40+AH40 -> 0 | AJ40: =U40+X40+AA40+AD40+AG40 -> 0 | AK40: 0 | AL40: =AJ40+AK40 -> 0
A42: Total Fulfilment | B42: ='UK P&L'!AF43 -> -1834151.7 | C42: =SUM(C36:C40) -> 0 | D42: =B42+C42 -> -1834151.7 | E42: ='CE P&L'!AF43 -> -808675.65 | F42: =SUM(F36:F40) -> 75000 | G42: =E42+F42 -> -733675.65 | H42: ='EE P&L'!AF43 -> -1213317 | I42: =SUM(I36:I40) -> 0 | J42: =H42+I42 -> -1213317 | K42: ='ROW P&L'!AF44 -> -54308.467 | L42: =SUM(L36:L40) -> 0 | M42: =K42+L42 -> -54308.467 | N42: ='Non Rev P&L'!AF24 -> -300000 | O42: =SUM(O36:O40) -> 0 | P42: =N42+O42 -> -300000 | Q42: =B42+E42+H42+K42+N42 -> -4210452.7 | R42: =SUM(R36:R40) -> 30000 | S42: =Q42+R42 -> -4180452.7 | U42: ='UK P&L'!AU43 -> -2741675.7 | V42: =SUM(V36:V40) -> 0 | W42: =U42+V42 -> -2741675.7 | X42: ='CE P&L'!AU43 -> -1291044.3 | Y42: =SUM(Y36:Y40) -> 0 | Z42: =X42+Y42 -> -1291044.3 | AA42: ='EE P&L'!AU43 -> -1396342 | AB42: =SUM(AB36:AB40) -> 0 | AC42: =AA42+AB42 -> -1396342 | AD42: ='ROW P&L'!AU44 -> -164373.67 | AE42: =SUM(AE36:AE40) -> 0 | AF42: =AD42+AE42 -> -164373.67 | AG42: ='Non Rev P&L'!AU24 -> -300000 | AH42: =SUM(AH36:AH40) -> 0 | AI42: =AG42+AH42 -> -300000 | AJ42: =U42+X42+AA42+AD42+AG42 -> -5893435.6 | AK42: =SUM(AK36:AK40) -> 0 | AL42: =AJ42+AK42 -> -5893435.6
A44: DTC CM2 | B44: ='UK P&L'!AF45 -> 3161017.8 | E44: ='UK P&L'!AI45 -> 459822.22 | H44: ='UK P&L'!AL45 -> 553872.9 | K44: ='UK P&L'!AO45 -> 647283.3 | N44: ='UK P&L'!AR45 -> 753174.32 | Q44: ='UK P&L'!AU45 -> 7368611.8 | U44: ='UK P&L'!AY45 -> 0 | X44: ='UK P&L'!BB45 -> 0 | AA44: ='UK P&L'!BE45 -> 0 | AD44: ='UK P&L'!BH45 -> 0 | AG44: ='UK P&L'!BK45 -> 0 | AJ44: ='UK P&L'!BN45 -> 0
A45: B2B CM2 | B45: ='UK P&L'!AF46 -> 2893976.9 | E45: ='UK P&L'!AI46 -> 209326.67 | H45: ='UK P&L'!AL46 -> 243656.88 | K45: ='UK P&L'!AO46 -> 675996.23 | N45: ='UK P&L'!AR46 -> 274836.79 | Q45: ='UK P&L'!AU46 -> 3443368.7 | U45: ='UK P&L'!AY46 -> 0 | X45: ='UK P&L'!BB46 -> 0 | AA45: ='UK P&L'!BE46 -> 0 | AD45: ='UK P&L'!BH46 -> 0 | AG45: ='UK P&L'!BK46 -> 0 | AJ45: ='UK P&L'!BN46 -> 0
A46: Marketplace CM2 | B46: ='UK P&L'!AF47 -> 968483.37 | E46: ='UK P&L'!AI47 -> 79046.885 | H46: ='UK P&L'!AL47 -> 75269.092 | K46: ='UK P&L'!AO47 -> 80857.686 | N46: ='UK P&L'!AR47 -> 96169.611 | Q46: ='UK P&L'!AU47 -> 978168.2 | U46: ='UK P&L'!AY47 -> 0 | X46: ='UK P&L'!BB47 -> 0 | AA46: ='UK P&L'!BE47 -> 0 | AD46: ='UK P&L'!BH47 -> 0 | AG46: ='UK P&L'!BK47 -> 0 | AJ46: ='UK P&L'!BN47 -> 0
A47: TikTok CM2 | B47: ='UK P&L'!AF48 -> 0 | E47: ='UK P&L'!AI48 -> 0 | H47: ='UK P&L'!AL48 -> 0 | K47: ='UK P&L'!AO48 -> 0 | N47: ='UK P&L'!AR48 -> 0 | Q47: ='UK P&L'!AU48 -> 0 | U47: ='UK P&L'!AY48 -> 0 | X47: ='UK P&L'!BB48 -> 0 | AA47: ='UK P&L'!BE48 -> 0 | AD47: ='UK P&L'!BH48 -> 0 | AG47: ='UK P&L'!BK48 -> 0 | AJ47: ='UK P&L'!BN48 -> 0
A48: Total CM2 | B48: ='UK P&L'!AF49 -> 7023478.1 | E48: ='UK P&L'!AI49 -> 748195.78 | H48: ='UK P&L'!AL49 -> 872798.88 | K48: ='UK P&L'!AO49 -> 1404137.2 | N48: ='UK P&L'!AR49 -> 1124180.7 | Q48: ='UK P&L'!AU49 -> 11790149 | U48: ='UK P&L'!AY49 -> 0 | X48: ='UK P&L'!BB49 -> 0 | AA48: ='UK P&L'!BE49 -> 0 | AD48: ='UK P&L'!BH49 -> 0 | AG48: ='UK P&L'!BK49 -> 0 | AJ48: ='UK P&L'!BN49 -> 0
A50: DTC CM2% | B50: ='UK P&L'!AF51 -> 0.65337476 | E50: ='UK P&L'!AI51 -> 0.66337476 | H50: ='UK P&L'!AL51 -> 0.66337476 | K50: ='UK P&L'!AO51 -> 0.66337476 | N50: ='UK P&L'!AR51 -> 0.66337476 | Q50: ='UK P&L'!AU51 -> 0.66337476 | U50: ='UK P&L'!AY51 -> 0 | X50: ='UK P&L'!BB51 -> 0 | AA50: ='UK P&L'!BE51 -> 0 | AD50: ='UK P&L'!BH51 -> 0 | AG50: ='UK P&L'!BK51 -> 0 | AJ50: ='UK P&L'!BN51 -> 0
A51: B2B CM2% | B51: ='UK P&L'!AF52 -> 0.69265368 | E51: ='UK P&L'!AI52 -> 0.69265368 | H51: ='UK P&L'!AL52 -> 0.69265368 | K51: ='UK P&L'!AO52 -> 0.69265368 | N51: ='UK P&L'!AR52 -> 0.69265368 | Q51: ='UK P&L'!AU52 -> 0.69265368 | U51: ='UK P&L'!AY52 -> 0 | X51: ='UK P&L'!BB52 -> 0 | AA51: ='UK P&L'!BE52 -> 0 | AD51: ='UK P&L'!BH52 -> 0 | AG51: ='UK P&L'!BK52 -> 0 | AJ51: ='UK P&L'!BN52 -> 0
A52: Marketplace CM2% | B52: ='UK P&L'!AF53 -> 0.41281221 | E52: ='UK P&L'!AI53 -> 0.41281221 | H52: ='UK P&L'!AL53 -> 0.41281221 | K52: ='UK P&L'!AO53 -> 0.41281221 | N52: ='UK P&L'!AR53 -> 0.41281221 | Q52: ='UK P&L'!AU53 -> 0.41281221 | U52: ='UK P&L'!AY53 -> 0 | X52: ='UK P&L'!BB53 -> 0 | AA52: ='UK P&L'!BE53 -> 0 | AD52: ='UK P&L'!BH53 -> 0 | AG52: ='UK P&L'!BK53 -> 0 | AJ52: ='UK P&L'!BN53 -> 0
A53: TikTok CM2% | B53: ='UK P&L'!AF54 -> 0 | E53: ='UK P&L'!AI54 -> 0 | H53: ='UK P&L'!AL54 -> 0 | K53: ='UK P&L'!AO54 -> 0 | N53: ='UK P&L'!AR54 -> 0 | Q53: ='UK P&L'!AU54 -> 0 | U53: ='UK P&L'!AY54 -> 0 | X53: ='UK P&L'!BB54 -> 0 | AA53: ='UK P&L'!BE54 -> 0 | AD53: ='UK P&L'!BH54 -> 0 | AG53: ='UK P&L'!BK54 -> 0 | AJ53: ='UK P&L'!BN54 -> 0
A54: Total CM2% | B54: ='UK P&L'!AF55 -> 0.61814696 | E54: ='UK P&L'!AI55 -> 0.63040486 | H54: ='UK P&L'!AL55 -> 0.63752729 | K54: ='UK P&L'!AO55 -> 0.65382767 | N54: ='UK P&L'!AR55 -> 0.63688698 | Q54: ='UK P&L'!AU55 -> 0.63908233 | U54: ='UK P&L'!AY55 -> 0 | X54: ='UK P&L'!BB55 -> 0 | AA54: ='UK P&L'!BE55 -> 0 | AD54: ='UK P&L'!BH55 -> 0 | AG54: ='UK P&L'!BK55 -> 0 | AJ54: ='UK P&L'!BN55 -> 0
A56: Marketing
A58: D2C Model Marketing | B58: ='UK P&L'!AF59 -> -1983035.5 | C58: 0 | D58: =B58+C58 -> -1983035.5 | E58: ='CE P&L'!AF59 -> -454126.8 | F58: 0 | G58: =E58+F58 -> -454126.8 | H58: ='EE P&L'!AF59 -> -1668508.6 | I58: 0 | J58: =H58+I58 -> -1668508.6 | K58: ='ROW P&L'!AF60 -> 0 | L58: 0 | M58: =K58+L58 -> 0 | N58: ='Non Rev P&L'!AF31 -> 0 | O58: 0 | P58: =N58+O58 -> 0 | Q58: =B58+E58+H58+K58+N58 -> -4105670.9 | R58: 0 | S58: =Q58+R58 -> -4105670.9 | U58: ='UK P&L'!AU59 -> -3631417.9 | V58: 0 | W58: =U58+V58 -> -3631417.9 | X58: ='CE P&L'!AU59 -> -894498 | Y58: 0 | Z58: =X58+Y58 -> -894498 | AA58: ='EE P&L'!AU59 -> -2010460.3 | AB58: 0 | AC58: =AA58+AB58 -> -2010460.3 | AD58: ='ROW P&L'!AU60 -> 0 | AE58: 0 | AF58: =AD58+AE58 -> 0 | AG58: ='Non Rev P&L'!AU31 -> 0 | AH58: 0 | AI58: =AG58+AH58 -> 0 | AJ58: =U58+X58+AA58+AD58+AG58 -> -6536376.2 | AK58: 0 | AL58: =AJ58+AK58 -> -6536376.2
A59: D2C Model Brand | B59: ='UK P&L'!AF60 -> -300000 | C59: 0 | D59: =B59+C59 -> -300000 | E59: ='CE P&L'!AF60 -> -97500 | F59: 0 | G59: =E59+F59 -> -97500 | H59: ='EE P&L'!AF60 -> -65000 | I59: 0 | J59: =H59+I59 -> -65000 | K59: ='ROW P&L'!AF61 -> 0 | L59: 0 | M59: =K59+L59 -> 0 | N59: ='Non Rev P&L'!AF32 -> 0 | O59: 0 | P59: =N59+O59 -> 0 | Q59: =B59+E59+H59+K59+N59 -> -462500 | S59: =Q59+R59 -> -462500 | U59: ='UK P&L'!AU60 -> -300000 | V59: 0 | W59: =U59+V59 -> -300000 | X59: ='CE P&L'!AU60 -> -50000 | Y59: 0 | Z59: =X59+Y59 -> -50000 | AA59: ='EE P&L'!AU60 -> -47500 | AB59: 0 | AC59: =AA59+AB59 -> -47500 | AD59: ='ROW P&L'!AU61 -> 0 | AE59: 0 | AF59: =AD59+AE59 -> 0 | AG59: ='Non Rev P&L'!AU32 -> 0 | AH59: 0 | AI59: =AG59+AH59 -> 0 | AJ59: =U59+X59+AA59+AD59+AG59 -> -397500 | AK59: 0 | AL59: =AJ59+AK59 -> -397500
A60: Influencers | B60: ='UK P&L'!AF61 -> 0 | C60: 0 | D60: =B60+C60 -> 0 | E60: ='CE P&L'!AF61 -> 0 | F60: 0 | G60: =E60+F60 -> 0 | H60: ='EE P&L'!AF61 -> 0 | I60: 0 | J60: =H60+I60 -> 0 | K60: ='ROW P&L'!AF62 -> 0 | L60: 0 | M60: =K60+L60 -> 0 | N60: ='Non Rev P&L'!AF33 -> 0 | O60: 0 | P60: =N60+O60 -> 0 | Q60: =B60+E60+H60+K60+N60 -> 0 | R60: 0 | S60: =Q60+R60 -> 0 | U60: ='UK P&L'!AU61 -> 0 | V60: 0 | W60: =U60+V60 -> 0 | X60: ='CE P&L'!AU61 -> 0 | Y60: 0 | Z60: =X60+Y60 -> 0 | AA60: ='EE P&L'!AU61 -> 0 | AB60: 0 | AC60: =AA60+AB60 -> 0 | AD60: ='ROW P&L'!AU62 -> 0 | AE60: 0 | AF60: =AD60+AE60 -> 0 | AG60: ='Non Rev P&L'!AU33 -> 0 | AH60: 0 | AI60: =AG60+AH60 -> 0 | AJ60: =U60+X60+AA60+AD60+AG60 -> 0 | AK60: 0 | AL60: =AJ60+AK60 -> 0
A61: PPC | B61: ='UK P&L'!AF62 -> 0 | C61: 0 | D61: =B61+C61 -> 0 | E61: ='CE P&L'!AF62 -> 0 | F61: 0 | G61: =E61+F61 -> 0 | H61: ='EE P&L'!AF62 -> 0 | I61: 0 | J61: =H61+I61 -> 0 | K61: ='ROW P&L'!AF63 -> 0 | L61: 0 | M61: =K61+L61 -> 0 | N61: ='Non Rev P&L'!AF34 -> 0 | O61: 0 | P61: =N61+O61 -> 0 | Q61: =B61+E61+H61+K61+N61 -> 0 | R61: 0 | S61: =Q61+R61 -> 0 | U61: ='UK P&L'!AU62 -> 0 | V61: 0 | W61: =U61+V61 -> 0 | X61: ='CE P&L'!AU62 -> 0 | Y61: 0 | Z61: =X61+Y61 -> 0 | AA61: ='EE P&L'!AU62 -> 0 | AB61: 0 | AC61: =AA61+AB61 -> 0 | AD61: ='ROW P&L'!AU63 -> 0 | AE61: 0 | AF61: =AD61+AE61 -> 0 | AG61: ='Non Rev P&L'!AU34 -> 0 | AH61: 0 | AI61: =AG61+AH61 -> 0 | AJ61: =U61+X61+AA61+AD61+AG61 -> 0 | AK61: 0 | AL61: =AJ61+AK61 -> 0
A62: Paid Social | B62: ='UK P&L'!AF63 -> 0 | C62: 0 | D62: =B62+C62 -> 0 | E62: ='CE P&L'!AF63 -> 0 | F62: 0 | G62: =E62+F62 -> 0 | H62: ='EE P&L'!AF63 -> 0 | I62: 0 | J62: =H62+I62 -> 0 | K62: ='ROW P&L'!AF64 -> 0 | L62: 0 | M62: =K62+L62 -> 0 | N62: ='Non Rev P&L'!AF35 -> 0 | O62: 0 | P62: =N62+O62 -> 0 | Q62: =B62+E62+H62+K62+N62 -> 0 | R62: 0 | S62: =Q62+R62 -> 0 | U62: ='UK P&L'!AU63 -> 0 | V62: 0 | W62: =U62+V62 -> 0 | X62: ='CE P&L'!AU63 -> 0 | Y62: 0 | Z62: =X62+Y62 -> 0 | AA62: ='EE P&L'!AU63 -> 0 | AB62: 0 | AC62: =AA62+AB62 -> 0 | AD62: ='ROW P&L'!AU64 -> 0 | AE62: 0 | AF62: =AD62+AE62 -> 0 | AG62: ='Non Rev P&L'!AU35 -> 0 | AH62: 0 | AI62: =AG62+AH62 -> 0 | AJ62: =U62+X62+AA62+AD62+AG62 -> 0 | AK62: 0 | AL62: =AJ62+AK62 -> 0
A63: Retail Partnerships | B63: ='UK P&L'!AF64 -> -418980.69 | C63: 0 | D63: =B63+C63 -> -418980.69 | E63: ='CE P&L'!AF64 -> -106918.74 | F63: 0 | G63: =E63+F63 -> -106918.74 | H63: ='EE P&L'!AF64 -> -22359.666 | I63: 0 | J63: =H63+I63 -> -22359.666 | K63: ='ROW P&L'!AF65 -> 0 | L63: 0 | M63: =K63+L63 -> 0 | N63: ='Non Rev P&L'!AF36 -> 0 | O63: 0 | P63: =N63+O63 -> 0 | Q63: =B63+E63+H63+K63+N63 -> -548259.09 | R63: 0 | S63: =Q63+R63 -> -548259.09 | U63: ='UK P&L'!AU64 -> -609545.44 | V63: 0 | W63: =U63+V63 -> -609545.44 | X63: ='CE P&L'!AU64 -> -170209.31 | Y63: 0 | Z63: =X63+Y63 -> -170209.31 | AA63: ='EE P&L'!AU64 -> -17450.65 | AB63: 0 | AC63: =AA63+AB63 -> -17450.65 | AD63: ='ROW P&L'!AU65 -> 0 | AE63: 0 | AF63: =AD63+AE63 -> 0 | AG63: ='Non Rev P&L'!AU36 -> 0 | AH63: 0 | AI63: =AG63+AH63 -> 0 | AJ63: =U63+X63+AA63+AD63+AG63 -> -797205.4 | AK63: 0 | AL63: =AJ63+AK63 -> -797205.4
A64: Retros | B64: ='UK P&L'!AF65 -> -1202967.7 | C64: 0 | D64: =B64+C64 -> -1202967.7 | E64: ='CE P&L'!AF65 -> -71789.991 | F64: 0 | G64: =E64+F64 -> -71789.991 | H64: ='EE P&L'!AF65 -> -22359.666 | I64: 0 | J64: =H64+I64 -> -22359.666 | K64: ='ROW P&L'!AF66 -> 0 | L64: 0 | M64: =K64+L64 -> 0 | N64: ='Non Rev P&L'!AF37 -> 0 | O64: 0 | P64: =N64+O64 -> 0 | Q64: =B64+E64+H64+K64+N64 -> -1297117.4 | R64: 0 | S64: =Q64+R64 -> -1297117.4 | U64: ='UK P&L'!AU65 -> -1140003.7 | V64: 0 | W64: =U64+V64 -> -1140003.7 | X64: ='CE P&L'!AU65 -> -100217.43 | Y64: 0 | Z64: =X64+Y64 -> -100217.43 | AA64: ='EE P&L'!AU65 -> -15873.2 | AB64: 0 | AC64: =AA64+AB64 -> -15873.2 | AD64: ='ROW P&L'!AU66 -> 0 | AE64: 0 | AF64: =AD64+AE64 -> 0 | AG64: ='Non Rev P&L'!AU37 -> 0 | AH64: 0 | AI64: =AG64+AH64 -> 0 | AJ64: =U64+X64+AA64+AD64+AG64 -> -1256094.3 | AK64: 0 | AL64: =AJ64+AK64 -> -1256094.3
A65: Trade Shows | B65: ='UK P&L'!AF67 -> 0 | C65: 0 | D65: =B65+C65 -> 0 | E65: ='CE P&L'!AF67 -> -39500 | F65: 0 | G65: =E65+F65 -> -39500 | H65: ='EE P&L'!AF67 -> 0 | I65: 0 | J65: =H65+I65 -> 0 | K65: ='ROW P&L'!AF68 -> -15000 | L65: 0 | M65: =K65+L65 -> -15000 | N65: ='Non Rev P&L'!AF38 -> 0 | O65: 0 | P65: =N65+O65 -> 0 | Q65: =B65+E65+H65+K65+N65 -> -54500 | R65: 0 | S65: =Q65+R65 -> -54500 | U65: ='UK P&L'!AU67 -> 0 | V65: 0 | W65: =U65+V65 -> 0 | X65: ='CE P&L'!AU67 -> -39500 | Y65: 0 | Z65: =X65+Y65 -> -39500 | AA65: ='EE P&L'!AU67 -> 0 | AB65: 0 | AC65: =AA65+AB65 -> 0 | AD65: ='ROW P&L'!AU68 -> -15000 | AE65: 0 | AF65: =AD65+AE65 -> -15000 | AG65: ='Non Rev P&L'!AU38 -> 0 | AH65: 0 | AI65: =AG65+AH65 -> 0 | AJ65: =U65+X65+AA65+AD65+AG65 -> -54500 | AK65: 0 | AL65: =AJ65+AK65 -> -54500
A66: Marketplace Marketing | B66: ='UK P&L'!AF68 -> -539594.44 | C66: 0 | D66: =B66+C66 -> -539594.44 | E66: ='CE P&L'!AF68 -> -262885.97 | F66: 0 | G66: =E66+F66 -> -262885.97 | H66: ='EE P&L'!AF68 -> 0 | I66: 0 | J66: =H66+I66 -> 0 | K66: ='ROW P&L'!AF69 -> -10852.122 | L66: 0 | M66: =K66+L66 -> -10852.122 | N66: ='Non Rev P&L'!AF39 -> 0 | O66: 0 | P66: =N66+O66 -> 0 | Q66: =B66+E66+H66+K66+N66 -> -813332.52 | R66: 0 | S66: =Q66+R66 -> -813332.52 | U66: ='UK P&L'!AU68 -> -523615.8 | V66: 0 | W66: =U66+V66 -> -523615.8 | X66: ='CE P&L'!AU68 -> -261124 | Y66: 0 | Z66: =X66+Y66 -> -261124 | AA66: ='EE P&L'!AU68 -> 0 | AB66: 0 | AC66: =AA66+AB66 -> 0 | AD66: ='ROW P&L'!AU69 -> -14790.781 | AE66: 0 | AF66: =AD66+AE66 -> -14790.781 | AG66: ='Non Rev P&L'!AU39 -> 0 | AH66: 0 | AI66: =AG66+AH66 -> 0 | AJ66: =U66+X66+AA66+AD66+AG66 -> -799530.58 | AK66: 0 | AL66: =AJ66+AK66 -> -799530.58
A67: TikTok Marketing | B67: ='UK P&L'!AF69 -> 0 | C67: 0 | D67: =B67+C67 -> 0 | E67: ='CE P&L'!AF69 -> 0 | F67: 0 | G67: =E67+F67 -> 0 | H67: ='EE P&L'!AF69 -> 0 | I67: 0 | J67: =H67+I67 -> 0 | K67: ='ROW P&L'!AF70 -> 0 | L67: 0 | M67: =K67+L67 -> 0 | N67: ='Non Rev P&L'!AF40 -> 0 | O67: 0 | P67: =N67+O67 -> 0 | Q67: =B67+E67+H67+K67+N67 -> 0 | R67: 0 | S67: =Q67+R67 -> 0 | U67: ='UK P&L'!AU69 -> 0 | V67: 0 | W67: =U67+V67 -> 0 | X67: ='CE P&L'!AU69 -> 0 | Y67: 0 | Z67: =X67+Y67 -> 0 | AA67: ='EE P&L'!AU69 -> 0 | AB67: 0 | AC67: =AA67+AB67 -> 0 | AD67: ='ROW P&L'!AU70 -> 0 | AE67: 0 | AF67: =AD67+AE67 -> 0 | AG67: ='Non Rev P&L'!AU40 -> 0 | AH67: 0 | AI67: =AG67+AH67 -> 0 | AJ67: =U67+X67+AA67+AD67+AG67 -> 0 | AK67: 0 | AL67: =AJ67+AK67 -> 0
A69: Total Marketing | B69: ='UK P&L'!AF71 -> -4447853.3 | C69: =SUM(C58:C67) -> 0 | D69: =B69+C69 -> -4447853.3 | E69: ='CE P&L'!AF71 -> -1104924 | F69: =SUM(F58:F67) -> 0 | G69: =E69+F69 -> -1104924 | H69: ='EE P&L'!AF71 -> -1811630.5 | I69: =SUM(I58:I67) -> 0 | J69: =H69+I69 -> -1811630.5 | K69: ='ROW P&L'!AF72 -> -62540.993 | L69: =SUM(L58:L67) -> 0 | M69: =K69+L69 -> -62540.993 | N69: ='Non Rev P&L'!AF42 -> 0 | O69: =SUM(O58:O67) -> 0 | P69: =N69+O69 -> 0 | Q69: =B69+E69+H69+K69+N69 -> -7426948.8 | R69: =SUM(R58:R67) -> 0 | S69: =Q69+R69 -> -7426948.8 | U69: ='UK P&L'!AU71 -> -6414989.1 | V69: =SUM(V58:V67) -> 0 | W69: =U69+V69 -> -6414989.1 | X69: ='CE P&L'!AU71 -> -1584146.5 | Y69: =SUM(Y58:Y67) -> 0 | Z69: =X69+Y69 -> -1584146.5 | AA69: ='EE P&L'!AU71 -> -2126356.8 | AB69: =SUM(AB58:AB67) -> 0 | AC69: =AA69+AB69 -> -2126356.8 | AD69: ='ROW P&L'!AU72 -> -55792.912 | AE69: =SUM(AE58:AE67) -> 0 | AF69: =AD69+AE69 -> -55792.912 | AG69: ='Non Rev P&L'!AU42 -> 0 | AH69: =SUM(AH58:AH67) -> 0 | AI69: =AG69+AH69 -> 0 | AJ69: =U69+X69+AA69+AD69+AG69 -> -10181285 | AK69: =SUM(AK58:AK67) -> 0 | AL69: =AJ69+AK69 -> -10181285
A71: DTC CM3
A72: B2B CM3
A73: Marketplace CM3
A74: TikTok CM3
A75: Total CM3
A77: DTC CM3%
A78: B2B CM3%
A79: Marketplace CM3%
A80: TikTok CM3%
A81: Total CM3%
A85: Other Overheads
A87: Staff Costs | B87: ='UK P&L'!AF89 -> 0 | C87: 0 | D87: =B87+C87 -> 0 | E87: ='CE P&L'!AF89 -> -82204.894 | F87: 0 | G87: =E87+F87 -> -82204.894 | H87: ='EE P&L'!AF89 -> -237812.42 | I87: 0 | J87: =H87+I87 -> -237812.42 | K87: ='ROW P&L'!AF90 -> 0 | L87: 0 | M87: =K87+L87 -> 0 | N87: ='Non Rev P&L'!AF52 -> -2788763.7 | O87: 0 | P87: =N87+O87 -> -2788763.7 | Q87: =B87+E87+H87+K87+N87 -> -3108781 | S87: =Q87+R87 -> -3108781 | U87: ='UK P&L'!AU89 -> 0 | V87: 0 | W87: =U87+V87 -> 0 | X87: ='CE P&L'!AU89 -> -156792.39 | Y87: 0 | Z87: =X87+Y87 -> -156792.39 | AA87: ='EE P&L'!AU89 -> -243662.42 | AB87: 0 | AC87: =AA87+AB87 -> -243662.42 | AD87: ='ROW P&L'!AU88 -> 0 | AE87: 0 | AF87: =AD87+AE87 -> 0 | AG87: ='Non Rev P&L'!AU52 -> -2765812.5 | AH87: 0 | AI87: =AG87+AH87 -> -2765812.5 | AJ87: =U87+X87+AA87+AD87+AG87 -> -3166267.3 | AK87: 0 | AL87: =AJ87+AK87 -> -3166267.3
A88: Freelancers | B88: ='UK P&L'!AF90 -> -9000 | C88: 0 | D88: =B88+C88 -> -9000 | E88: ='CE P&L'!AF90 -> 0 | F88: 0 | G88: =E88+F88 -> 0 | H88: ='EE P&L'!AF90 -> -214056.69 | I88: 0 | J88: =H88+I88 -> -214056.69 | K88: ='ROW P&L'!AF91 -> 0 | L88: 0 | M88: =K88+L88 -> 0 | N88: ='Non Rev P&L'!AF53 -> -186421.95 | O88: 0 | P88: =N88+O88 -> -186421.95 | Q88: =B88+E88+H88+K88+N88 -> -409478.64 | R88: 0 | S88: =Q88+R88 -> -409478.64 | U88: ='UK P&L'!AU90 -> -9000 | V88: 0 | W88: =U88+V88 -> -9000 | X88: ='CE P&L'!AU90 -> 0 | Y88: 0 | Z88: =X88+Y88 -> 0 | AA88: ='EE P&L'!AU90 -> -214056.69 | AB88: 0 | AC88: =AA88+AB88 -> -214056.69 | AD88: ='ROW P&L'!AU89 -> 0 | AE88: 0 | AF88: =AD88+AE88 -> 0 | AG88: ='Non Rev P&L'!AU53 -> -175489.75 | AH88: 0 | AI88: =AG88+AH88 -> -175489.75 | AJ88: =U88+X88+AA88+AD88+AG88 -> -398546.44 | AK88: 0 | AL88: =AJ88+AK88 -> -398546.44
A89: Consultancy | B89: ='UK P&L'!AF91 -> 0 | C89: 0 | D89: =B89+C89 -> 0 | E89: ='CE P&L'!AF91 -> 0 | F89: 0 | G89: =E89+F89 -> 0 | H89: ='EE P&L'!AF91 -> 0 | I89: 0 | J89: =H89+I89 -> 0 | K89: ='ROW P&L'!AF92 -> 0 | L89: 0 | M89: =K89+L89 -> 0 | N89: ='Non Rev P&L'!AF54 -> 0 | O89: 0 | P89: =N89+O89 -> 0 | Q89: =B89+E89+H89+K89+N89 -> 0 | R89: 0 | S89: =Q89+R89 -> 0 | U89: ='UK P&L'!AU91 -> 0 | V89: 0 | W89: =U89+V89 -> 0 | X89: ='CE P&L'!AU91 -> 0 | Y89: 0 | Z89: =X89+Y89 -> 0 | AA89: ='EE P&L'!AU91 -> 0 | AB89: 0 | AC89: =AA89+AB89 -> 0 | AD89: ='ROW P&L'!AU90 -> 0 | AE89: 0 | AF89: =AD89+AE89 -> 0 | AG89: ='Non Rev P&L'!AU54 -> 0 | AH89: 0 | AI89: =AG89+AH89 -> 0 | AJ89: =U89+X89+AA89+AD89+AG89 -> 0 | AK89: 0 | AL89: =AJ89+AK89 -> 0
A90: Software | B90: ='UK P&L'!AF92 -> 0 | C90: 0 | D90: =B90+C90 -> 0 | E90: ='CE P&L'!AF92 -> 0 | F90: 0 | G90: =E90+F90 -> 0 | H90: ='EE P&L'!AF92 -> 0 | I90: 0 | J90: =H90+I90 -> 0 | K90: ='ROW P&L'!AF93 -> 0 | L90: 0 | M90: =K90+L90 -> 0 | N90: ='Non Rev P&L'!AF55 -> 0 | O90: 0 | P90: =N90+O90 -> 0 | Q90: =B90+E90+H90+K90+N90 -> 0 | R90: 0 | S90: =Q90+R90 -> 0 | U90: ='UK P&L'!AU92 -> 0 | V90: 0 | W90: =U90+V90 -> 0 | X90: ='CE P&L'!AU92 -> 0 | Y90: 0 | Z90: =X90+Y90 -> 0 | AA90: ='EE P&L'!AU92 -> 0 | AB90: 0 | AC90: =AA90+AB90 -> 0 | AD90: ='ROW P&L'!AU91 -> 0 | AE90: 0 | AF90: =AD90+AE90 -> 0 | AG90: ='Non Rev P&L'!AU55 -> 0 | AH90: 0 | AI90: =AG90+AH90 -> 0 | AJ90: =U90+X90+AA90+AD90+AG90 -> 0 | AK90: 0 | AL90: =AJ90+AK90 -> 0
A91: Telephone & Computer | B91: ='UK P&L'!AF93 -> 0 | C91: 0 | D91: =B91+C91 -> 0 | E91: ='CE P&L'!AF93 -> 0 | F91: 0 | G91: =E91+F91 -> 0 | H91: ='EE P&L'!AF93 -> 0 | I91: 0 | J91: =H91+I91 -> 0 | K91: ='ROW P&L'!AF94 -> 0 | L91: 0 | M91: =K91+L91 -> 0 | N91: ='Non Rev P&L'!AF56 -> 0 | O91: 0 | P91: =N91+O91 -> 0 | Q91: =B91+E91+H91+K91+N91 -> 0 | R91: 0 | S91: =Q91+R91 -> 0 | U91: ='UK P&L'!AU93 -> 0 | V91: 0 | W91: =U91+V91 -> 0 | X91: ='CE P&L'!AU93 -> 0 | Y91: 0 | Z91: =X91+Y91 -> 0 | AA91: ='EE P&L'!AU93 -> 0 | AB91: 0 | AC91: =AA91+AB91 -> 0 | AD91: ='ROW P&L'!AU92 -> 0 | AE91: 0 | AF91: =AD91+AE91 -> 0 | AG91: ='Non Rev P&L'!AU56 -> 0 | AH91: 0 | AI91: =AG91+AH91 -> 0 | AJ91: =U91+X91+AA91+AD91+AG91 -> 0 | AK91: 0 | AL91: =AJ91+AK91 -> 0
A92: Insurance | B92: ='UK P&L'!AF94 -> 0 | C92: 0 | D92: =B92+C92 -> 0 | E92: ='CE P&L'!AF94 -> 0 | F92: 0 | G92: =E92+F92 -> 0 | H92: ='EE P&L'!AF94 -> 0 | I92: 0 | J92: =H92+I92 -> 0 | K92: ='ROW P&L'!AF95 -> 0 | L92: 0 | M92: =K92+L92 -> 0 | N92: ='Non Rev P&L'!AF57 -> 0 | O92: 0 | P92: =N92+O92 -> 0 | Q92: =B92+E92+H92+K92+N92 -> 0 | R92: 0 | S92: =Q92+R92 -> 0 | U92: ='UK P&L'!AU94 -> 0 | V92: 0 | W92: =U92+V92 -> 0 | X92: ='CE P&L'!AU94 -> 0 | Y92: 0 | Z92: =X92+Y92 -> 0 | AA92: ='EE P&L'!AU94 -> 0 | AB92: 0 | AC92: =AA92+AB92 -> 0 | AD92: ='ROW P&L'!AU93 -> 0 | AE92: 0 | AF92: =AD92+AE92 -> 0 | AG92: ='Non Rev P&L'!AU57 -> 0 | AH92: 0 | AI92: =AG92+AH92 -> 0 | AJ92: =U92+X92+AA92+AD92+AG92 -> 0 | AK92: 0 | AL92: =AJ92+AK92 -> 0
A93: Office Costs | B93: ='UK P&L'!AF95 -> 0 | C93: 0 | D93: =B93+C93 -> 0 | E93: ='CE P&L'!AF95 -> 0 | F93: 0 | G93: =E93+F93 -> 0 | H93: ='EE P&L'!AF95 -> 0 | I93: 0 | J93: =H93+I93 -> 0 | K93: 0 | L93: 0 | M93: =K93+L93 -> 0 | N93: ='Non Rev P&L'!AF58 -> 0 | O93: 0 | P93: =N93+O93 -> 0 | Q93: =B93+E93+H93+K93+N93 -> 0 | R93: 0 | S93: =Q93+R93 -> 0 | U93: ='UK P&L'!AU95 -> 0 | V93: 0 | W93: =U93+V93 -> 0 | X93: ='CE P&L'!AU95 -> 0 | Y93: 0 | Z93: =X93+Y93 -> 0 | AA93: ='EE P&L'!AU95 -> 0 | AB93: 0 | AC93: =AA93+AB93 -> 0 | AD93: ='ROW P&L'!AU94 -> 0 | AE93: 0 | AF93: =AD93+AE93 -> 0 | AG93: ='Non Rev P&L'!AU58 -> 0 | AH93: 0 | AI93: =AG93+AH93 -> 0 | AJ93: =U93+X93+AA93+AD93+AG93 -> 0 | AK93: 0 | AL93: =AJ93+AK93 -> 0
A94: Travel & Entertainment | B94: ='UK P&L'!AF96 -> 0 | C94: 0 | D94: =B94+C94 -> 0 | E94: ='CE P&L'!AF96 -> 0 | F94: 0 | G94: =E94+F94 -> 0 | H94: ='EE P&L'!AF96 -> 0 | I94: 0 | J94: =H94+I94 -> 0 | K94: ='ROW P&L'!AF97 -> 0 | L94: 0 | M94: =K94+L94 -> 0 | N94: ='Non Rev P&L'!AF59 -> 0 | O94: 0 | P94: =N94+O94 -> 0 | Q94: =B94+E94+H94+K94+N94 -> 0 | R94: 0 | S94: =Q94+R94 -> 0 | U94: ='UK P&L'!AU96 -> 0 | V94: 0 | W94: =U94+V94 -> 0 | X94: ='CE P&L'!AU96 -> 0 | Y94: 0 | Z94: =X94+Y94 -> 0 | AA94: ='EE P&L'!AU96 -> 0 | AB94: 0 | AC94: =AA94+AB94 -> 0 | AD94: ='ROW P&L'!AU95 -> 0 | AE94: 0 | AF94: =AD94+AE94 -> 0 | AG94: ='Non Rev P&L'!AU59 -> 0 | AH94: 0 | AI94: =AG94+AH94 -> 0 | AJ94: =U94+X94+AA94+AD94+AG94 -> 0 | AK94: 0 | AL94: =AJ94+AK94 -> 0
A95: Other Overheads | B95: ='UK P&L'!AF97 -> -659831.22 | C95: 0 | D95: =B95+C95 -> -659831.22 | E95: ='CE P&L'!AF97 -> -149358.87 | F95: 0 | G95: =E95+F95 -> -149358.87 | H95: ='EE P&L'!AF97 -> -422337.81 | I95: 0 | J95: =H95+I95 -> -422337.81 | K95: ='ROW P&L'!AF98 -> -92395.18 | L95: 0 | M95: =K95+L95 -> -92395.18 | N95: ='Non Rev P&L'!AF60 -> 0 | O95: 0 | P95: =N95+O95 -> 0 | Q95: =B95+E95+H95+K95+N95 -> -1323923.1 | R95: 0 | S95: =Q95+R95 -> -1323923.1 | U95: ='UK P&L'!AU97 -> -662720.8 | V95: 0 | W95: =U95+V95 -> -662720.8 | X95: ='CE P&L'!AU97 -> -198522.95 | Y95: 0 | Z95: =X95+Y95 -> -198522.95 | AA95: ='EE P&L'!AU97 -> -440058.25 | AB95: 0 | AC95: =AA95+AB95 -> -440058.25 | AD95: ='ROW P&L'!AU96 -> -149564.55 | AE95: 0 | AF95: =AD95+AE95 -> -149564.55 | AG95: ='Non Rev P&L'!AU60 -> 0 | AH95: 0 | AI95: =AG95+AH95 -> 0 | AJ95: =U95+X95+AA95+AD95+AG95 -> -1450866.5 | AK95: 0 | AL95: =AJ95+AK95 -> -1450866.5
K96: ='ROW P&L'!AF97 -> 0 | M96: =K96+L96 -> 0 | N96: ='Non Rev P&L'!AF61 -> 0 | P96: =N96+O96 -> 0 | AD96: ='ROW P&L'!AU97 -> 0 | AF96: =AD96+AE96 -> 0 | AG96: ='Non Rev P&L'!AU61 -> 0 | AI96: =AG96+AH96 -> 0
A97: Total Other Overheads | B97: ='UK P&L'!AF99 -> -668831.22 | C97: =SUM(C86:C95) -> 0 | D97: =B97+C97 -> -668831.22 | E97: ='CE P&L'!AF99 -> -231563.76 | F97: =SUM(F86:F95) -> 0 | G97: =E97+F97 -> -231563.76 | H97: ='EE P&L'!AF99 -> -874206.92 | I97: =SUM(I86:I95) -> 0 | J97: =H97+I97 -> -874206.92 | K97: ='ROW P&L'!AF98 -> -92395.18 | L97: =SUM(L86:L95) -> 0 | M97: =K97+L97 -> -92395.18 | N97: ='Non Rev P&L'!AF62 -> -2975185.6 | O97: =SUM(O86:O95) -> 0 | P97: =N97+O97 -> -2975185.6 | Q97: =B97+E97+H97+K97+N97 -> -4842182.7 | R97: =SUM(R86:R95) -> 0 | S97: =Q97+R97 -> -4842182.7 | U97: ='UK P&L'!AU99 -> -671720.8 | V97: =SUM(V86:V95) -> 0 | W97: =U97+V97 -> -671720.8 | X97: ='CE P&L'!AU99 -> -355315.34 | Y97: =SUM(Y86:Y95) -> 0 | Z97: =X97+Y97 -> -355315.34 | AA97: ='EE P&L'!AU99 -> -897777.36 | AB97: =SUM(AB86:AB95) -> 0 | AC97: =AA97+AB97 -> -897777.36 | AD97: ='ROW P&L'!AU98 -> -149564.55 | AE97: =SUM(AE86:AE95) -> 0 | AF97: =AD97+AE97 -> -149564.55 | AG97: ='Non Rev P&L'!AU62 -> -2941302.2 | AH97: =SUM(AH86:AH95) -> 0 | AI97: =AG97+AH97 -> -2941302.2 | AJ97: =U97+X97+AA97+AD97+AG97 -> -5015680.3 | AK97: =SUM(AK86:AK95) -> 0 | AL97: =AJ97+AK97 -> -5015680.3
A99: EBITDA | B99: ='UK P&L'!AF101 -> 1906793.6 | C99: =D99-B99 -> 0 | D99: =D11+D20+D42+D69+D97 -> 1906793.6 | E99: ='CE P&L'!AF101 -> 1029988.2 | F99: =G99-E99 -> 75000 | G99: =G11+G20+G42+G69+G97 -> 1104988.2 | H99: ='EE P&L'!AF101 -> 1168593 | I99: =J99-H99 -> 0 | J99: =J11+J20+J42+J69+J97 -> 1168593 | K99: ='ROW P&L'!AF100 -> 376118.38 | L99: =M99-K99 -> 0 | M99: =M11+M20+M42+M69+M97 -> 376118.38 | N99: ='Non Rev P&L'!AF64 -> -3275185.6 | O99: =P99-N99 -> 0 | P99: =P11+P20+P42+P69+P97 -> -3275185.6 | Q99: =B99+E99+H99+K99+N99 -> 1206307.5 | R99: =S99-Q99 -> 330000 | S99: =S11+S20+S42+S69+S97 -> 1536307.5 | U99: ='UK P&L'!AU101 -> 4703438.7 | V99: =W99-U99 -> 0 | W99: =W11+W20+W42+W69+W97 -> 4703438.7 | X99: ='CE P&L'!AU101 -> 2006104.1 | Y99: =Z99-X99 -> 0 | Z99: =Z11+Z20+Z42+Z69+Z97 -> 2006104.1 | AA99: ='EE P&L'!AU101 -> 1406180.6 | AB99: =AC99-AA99 -> 0 | AC99: =AC11+AC20+AC42+AC69+AC97 -> 1406180.6 | AD99: ='ROW P&L'!AU100 -> 232433.84 | AE99: =AF99-AD99 -> 0 | AF99: =AF11+AF20+AF42+AF69+AF97 -> 232433.84 | AG99: ='Non Rev P&L'!AU64 -> -3241302.2 | AH99: =AI99-AG99 -> 0 | AI99: =AI11+AI20+AI42+AI69+AI97 -> -3241302.2 | AJ99: =U99+X99+AA99+AD99+AG99 -> 5106855.1 | AK99: =AL99-AJ99 -> 0 | AL99: =AL11+AL20+AL42+AL69+AL97 -> 5106855.1

Sheet YoY Comp
A1: YoY Comp
B2: FY26 (Current Year) | I2: FY26/27 | P2: YoY Comparison 26/27 | W2: FY28 | AD2: YoY Comparison 27/28 | AK2: FY27 Stretch | AR2: YoY Comparison 26/27 Stretch | AY2: FY28 Stretch | BF2: YoY Comparison 27/28 Stretch
B3: UK | C3: CE | D3: EE | E3: ROW | F3: Non Rev | G3: Combined | I3: UK | J3: CE | K3: EE | L3: ROW | M3: Non Rev | N3: Combined | P3: UK | Q3: CE | R3: EE | S3: ROW | T3: Non Rev | U3: Combined | W3: UK | X3: CE | Y3: EE | Z3: ROW | AA3: Non Rev | AB3: Combined | AD3: UK | AE3: CE | AF3: EE | AG3: ROW | AH3: Non Rev | AI3: Combined | AK3: UK | AL3: CE | AM3: EE | AN3: ROW | AO3: Non Rev | AP3: Combined | AR3: UK | AS3: CE | AT3: EE | AU3: ROW | AV3: Non Rev | AW3: Combined | AY3: UK | AZ3: CE | BA3: EE | BB3: ROW | BC3: Non Rev | BD3: Combined | BF3: UK | BG3: CE | BH3: EE | BI3: ROW | BJ3: Non Rev | BK3: Combined
A4: Revenue
A6: DTC Revenue | B6: 2202796 | C6: 1152910 | D6: 4950711 | E6: 46598 | G6: 8353015 | I6: 4837985.8 | J6: 1666198.3 | K6: 6022814.5 | L6: 0 | N6: 12526999 | P6: =IFERROR((I6-B6)/B6,0) -> 1.1962932 | Q6: =IFERROR((J6-C6)/C6,0) -> 0.44521108 | R6: =IFERROR((K6-D6)/D6,0) -> 0.21655546 | S6: =IFERROR((L6-E6)/E6,0) -> -1 | T6: =IFERROR((M6-F6)/F6,0) -> 0 | U6: =IFERROR((N6-G6)/G6,0) -> 0.49969785 | W6: 11107766 | X6: 3483235.2 | Y6: 6936063.2 | Z6: 0 | AB6: 21527065 | AD6: =IFERROR((W6-I6)/I6,0) -> 1.2959485 | AE6: =IFERROR((X6-J6)/J6,0) -> 1.0905286 | AF6: =IFERROR((Y6-K6)/K6,0) -> 0.15163155 | AG6: =IFERROR((Z6-L6)/L6,0) -> 0 | AH6: =IFERROR((AA6-M6)/M6,0) -> 0 | AI6: =IFERROR((AB6-N6)/N6,0) -> 0.7184535 | AK6: 5004917.5 | AL6: 2163434.5 | AM6: 6437527.6 | AN6: 0 | AP6: 13605880 | AR6: =IFERROR((AK6-B6)/B6,0) -> 1.2720749 | AS6: =IFERROR((AL6-C6)/C6,0) -> 0.87649904 | AT6: =IFERROR((AM6-D6)/D6,0) -> 0.30032385 | AU6: =IFERROR((AN6-E6)/E6,0) -> -1 | AV6: =IFERROR((AO6-F6)/F6,0) -> 0 | AW6: =IFERROR((AP6-G6)/G6,0) -> 0.62885851 | AY6: 11345162 | AZ6: 5147771.6 | BA6: 7466237.2 | BB6: 0 | BD6: 23959171 | BF6: =IFERROR((AY6-I6)/I6,0) -> 1.3450177 | BG6: =IFERROR((AZ6-J6)/J6,0) -> 2.0895311 | BH6: =IFERROR((BA6-K6)/K6,0) -> 0.23965916 | BI6: =IFERROR((BB6-L6)/L6,0) -> 0 | BJ6: =IFERROR((BC6-M6)/M6,0) -> 0 | BK6: =IFERROR((BD6-N6)/N6,0) -> 0.91260267
A7: B2B Revenue | B7: 3596822 | C7: 1243001 | D7: 642857 | E7: 1146191 | G7: 6628963 | I7: 4178100.8 | J7: 1803733.2 | K7: 817347.16 | L7: 768617.31 | N7: 7567798.5 | P7: =IFERROR((I7-B7)/B7,0) -> 0.161609 | Q7: =IFERROR((J7-C7)/C7,0) -> 0.45111164 | R7: =IFERROR((K7-D7)/D7,0) -> 0.2714292 | S7: =IFERROR((L7-E7)/E7,0) -> -0.32941603 | T7: =IFERROR((M7-F7)/F7,0) -> 0 | U7: =IFERROR((N7-G7)/G7,0) -> 0.1416263 | W7: 4971270.3 | X7: 2592839.9 | Y7: 925414.52 | Z7: 795421.62 | AB7: 9284946.4 | AD7: =IFERROR((W7-I7)/I7,0) -> 0.18983973 | AE7: =IFERROR((X7-J7)/J7,0) -> 0.43748525 | AF7: =IFERROR((Y7-K7)/K7,0) -> 0.13221721 | AG7: =IFERROR((Z7-L7)/L7,0) -> 0.034873418 | AH7: =IFERROR((AA7-M7)/M7,0) -> 0 | AI7: =IFERROR((AB7-N7)/N7,0) -> 0.2269019 | AK7: 4788173.5 | AL7: 2353893.3 | AM7: 840943.4 | AN7: 417314.65 | AP7: 8371647.6 | AR7: =IFERROR((AK7-B7)/B7,0) -> 0.33122337 | AS7: =IFERROR((AL7-C7)/C7,0) -> 0.89371791 | AT7: =IFERROR((AM7-D7)/D7,0) -> 0.30813446 | AU7: =IFERROR((AN7-E7)/E7,0) -> -0.63591177 | AV7: =IFERROR((AO7-F7)/F7,0) -> 0 | AW7: =IFERROR((AP7-G7)/G7,0) -> 0.26288947 | AY7: 4662436.2 | AZ7: 3911144 | BA7: 919490.57 | BB7: 1840320.6 | BD7: 10438438 | BF7: =IFERROR((AY7-I7)/I7,0) -> 0.11592238 | BG7: =IFERROR((AZ7-J7)/J7,0) -> 1.1683606 | BH7: =IFERROR((BA7-K7)/K7,0) -> 0.12496942 | BI7: =IFERROR((BB7-L7)/L7,0) -> 1.3943262 | BJ7: =IFERROR((BC7-M7)/M7,0) -> 0 | BK7: =IFERROR((BD7-N7)/N7,0) -> 0.37932296
A8: Marketplace Revenue | B8: 2217136 | C8: 605926 | E8: 131537 | G8: 2955853 | I8: 2346062.8 | J8: 832076.01 | K8: 0 | L8: 126298.76 | N8: 3304437.5 | P8: =IFERROR((I8-B8)/B8,0) -> 0.058150141 | Q8: =IFERROR((J8-C8)/C8,0) -> 0.37323042 | R8: =IFERROR((K8-D8)/D8,0) -> 0 | S8: =IFERROR((L8-E8)/E8,0) -> -0.03982332 | T8: =IFERROR((M8-F8)/F8,0) -> 0 | U8: =IFERROR((N8-G8)/G8,0) -> 0.11793027 | W8: 2369523.4 | X8: 1007585.8 | Y8: 0 | Z8: 126298.76 | AB8: 3503407.9 | AD8: =IFERROR((W8-I8)/I8,0) -> 0.01 | AE8: =IFERROR((X8-J8)/J8,0) -> 0.21092997 | AF8: =IFERROR((Y8-K8)/K8,0) -> 0 | AG8: =IFERROR((Z8-L8)/L8,0) -> 0 | AH8: =IFERROR((AA8-M8)/M8,0) -> 0 | AI8: =IFERROR((AB8-N8)/N8,0) -> 0.060213089 | AK8: 2551162 | AL8: 1334223.9 | AM8: 0 | AN8: 126298.76 | AP8: 4011684.7 | AR8: =IFERROR((AK8-B8)/B8,0) -> 0.15065652 | AS8: =IFERROR((AL8-C8)/C8,0) -> 1.2019585 | AT8: =IFERROR((AM8-D8)/D8,0) -> 0 | AU8: =IFERROR((AN8-E8)/E8,0) -> -0.03982332 | AV8: =IFERROR((AO8-F8)/F8,0) -> 0 | AW8: =IFERROR((AP8-G8)/G8,0) -> 0.35720033 | AY8: 2576673.6 | AZ8: 2339971.9 | BA8: 0 | BB8: 126298.76 | BD8: 5042944.2 | BF8: =IFERROR((AY8-I8)/I8,0) -> 0.098296965 | BG8: =IFERROR((AZ8-J8)/J8,0) -> 1.8122092 | BH8: =IFERROR((BA8-K8)/K8,0) -> 0 | BI8: =IFERROR((BB8-L8)/L8,0) -> 0 | BJ8: =IFERROR((BC8-M8)/M8,0) -> 0 | BK8: =IFERROR((BD8-N8)/N8,0) -> 0.52611274
A9: TikTok Revenue | B9: 89872 | G9: 89872 | I9: 0 | J9: 0 | K9: 0 | L9: 0 | N9: 0 | P9: =IFERROR((I9-B9)/B9,0) -> -1 | Q9: =IFERROR((J9-C9)/C9,0) -> 0 | R9: =IFERROR((K9-D9)/D9,0) -> 0 | S9: =IFERROR((L9-E9)/E9,0) -> 0 | T9: =IFERROR((M9-F9)/F9,0) -> 0 | U9: =IFERROR((N9-G9)/G9,0) -> -1 | W9: 0 | X9: 0 | Y9: 0 | Z9: 0 | AB9: 0 | AD9: =IFERROR((W9-I9)/I9,0) -> 0 | AE9: =IFERROR((X9-J9)/J9,0) -> 0 | AF9: =IFERROR((Y9-K9)/K9,0) -> 0 | AG9: =IFERROR((Z9-L9)/L9,0) -> 0 | AH9: =IFERROR((AA9-M9)/M9,0) -> 0 | AI9: =IFERROR((AB9-N9)/N9,0) -> 0 | AK9: 0 | AL9: 0 | AM9: 0 | AN9: 0 | AP9: 0 | AR9: =IFERROR((AK9-B9)/B9,0) -> -1 | AS9: =IFERROR((AL9-C9)/C9,0) -> 0 | AT9: =IFERROR((AM9-D9)/D9,0) -> 0 | AU9: =IFERROR((AN9-E9)/E9,0) -> 0 | AV9: =IFERROR((AO9-F9)/F9,0) -> 0 | AW9: =IFERROR((AP9-G9)/G9,0) -> -1 | AY9: 0 | AZ9: 0 | BA9: 0 | BB9: 0 | BD9: 0 | BF9: =IFERROR((AY9-I9)/I9,0) -> 0 | BG9: =IFERROR((AZ9-J9)/J9,0) -> 0 | BH9: =IFERROR((BA9-K9)/K9,0) -> 0 | BI9: =IFERROR((BB9-L9)/L9,0) -> 0 | BJ9: =IFERROR((BC9-M9)/M9,0) -> 0 | BK9: =IFERROR((BD9-N9)/N9,0) -> 0
A11: Total Revenue | B11: 8106625 | C11: 3001838 | D11: 5593568 | E11: 1324326 | G11: 18027702 | I11: 11362149 | J11: 4302007.5 | K11: 6840161.7 | L11: 894916.07 | M11: ='Non Rev P&L'!AF7 -> 0 | N11: 23399235 | P11: =IFERROR((I11-B11)/B11,0) -> 0.40158813 | Q11: =IFERROR((J11-C11)/C11,0) -> 0.43312449 | R11: =IFERROR((K11-D11)/D11,0) -> 0.22286199 | S11: =IFERROR((L11-E11)/E11,0) -> -0.32424791 | T11: =IFERROR((M11-F11)/F11,0) -> 0 | U11: =IFERROR((N11-G11)/G11,0) -> 0.29795992 | W11: 18448560 | X11: 7083660.9 | Y11: 7861477.7 | Z11: 921720.38 | AB11: 34315419 | AD11: =IFERROR((W11-I11)/I11,0) -> 0.62368575 | AE11: =IFERROR((X11-J11)/J11,0) -> 0.64659425 | AF11: =IFERROR((Y11-K11)/K11,0) -> 0.14931168 | AG11: =IFERROR((Z11-L11)/L11,0) -> 0.029951762 | AH11: =IFERROR((AA11-M11)/M11,0) -> 0 | AI11: =IFERROR((AB11-N11)/N11,0) -> 0.46651886 | AK11: 12344253 | AL11: 5851551.7 | AM11: 7278471 | AN11: 543613.41 | AP11: 25989212 | AR11: =IFERROR((AK11-B11)/B11,0) -> 0.52273641 | AS11: =IFERROR((AL11-C11)/C11,0) -> 0.94932294 | AT11: =IFERROR((AM11-D11)/D11,0) -> 0.3012215 | AU11: =IFERROR((AN11-E11)/E11,0) -> -0.58951692 | AV11: =IFERROR((AO11-F11)/F11,0) -> 0 | AW11: =IFERROR((AP11-G11)/G11,0) -> 0.44162644 | AY11: 18584272 | AZ11: 11398887 | BA11: 8385727.7 | BB11: 1966619.3 | BD11: 39440553 | BF11: =IFERROR((AY11-I11)/I11,0) -> 0.63562997 | BG11: =IFERROR((AZ11-J11)/J11,0) -> 1.649667 | BH11: =IFERROR((BA11-K11)/K11,0) -> 0.22595461 | BI11: =IFERROR((BB11-L11)/L11,0) -> 1.1975461 | BJ11: =IFERROR((BC11-M11)/M11,0) -> 0 | BK11: =IFERROR((BD11-N11)/N11,0) -> 0.68554887
A13: Cost of Goods Sold (CoGS)
A15: DTC CoGS | B15: -529860 | C15: -280038 | D15: -1269852 | E15: -6423 | F15: 26112 | G15: -2095277 | I15: -1015977 | J15: -399887.59 | K15: -1445475.5 | L15: 0 | N15: -2861340.1 | P15: =IFERROR((I15-B15)/B15,0) -> 0.91744428 | Q15: =IFERROR((J15-C15)/C15,0) -> 0.42797618 | R15: =IFERROR((K15-D15)/D15,0) -> 0.13830232 | S15: =IFERROR((L15-E15)/E15,0) -> -1 | T15: =IFERROR((M15-F15)/F15,0) -> -1 | U15: =IFERROR((N15-G15)/G15,0) -> 0.36561424 | W15: -2221553.3 | X15: -835976.45 | Y15: -1664655.2 | Z15: 0 | AB15: -4722184.9 | AD15: =IFERROR((W15-I15)/I15,0) -> 1.1866176 | AE15: =IFERROR((X15-J15)/J15,0) -> 1.0905286 | AF15: =IFERROR((Y15-K15)/K15,0) -> 0.15163155 | AG15: =IFERROR((Z15-L15)/L15,0) -> 0 | AH15: =IFERROR((AA15-M15)/M15,0) -> 0 | AI15: =IFERROR((AB15-N15)/N15,0) -> 0.6503403 | AK15: -1051032.7 | AL15: -519224.28 | AM15: -1545006.6 | AN15: 0 | AP15: -3115263.6 | AR15: =IFERROR((AK15-B15)/B15,0) -> 0.98360449 | AS15: =IFERROR((AL15-C15)/C15,0) -> 0.85412081 | AT15: =IFERROR((AM15-D15)/D15,0) -> 0.21668243 | AU15: =IFERROR((AN15-E15)/E15,0) -> -1 | AV15: =IFERROR((AO15-F15)/F15,0) -> -1 | AW15: =IFERROR((AP15-G15)/G15,0) -> 0.48680274 | AY15: -2269032.5 | AZ15: -1235465.2 | BA15: -1791896.9 | BB15: 0 | BD15: -5296394.6 | BF15: =IFERROR((AY15-I15)/I15,0) -> 1.2333502 | BG15: =IFERROR((AZ15-J15)/J15,0) -> 2.0895311 | BH15: =IFERROR((BA15-K15)/K15,0) -> 0.23965916 | BI15: =IFERROR((BB15-L15)/L15,0) -> 0 | BJ15: =IFERROR((BC15-M15)/M15,0) -> 0 | BK15: =IFERROR((BD15-N15)/N15,0) -> 0.85101888
A16: B2B CoGS | B16: -998660 | C16: -404020 | D16: -235555 | E16: -466664 | G16: -2053505 | I16: -1066251.3 | J16: -577194.63 | K16: -326938.87 | L16: -286819.27 | N16: -2257204.1 | P16: =IFERROR((I16-B16)/B16,0) -> 0.067682017 | Q16: =IFERROR((J16-C16)/C16,0) -> 0.42862886 | R16: =IFERROR((K16-D16)/D16,0) -> 0.38795129 | S16: =IFERROR((L16-E16)/E16,0) -> -0.38538377 | T16: =IFERROR((M16-F16)/F16,0) -> 0 | U16: =IFERROR((N16-G16)/G16,0) -> 0.099195809 | W16: -1268668.2 | X16: -829708.77 | Y16: -370165.81 | Z16: -296821.64 | AB16: -2765364.4 | AD16: =IFERROR((W16-I16)/I16,0) -> 0.18983973 | AE16: =IFERROR((X16-J16)/J16,0) -> 0.43748525 | AF16: =IFERROR((Y16-K16)/K16,0) -> 0.13221721 | AG16: =IFERROR((Z16-L16)/L16,0) -> 0.034873418 | AH16: =IFERROR((AA16-M16)/M16,0) -> 0 | AI16: =IFERROR((AB16-N16)/N16,0) -> 0.22512821 | AK16: -1221941.9 | AL16: -588473.31 | AM16: -252283.02 | AN16: -133540.69 | AP16: -2196238.9 | AR16: =IFERROR((AK16-B16)/B16,0) -> 0.22358148 | AS16: =IFERROR((AL16-C16)/C16,0) -> 0.45654501 | AT16: =IFERROR((AM16-D16)/D16,0) -> 0.071015341 | AU16: =IFERROR((AN16-E16)/E16,0) -> -0.71383975 | AV16: =IFERROR((AO16-F16)/F16,0) -> 0 | AW16: =IFERROR((AP16-G16)/G16,0) -> 0.069507454 | AY16: -1189853.7 | AZ16: -977786 | BA16: -275847.17 | BB16: -588902.59 | BD16: -3032389.5 | BF16: =IFERROR((AY16-I16)/I16,0) -> 0.11592238 | BG16: =IFERROR((AZ16-J16)/J16,0) -> 0.69403169 | BH16: =IFERROR((BA16-K16)/K16,0) -> -0.15627293 | BI16: =IFERROR((BB16-L16)/L16,0) -> 1.0532183 | BJ16: =IFERROR((BC16-M16)/M16,0) -> 0 | BK16: =IFERROR((BD16-N16)/N16,0) -> 0.34342724
A17: Marketplace CoGS | B17: -382302 | C17: -106836 | E17: -16207 | G17: -505343 | I17: -422291.3 | J17: -149773.68 | K17: 0 | L17: -22733.777 | N17: -594798.76 | P17: =IFERROR((I17-B17)/B17,0) -> 0.10460133 | Q17: =IFERROR((J17-C17)/C17,0) -> 0.40190275 | R17: =IFERROR((K17-D17)/D17,0) -> 0 | S17: =IFERROR((L17-E17)/E17,0) -> 0.40271344 | T17: =IFERROR((M17-F17)/F17,0) -> 0 | U17: =IFERROR((N17-G17)/G17,0) -> 0.17701988 | W17: -426514.21 | X17: -181365.44 | Y17: 0 | Z17: -22733.777 | AB17: -630613.43 | AD17: =IFERROR((W17-I17)/I17,0) -> 0.01 | AE17: =IFERROR((X17-J17)/J17,0) -> 0.21092997 | AF17: =IFERROR((Y17-K17)/K17,0) -> 0 | AG17: =IFERROR((Z17-L17)/L17,0) -> 0 | AH17: =IFERROR((AA17-M17)/M17,0) -> 0 | AI17: =IFERROR((AB17-N17)/N17,0) -> 0.060213089 | AK17: -459209.16 | AL17: -240160.31 | AM17: 0 | AN17: -22733.777 | AP17: -722103.24 | AR17: =IFERROR((AK17-B17)/B17,0) -> 0.2011686 | AS17: =IFERROR((AL17-C17)/C17,0) -> 1.2479343 | AT17: =IFERROR((AM17-D17)/D17,0) -> 0 | AU17: =IFERROR((AN17-E17)/E17,0) -> 0.40271344 | AV17: =IFERROR((AO17-F17)/F17,0) -> 0 | AW17: =IFERROR((AP17-G17)/G17,0) -> 0.42893687 | AY17: -463801.25 | AZ17: -421194.93 | BA17: 0 | BB17: -22733.777 | BD17: -907729.96 | BF17: =IFERROR((AY17-I17)/I17,0) -> 0.098296965 | BG17: =IFERROR((AZ17-J17)/J17,0) -> 1.8122092 | BH17: =IFERROR((BA17-K17)/K17,0) -> 0 | BI17: =IFERROR((BB17-L17)/L17,0) -> 0 | BJ17: =IFERROR((BC17-M17)/M17,0) -> 0 | BK17: =IFERROR((BD17-N17)/N17,0) -> 0.52611274
A18: TikTok CoGS | B18: -18989 | G18: -18989 | I18: 0 | J18: 0 | K18: 0 | L18: 0 | N18: 0 | P18: =IFERROR((I18-B18)/B18,0) -> -1 | Q18: =IFERROR((J18-C18)/C18,0) -> 0 | R18: =IFERROR((K18-D18)/D18,0) -> 0 | S18: =IFERROR((L18-E18)/E18,0) -> 0 | T18: =IFERROR((M18-F18)/F18,0) -> 0 | U18: =IFERROR((N18-G18)/G18,0) -> -1 | W18: 0 | X18: 0 | Y18: 0 | Z18: 0 | AB18: 0 | AD18: =IFERROR((W18-I18)/I18,0) -> 0 | AE18: =IFERROR((X18-J18)/J18,0) -> 0 | AF18: =IFERROR((Y18-K18)/K18,0) -> 0 | AG18: =IFERROR((Z18-L18)/L18,0) -> 0 | AH18: =IFERROR((AA18-M18)/M18,0) -> 0 | AI18: =IFERROR((AB18-N18)/N18,0) -> 0 | AK18: 0 | AL18: 0 | AM18: 0 | AN18: 0 | AP18: 0 | AR18: =IFERROR((AK18-B18)/B18,0) -> -1 | AS18: =IFERROR((AL18-C18)/C18,0) -> 0 | AT18: =IFERROR((AM18-D18)/D18,0) -> 0 | AU18: =IFERROR((AN18-E18)/E18,0) -> 0 | AV18: =IFERROR((AO18-F18)/F18,0) -> 0 | AW18: =IFERROR((AP18-G18)/G18,0) -> -1 | AY18: 0 | AZ18: 0 | BA18: 0 | BB18: 0 | BD18: 0 | BF18: =IFERROR((AY18-I18)/I18,0) -> 0 | BG18: =IFERROR((AZ18-J18)/J18,0) -> 0 | BH18: =IFERROR((BA18-K18)/K18,0) -> 0 | BI18: =IFERROR((BB18-L18)/L18,0) -> 0 | BJ18: =IFERROR((BC18-M18)/M18,0) -> 0 | BK18: =IFERROR((BD18-N18)/N18,0) -> 0
A20: Total CoGS | B20: -1929811 | C20: -790895 | D20: -1505406 | E20: -489293 | F20: 26112 | G20: -4673115 | I20: -2504519.6 | J20: -1126855.9 | K20: -1772414.3 | L20: -309553.05 | N20: -5713342.9 | P20: =IFERROR((I20-B20)/B20,0) -> 0.29780566 | Q20: =IFERROR((J20-C20)/C20,0) -> 0.42478573 | R20: =IFERROR((K20-D20)/D20,0) -> 0.17736634 | S20: =IFERROR((L20-E20)/E20,0) -> -0.36734626 | T20: =IFERROR((M20-F20)/F20,0) -> -1 | U20: =IFERROR((N20-G20)/G20,0) -> 0.22259841 | W20: -3916735.7 | X20: -1847050.7 | Y20: -2034821 | Z20: -319555.41 | AB20: -8118162.7 | AD20: =IFERROR((W20-I20)/I20,0) -> 0.56386701 | AE20: =IFERROR((X20-J20)/J20,0) -> 0.63911876 | AF20: =IFERROR((Y20-K20)/K20,0) -> 0.14805039 | AG20: =IFERROR((Z20-L20)/L20,0) -> 0.032312292 | AH20: =IFERROR((AA20-M20)/M20,0) -> 0 | AI20: =IFERROR((AB20-N20)/N20,0) -> 0.4209129 | AK20: -2732183.7 | AL20: -1347857.9 | AM20: -1797289.6 | AN20: -156274.47 | AP20: -6033605.7 | AR20: =IFERROR((AK20-B20)/B20,0) -> 0.41577788 | AS20: =IFERROR((AL20-C20)/C20,0) -> 0.70421851 | AT20: =IFERROR((AM20-D20)/D20,0) -> 0.19389031 | AU20: =IFERROR((AN20-E20)/E20,0) -> -0.68061169 | AV20: =IFERROR((AO20-F20)/F20,0) -> -1 | AW20: =IFERROR((AP20-G20)/G20,0) -> 0.29113144 | AY20: -3922687.4 | AZ20: -2634446.1 | BA20: -2067744.1 | BB20: -611636.36 | BD20: -9236514 | BF20: =IFERROR((AY20-I20)/I20,0) -> 0.56624342 | BG20: =IFERROR((AZ20-J20)/J20,0) -> 1.3378731 | BH20: =IFERROR((BA20-K20)/K20,0) -> 0.16662568 | BI20: =IFERROR((BB20-L20)/L20,0) -> 0.9758693 | BJ20: =IFERROR((BC20-M20)/M20,0) -> 0 | BK20: =IFERROR((BD20-N20)/N20,0) -> 0.61665667
W21: -0.21230577 | X21: -0.26074804 | Y21: -0.25883441 | Z21: -0.34669453 | AB21: -0.23657478 | AK21: -0.22133245 | AL21: -0.23034196 | AM21: -0.24693231 | AN21: -0.28747353 | AP21: -0.23215809 | AY21: -0.21107566 | AZ21: -0.23111432 | BA21: -0.24657897 | BB21: -0.31100902 | BD21: -0.23418824
A22: DTC CM1 | B22: =B6+B15 -> 1672936 | C22: =C6+C15 -> 872872 | D22: =D6+D15 -> 3680859 | E22: =E6+E15 -> 40175 | F22: =F6+F15 -> 26112 | G22: =G6+G15 -> 6257738 | I22: =I6+I15 -> 3822008.8 | J22: =J6+J15 -> 1266310.7 | K22: =K6+K15 -> 4577339 | L22: =L6+L15 -> 0 | M22: =M6+M15 -> 0 | N22: =N6+N15 -> 9665658.6 | W22: =W6+W15 -> 8886213 | X22: =X6+X15 -> 2647258.7 | Y22: =Y6+Y15 -> 5271408 | Z22: =Z6+Z15 -> 0 | AA22: =AA6+AA15 -> 0 | AB22: =AB6+AB15 -> 16804880 | AK22: 3953884.8 | AL22: 1644210.2 | AM22: 4892521 | AN22: 0 | AP22: 10490616 | AY22: 9076129.8 | AZ22: 3912306.4 | BA22: 5674340.3 | BB22: 0 | BD22: 18662776
A23: B2B CM1 | B23: =B7+B16 -> 2598162 | C23: =C7+C16 -> 838981 | D23: =D7+D16 -> 407302 | E23: =E7+E16 -> 679527 | F23: =F7+F16 -> 0 | G23: =G7+G16 -> 4575458 | I23: =I7+I16 -> 3111849.5 | J23: =J7+J16 -> 1226538.6 | K23: =K7+K16 -> 490408.3 | L23: =L7+L16 -> 481798.04 | M23: =M7+M16 -> 0 | N23: =N7+N16 -> 5310594.4 | W23: =W7+W16 -> 3702602.1 | X23: =X7+X16 -> 1763131.1 | Y23: =Y7+Y16 -> 555248.71 | Z23: =Z7+Z16 -> 498599.98 | AA23: =AA7+AA16 -> 0 | AB23: =AB7+AB16 -> 6519582 | AK23: 3566231.6 | AL23: 1765419.9 | AM23: 588660.38 | AN23: 283773.96 | AP23: 6175408.7 | AY23: 3472582.5 | AZ23: 2933358 | BA23: 643643.4 | BB23: 1251418 | BD23: 7406048.7
A24: Marketplace CM1 | B24: =B8+B17 -> 1834834 | C24: =C8+C17 -> 499090 | D24: =D8+D17 -> 0 | E24: =E8+E17 -> 115330 | F24: =F8+F17 -> 0 | G24: =G8+G17 -> 2450510 | I24: =I8+I17 -> 1923771.5 | J24: =J8+J17 -> 682302.33 | K24: =K8+K17 -> 0 | L24: =L8+L17 -> 103564.98 | M24: =M8+M17 -> 0 | N24: =N8+N17 -> 2709638.8 | W24: =W8+W17 -> 1943009.2 | X24: =X8+X17 -> 826220.34 | Y24: =Y8+Y17 -> 0 | Z24: =Z8+Z17 -> 103564.98 | AA24: =AA8+AA17 -> 0 | AB24: =AB8+AB17 -> 2872794.5 | AK24: 2091952.8 | AL24: 1094063.6 | AM24: 0 | AN24: 103564.98 | AP24: 3289581.4 | AY24: 2112872.4 | AZ24: 1918776.9 | BA24: 0 | BB24: 103564.98 | BD24: 4135214.3
A25: TikTok CM1 | B25: =B9+B18 -> 70883 | C25: =C9+C18 -> 0 | D25: =D9+D18 -> 0 | E25: =E9+E18 -> 0 | F25: =F9+F18 -> 0 | G25: =G9+G18 -> 70883 | I25: =I9+I18 -> 0 | J25: =J9+J18 -> 0 | K25: =K9+K18 -> 0 | L25: =L9+L18 -> 0 | M25: =M9+M18 -> 0 | N25: =N9+N18 -> 0 | W25: =W9+W18 -> 0 | X25: =X9+X18 -> 0 | Y25: =Y9+Y18 -> 0 | Z25: =Z9+Z18 -> 0 | AA25: =AA9+AA18 -> 0 | AB25: =AB9+AB18 -> 0 | AK25: 0 | AL25: 0 | AM25: 0 | AN25: 0 | AP25: 0 | AY25: 0 | AZ25: 0 | BA25: 0 | BB25: 0 | BD25: 0
A26: Total CM1 | B26: =B11+B20 -> 6176814 | C26: =C11+C20 -> 2210943 | D26: =D11+D20 -> 4088162 | E26: =E11+E20 -> 835033 | F26: =F11+F20 -> 26112 | G26: =G11+G20 -> 13354587 | I26: =I11+I20 -> 8857629.8 | J26: =J11+J20 -> 3175151.6 | K26: =K11+K20 -> 5067747.3 | L26: =L11+L20 -> 585363.02 | M26: =M11+M20 -> 0 | N26: =N11+N20 -> 17685892 | W26: =W11+W20 -> 14531824 | X26: =X11+X20 -> 5236610.2 | Y26: =Y11+Y20 -> 5826656.7 | Z26: =Z11+Z20 -> 602164.97 | AA26: =AA11+AA20 -> 0 | AB26: =AB11+AB20 -> 26197256 | AK26: 9612069.3 | AL26: 4503693.8 | AM26: 5481181.3 | AN26: 387338.95 | AP26: 19955606 | AY26: 14661585 | AZ26: 8764441.3 | BA26: 6317983.7 | BB26: 1354983 | BD26: 30204039
A28: DTC CM1% | B28: =IFERROR(B22/B6,0) -> 0.75946025 | C28: =IFERROR(C22/C6,0) -> 0.75710333 | D28: =IFERROR(D22/D6,0) -> 0.74350108 | E28: =IFERROR(E22/E6,0) -> 0.86216147 | F28: =IFERROR(F22/F6,0) -> 0 | G28: =IFERROR(G22/G6,0) -> 0.7491592 | I28: =IFERROR(I22/I6,0) -> 0.79 | J28: =IFERROR(J22/J6,0) -> 0.76 | K28: =IFERROR(K22/K6,0) -> 0.76 | L28: =IFERROR(L22/L6,0) -> 0 | M28: =IFERROR(M22/M6,0) -> 0 | N28: =IFERROR(N22/N6,0) -> 0.77158614 | W28: =IFERROR(W22/W6,0) -> 0.8 | X28: =IFERROR(X22/X6,0) -> 0.76 | Y28: =IFERROR(Y22/Y6,0) -> 0.76 | Z28: =IFERROR(Z22/Z6,0) -> 0 | AA28: =IFERROR(AA22/AA6,0) -> 0 | AB28: =IFERROR(AB22/AB6,0) -> 0.78063963 | AK28: 0.79 | AL28: 0.76 | AM28: 0.76 | AN28: 0 | AP28: 0.77103549 | AY28: 0.8 | AZ28: 0.76 | BA28: 0.76 | BB28: 0 | BD28: 0.77894083
A29: B2B CM1% | B29: =IFERROR(B23/B7,0) -> 0.72234934 | C29: =IFERROR(C23/C7,0) -> 0.67496406 | D29: =IFERROR(D23/D7,0) -> 0.63358103 | E29: =IFERROR(E23/E7,0) -> 0.59285669 | F29: =IFERROR(F23/F7,0) -> 0 | G29: =IFERROR(G23/G7,0) -> 0.69022229 | I29: =IFERROR(I23/I7,0) -> 0.7448 | J29: =IFERROR(J23/J7,0) -> 0.68 | K29: =IFERROR(K23/K7,0) -> 0.6 | L29: =IFERROR(L23/L7,0) -> 0.62683735 | M29: =IFERROR(M23/M7,0) -> 0 | N29: =IFERROR(N23/N7,0) -> 0.7017357 | W29: =IFERROR(W23/W7,0) -> 0.7448 | X29: =IFERROR(X23/X7,0) -> 0.68 | Y29: =IFERROR(Y23/Y7,0) -> 0.6 | Z29: =IFERROR(Z23/Z7,0) -> 0.62683735 | AA29: =IFERROR(AA23/AA7,0) -> 0 | AB29: =IFERROR(AB23/AB7,0) -> 0.7021669 | AK29: 0.7448 | AL29: 0.75 | AM29: 0.7 | AN29: 0.68 | AP29: 0.73765751 | AY29: 0.7448 | AZ29: 0.75 | BA29: 0.7 | BB29: 0.68 | BD29: 0.70949778
A30: Marketplace CM1% | B30: =IFERROR(B24/B8,0) -> 0.82756944 | C30: =IFERROR(C24/C8,0) -> 0.82368144 | D30: =IFERROR(D24/D8,0) -> 0 | E30: =IFERROR(E24/E8,0) -> 0.87678752 | F30: =IFERROR(F24/F8,0) -> 0 | G30: =IFERROR(G24/G8,0) -> 0.82903649 | I30: =IFERROR(I24/I8,0) -> 0.82 | J30: =IFERROR(J24/J8,0) -> 0.82 | K30: =IFERROR(K24/K8,0) -> 0 | L30: =IFERROR(L24/L8,0) -> 0.82 | M30: =IFERROR(M24/M8,0) -> 0 | N30: =IFERROR(N24/N8,0) -> 0.82 | W30: =IFERROR(W24/W8,0) -> 0.82 | X30: =IFERROR(X24/X8,0) -> 0.82 | Y30: =IFERROR(Y24/Y8,0) -> 0 | Z30: =IFERROR(Z24/Z8,0) -> 0.82 | AA30: =IFERROR(AA24/AA8,0) -> 0 | AB30: =IFERROR(AB24/AB8,0) -> 0.82 | AK30: 0.82 | AL30: 0.82 | AM30: 0 | AN30: 0.82 | AP30: 0.82 | AY30: 0.82 | AZ30: 0.82 | BA30: 0 | BB30: 0.82 | BD30: 0.82
A31: TikTok CM1% | B31: =IFERROR(B25/B9,0) -> 0.78871061 | C31: =IFERROR(C25/C9,0) -> 0 | D31: =IFERROR(D25/D9,0) -> 0 | E31: =IFERROR(E25/E9,0) -> 0 | F31: =IFERROR(F25/F9,0) -> 0 | G31: =IFERROR(G25/G9,0) -> 0.78871061 | I31: =IFERROR(I25/I9,0) -> 0 | J31: =IFERROR(J25/J9,0) -> 0 | K31: =IFERROR(K25/K9,0) -> 0 | L31: =IFERROR(L25/L9,0) -> 0 | M31: =IFERROR(M25/M9,0) -> 0 | N31: =IFERROR(N25/N9,0) -> 0 | W31: =IFERROR(W25/W9,0) -> 0 | X31: =IFERROR(X25/X9,0) -> 0 | Y31: =IFERROR(Y25/Y9,0) -> 0 | Z31: =IFERROR(Z25/Z9,0) -> 0 | AA31: =IFERROR(AA25/AA9,0) -> 0 | AB31: =IFERROR(AB25/AB9,0) -> 0 | AK31: 0 | AL31: 0 | AM31: 0 | AN31: 0 | AP31: 0 | AY31: 0 | AZ31: 0 | BA31: 0 | BB31: 0 | BD31: 0
A32: Total CM1% | B32: =IFERROR(B26/B11,0) -> 0.76194643 | C32: =IFERROR(C26/C10,0) -> 0 | D32: =IFERROR(D26/D10,0) -> 0 | E32: =IFERROR(E26/E10,0) -> 0 | F32: =IFERROR(F26/F10,0) -> 0 | G32: =IFERROR(G26/G10,0) -> 0 | I32: =IFERROR(I26/I11,0) -> 0.77957343 | J32: =IFERROR(J26/J10,0) -> 0 | K32: =IFERROR(K26/K10,0) -> 0 | L32: =IFERROR(L26/L10,0) -> 0 | M32: =IFERROR(M26/M10,0) -> 0 | N32: =IFERROR(N26/N10,0) -> 0 | W32: =IFERROR(W26/W11,0) -> 0.78769423 | X32: =IFERROR(X26/X10,0) -> 0 | Y32: =IFERROR(Y26/Y10,0) -> 0 | Z32: =IFERROR(Z26/Z10,0) -> 0 | AA32: =IFERROR(AA26/AA10,0) -> 0 | AB32: =IFERROR(AB26/AB10,0) -> 0 | AK32: 0.77866755 | AL32: 0.76965804 | AM32: 0.75306769 | AN32: 0.71252647 | AP32: 0.76784191 | AY32: 0.78892434 | AZ32: 0.76888568 | BA32: 0.75342103 | BB32: 0.68899098 | BD32: 0.76581176
A34: Fulfilment
A36: Central | B36: -8901 | C36: 14198 | D36: - | E36: -128 | F36: -340393 | G36: -350589 | I36: 0 | J36: 0 | K36: 0 | L36: 0 | N36: -300000 | P36: =IFERROR((I36-B36)/B36,0) -> -1 | Q36: =IFERROR((J36-C36)/C36,0) -> -1 | R36: =IFERROR((K36-D36)/D36,0) -> 0 | S36: =IFERROR((L36-E36)/E36,0) -> -1 | T36: =IFERROR((M36-F36)/F36,0) -> -1 | U36: =IFERROR((N36-G36)/G36,0) -> -0.14429717 | W36: 0 | X36: 0 | Y36: 0 | Z36: 0 | AB36: -300000 | AD36: =IFERROR((W36-I36)/I36,0) -> 0 | AE36: =IFERROR((X36-J36)/J36,0) -> 0 | AF36: =IFERROR((Y36-K36)/K36,0) -> 0 | AG36: =IFERROR((Z36-L36)/L36,0) -> 0 | AH36: =IFERROR((AA36-M36)/M36,0) -> 0 | AI36: =IFERROR((AB36-N36)/N36,0) -> 0 | AK36: 0 | AL36: 0 | AM36: 0 | AN36: 0 | AP36: -300000 | AR36: =IFERROR((AK36-B36)/B36,0) -> -1 | AS36: =IFERROR((AL36-C36)/C36,0) -> -1 | AT36: =IFERROR((AM36-D36)/D36,0) -> 0 | AU36: =IFERROR((AN36-E36)/E36,0) -> -1 | AV36: =IFERROR((AO36-F36)/F36,0) -> -1 | AW36: =IFERROR((AP36-G36)/G36,0) -> -0.14429717 | AY36: 0 | AZ36: 0 | BA36: 0 | BB36: 0 | BD36: -300000 | BF36: =IFERROR((AY36-I36)/I36,0) -> 0 | BG36: =IFERROR((AZ36-J36)/J36,0) -> 0 | BH36: =IFERROR((BA36-K36)/K36,0) -> 0 | BI36: =IFERROR((BB36-L36)/L36,0) -> 0 | BJ36: =IFERROR((BC36-M36)/M36,0) -> 0 | BK36: =IFERROR((BD36-N36)/N36,0) -> 0
A37: DTC Fulfilment | B37: -263146 | C37: -242539 | D37: -833420 | E37: -27005 | F37: -42154 | G37: -1407620 | I37: -660990.96 | J37: -322094.41 | K37: -1164276.1 | L37: 0 | M37: -300000 | N37: -2147361.5 | P37: =IFERROR((I37-B37)/B37,0) -> 1.5118792 | Q37: =IFERROR((J37-C37)/C37,0) -> 0.32801081 | R37: =IFERROR((K37-D37)/D37,0) -> 0.39698606 | S37: =IFERROR((L37-E37)/E37,0) -> -1 | T37: =IFERROR((M37-F37)/F37,0) -> 6.1167623 | U37: =IFERROR((N37-G37)/G37,0) -> 0.52552642 | W37: -1517601.2 | X37: -673347.58 | Y37: -1340817.1 | Z37: 0 | AA37: -300000 | AB37: -3531765.9 | AD37: =IFERROR((W37-I37)/I37,0) -> 1.2959485 | AE37: =IFERROR((X37-J37)/J37,0) -> 1.0905286 | AF37: =IFERROR((Y37-K37)/K37,0) -> 0.15163155 | AG37: =IFERROR((Z37-L37)/L37,0) -> 0 | AH37: =IFERROR((AA37-M37)/M37,0) -> 0 | AI37: =IFERROR((AB37-N37)/N37,0) -> 0.64470021 | AK37: -683798.04 | AL37: -418215.63 | AM37: -1244444.7 | AN37: 0 | AO37: -300000 | AP37: -2346458.4 | AR37: =IFERROR((AK37-B37)/B37,0) -> 1.59855 | AS37: =IFERROR((AL37-C37)/C37,0) -> 0.72432321 | AT37: =IFERROR((AM37-D37)/D37,0) -> 0.49317836 | AU37: =IFERROR((AN37-E37)/E37,0) -> -1 | AV37: =IFERROR((AO37-F37)/F37,0) -> 6.1167623 | AW37: =IFERROR((AP37-G37)/G37,0) -> 0.66696863 | AY37: -1550035.5 | AZ37: -995120.72 | BA37: -1443305.6 | BB37: 0 | BC37: -300000 | BD37: -3988461.8 | BF37: =IFERROR((AY37-I37)/I37,0) -> 1.3450177 | BG37: =IFERROR((AZ37-J37)/J37,0) -> 2.0895311 | BH37: =IFERROR((BA37-K37)/K37,0) -> 0.23965916 | BI37: =IFERROR((BB37-L37)/L37,0) -> 0 | BJ37: =IFERROR((BC37-M37)/M37,0) -> 0 | BK37: =IFERROR((BD37-N37)/N37,0) -> 0.85737789
A38: B2B Fulfilment | B38: -203593 | C38: -94006 | D38: -36834 | E38: -77593 | F38: 5673 | G38: -406351 | I38: -217872.6 | J38: -125712.74 | K38: -49040.83 | L38: 0 | N38: -392626.17 | P38: =IFERROR((I38-B38)/B38,0) -> 0.070137967 | Q38: =IFERROR((J38-C38)/C38,0) -> 0.33728425 | R38: =IFERROR((K38-D38)/D38,0) -> 0.33140115 | S38: =IFERROR((L38-E38)/E38,0) -> -1 | T38: =IFERROR((M38-F38)/F38,0) -> -1 | U38: =IFERROR((N38-G38)/G38,0) -> -0.033775793 | W38: -259233.47 | X38: -180710.21 | Y38: -55524.871 | Z38: -110065.2 | AB38: -605533.76 | AD38: =IFERROR((W38-I38)/I38,0) -> 0.18983973 | AE38: =IFERROR((X38-J38)/J38,0) -> 0.43748525 | AF38: =IFERROR((Y38-K38)/K38,0) -> 0.13221721 | AG38: =IFERROR((Z38-L38)/L38,0) -> 0 | AH38: =IFERROR((AA38-M38)/M38,0) -> 0 | AI38: =IFERROR((AB38-N38)/N38,0) -> 0.5422654 | AK38: -249685.65 | AL38: -164056.62 | AM38: -50456.604 | AN38: -29673.807 | AP38: -493872.68 | AR38: =IFERROR((AK38-B38)/B38,0) -> 0.22639604 | AS38: =IFERROR((AL38-C38)/C38,0) -> 0.74517181 | AT38: =IFERROR((AM38-D38)/D38,0) -> 0.36983775 | AU38: =IFERROR((AN38-E38)/E38,0) -> -0.61757108 | AV38: =IFERROR((AO38-F38)/F38,0) -> -1 | AW38: =IFERROR((AP38-G38)/G38,0) -> 0.21538444 | AY38: -243128.91 | AZ38: -272590.55 | BA38: -55169.434 | BB38: -184032.06 | BD38: -754920.96 | BF38: =IFERROR((AY38-I38)/I38,0) -> 0.11592238 | BG38: =IFERROR((AZ38-J38)/J38,0) -> 1.1683606 | BH38: =IFERROR((BA38-K38)/K38,0) -> 0.12496942 | BI38: =IFERROR((BB38-L38)/L38,0) -> 0 | BJ38: =IFERROR((BC38-M38)/M38,0) -> 0 | BK38: =IFERROR((BD38-N38)/N38,0) -> 0.92274741
A39: Marketplace Fulfilment | B39: -900844 | C39: -234691 | D39: - | E39: -76999 | F39: -176 | G39: -1213145 | I39: -955288.1 | J39: -360868.49 | K39: 0 | L39: -54308.467 | N39: -1370465.1 | P39: =IFERROR((I39-B39)/B39,0) -> 0.060436773 | Q39: =IFERROR((J39-C39)/C39,0) -> 0.53763243 | R39: =IFERROR((K39-D39)/D39,0) -> 0 | S39: =IFERROR((L39-E39)/E39,0) -> -0.29468608 | T39: =IFERROR((M39-F39)/F39,0) -> -1 | U39: =IFERROR((N39-G39)/G39,0) -> 0.12967952 | W39: -964840.99 | X39: -436986.47 | Y39: 0 | Z39: -54308.467 | AB39: -1456135.9 | AD39: =IFERROR((W39-I39)/I39,0) -> 0.01 | AE39: =IFERROR((X39-J39)/J39,0) -> 0.21092997 | AF39: =IFERROR((Y39-K39)/K39,0) -> 0 | AG39: =IFERROR((Z39-L39)/L39,0) -> 0 | AH39: =IFERROR((AA39-M39)/M39,0) -> 0 | AI39: =IFERROR((AB39-N39)/N39,0) -> 0.062512254 | AK39: -1038802 | AL39: -578648.3 | AM39: 0 | AN39: -54308.467 | AP39: -1671758.8 | AR39: =IFERROR((AK39-B39)/B39,0) -> 0.15314306 | AS39: =IFERROR((AL39-C39)/C39,0) -> 1.4655752 | AT39: =IFERROR((AM39-D39)/D39,0) -> 0 | AU39: =IFERROR((AN39-E39)/E39,0) -> -0.29468608 | AV39: =IFERROR((AO39-F39)/F39,0) -> -1 | AW39: =IFERROR((AP39-G39)/G39,0) -> 0.37803707 | AY39: -1049190 | AZ39: -1014837.7 | BA39: 0 | BB39: -54308.467 | BD39: -2118336.2 | BF39: =IFERROR((AY39-I39)/I39,0) -> 0.098296965 | BG39: =IFERROR((AZ39-J39)/J39,0) -> 1.8122092 | BH39: =IFERROR((BA39-K39)/K39,0) -> 0 | BI39: =IFERROR((BB39-L39)/L39,0) -> 0 | BJ39: =IFERROR((BC39-M39)/M39,0) -> 0 | BK39: =IFERROR((BD39-N39)/N39,0) -> 0.54570609
A40: TikTok Fulfilment | B40: -27114 | C40: -1531 | D40: -6 | E40: -87 | F40: -526 | G40: -29264 | I40: 0 | J40: 0 | K40: 0 | L40: 0 | N40: 0 | P40: =IFERROR((I40-B40)/B40,0) -> -1 | Q40: =IFERROR((J40-C40)/C40,0) -> -1 | R40: =IFERROR((K40-D40)/D40,0) -> -1 | S40: =IFERROR((L40-E40)/E40,0) -> -1 | T40: =IFERROR((M40-F40)/F40,0) -> -1 | U40: =IFERROR((N40-G40)/G40,0) -> -1 | W40: 0 | X40: 0 | Y40: 0 | Z40: 0 | AB40: 0 | AD40: =IFERROR((W40-I40)/I40,0) -> 0 | AE40: =IFERROR((X40-J40)/J40,0) -> 0 | AF40: =IFERROR((Y40-K40)/K40,0) -> 0 | AG40: =IFERROR((Z40-L40)/L40,0) -> 0 | AH40: =IFERROR((AA40-M40)/M40,0) -> 0 | AI40: =IFERROR((AB40-N40)/N40,0) -> 0 | AK40: 0 | AL40: 0 | AM40: 0 | AN40: 0 | AP40: 0 | AR40: =IFERROR((AK40-B40)/B40,0) -> -1 | AS40: =IFERROR((AL40-C40)/C40,0) -> -1 | AT40: =IFERROR((AM40-D40)/D40,0) -> -1 | AU40: =IFERROR((AN40-E40)/E40,0) -> -1 | AV40: =IFERROR((AO40-F40)/F40,0) -> -1 | AW40: =IFERROR((AP40-G40)/G40,0) -> -1 | AY40: 0 | AZ40: 0 | BA40: 0 | BB40: 0 | BD40: 0 | BF40: =IFERROR((AY40-I40)/I40,0) -> 0 | BG40: =IFERROR((AZ40-J40)/J40,0) -> 0 | BH40: =IFERROR((BA40-K40)/K40,0) -> 0 | BI40: =IFERROR((BB40-L40)/L40,0) -> 0 | BJ40: =IFERROR((BC40-M40)/M40,0) -> 0 | BK40: =IFERROR((BD40-N40)/N40,0) -> 0
A42: Total Fulfilment | B42: =SUM(B36:B41) -> -1403598 | C42: =SUM(C36:C41) -> -558569 | D42: =SUM(D36:D41) -> -870260 | E42: =SUM(E36:E41) -> -181812 | F42: =SUM(F36:F41) -> -377576 | G42: =SUM(G36:G41) -> -3406969 | I42: -1834151.7 | J42: -808675.65 | K42: -1213317 | L42: -54308.467 | M42: -300000 | N42: -4210452.7 | W42: -2741675.7 | X42: -1291044.3 | Y42: -1396342 | Z42: -164373.67 | AA42: -300000 | AB42: -5893435.6 | AD42: =IFERROR((W42-I42)/I42,0) -> 0.49479223 | AE42: =IFERROR((X42-J42)/J42,0) -> 0.59649207 | AF42: =IFERROR((Y42-K42)/K42,0) -> 0.15084684 | AG42: =IFERROR((Z42-L42)/L42,0) -> 2.0266674 | AH42: =IFERROR((AA42-M42)/M42,0) -> 0 | AI42: =IFERROR((AB42-N42)/N42,0) -> 0.39971541 | AK42: -1972285.7 | AL42: -1160920.6 | AM42: -1294901.3 | AN42: -83982.274 | AO42: -300000 | AP42: -4812089.8 | AR42: =IFERROR((AK42-B42)/B42,0) -> 0.40516423 | AS42: =IFERROR((AL42-C42)/C42,0) -> 1.0783834 | AT42: =IFERROR((AM42-D42)/D42,0) -> 0.48794764 | AU42: =IFERROR((AN42-E42)/E42,0) -> -0.53808179 | AV42: =IFERROR((AO42-F42)/F42,0) -> -0.20545797 | AW42: =IFERROR((AP42-G42)/G42,0) -> 0.41242548 | AY42: -2842354.4 | AZ42: -2282549 | BA42: -1498475 | BB42: -238340.52 | BC42: -300000 | BD42: -7161718.9 | BF42: =IFERROR((AY42-I42)/I42,0) -> 0.54968342 | BG42: =IFERROR((AZ42-J42)/J42,0) -> 1.8225766 | BH42: =IFERROR((BA42-K42)/K42,0) -> 0.23502354 | BI42: =IFERROR((BB42-L42)/L42,0) -> 3.388644 | BJ42: =IFERROR((BC42-M42)/M42,0) -> 0 | BK42: =IFERROR((BD42-N42)/N42,0) -> 0.70093797
A43: Fulfilment % Rev | B43: =B42/B11 -> -0.17314209 | C43: =C42/C11 -> -0.18607566 | D43: =D42/D11 -> -0.15558227 | E43: =E42/E11 -> -0.13728644 | G43: =G42/G11 -> -0.18898521 | I43: =I42/I11 -> -0.16142647 | J43: =J42/J11 -> -0.18797634 | K43: =K42/K11 -> -0.17738133 | L43: =L42/L11 -> -0.060685542 | N43: =N42/N11 -> -0.17993976 | AK43: 0.1597736 | AL43: 0.19839533 | AM43: 0.17790843 | AN43: 0.15448897 | AP43: 0.18515721 | AY43: 0.15294408 | AZ43: 0.20024314 | BA43: 0.17869349 | BB43: 0.12119301 | BD43: 0.18158262
A45: DTC CM2 | B45: =IFERROR(B22+B37,0) -> 1409790 | C45: =IFERROR(C22+C37,0) -> 630333 | D45: =IFERROR(D22+D37,0) -> 2847439 | E45: =IFERROR(E22+E37,0) -> 13170 | F45: =IFERROR(F22+F37,0) -> -16042 | G45: =IFERROR(G22+G37,0) -> 4850118 | I45: =IFERROR(I22+I37,0) -> 3161017.8 | J45: =IFERROR(J22+J37,0) -> 944216.3 | K45: =IFERROR(K22+K37,0) -> 3413062.9 | L45: =IFERROR(L22+L37,0) -> 0 | M45: =IFERROR(M22+M37,0) -> -300000 | N45: =IFERROR(N22+N37,0) -> 7518297 | W45: =IFERROR(W22+W37,0) -> 7368611.8 | X45: =IFERROR(X22+X37,0) -> 1973911.2 | Y45: =IFERROR(Y22+Y37,0) -> 3930590.9 | Z45: =IFERROR(Z22+Z37,0) -> 0 | AA45: =IFERROR(AA22+AA37,0) -> -300000 | AB45: =IFERROR(AB22+AB37,0) -> 13273114 | AK45: 3270086.8 | AL45: 1225994.6 | AM45: 3648076.2 | AN45: 0 | AO45: =IFERROR(AO22+AO37,0) -> -300000 | AP45: 8144157.6 | AY45: 7526094.3 | AZ45: 2917185.7 | BA45: 4231034.7 | BB45: 0 | BC45: =IFERROR(BC22+BC37,0) -> -300000 | BD45: 14674315
A46: B2B CM2 | B46: =IFERROR(B23+B38,0) -> 2394569 | C46: =IFERROR(C23+C38,0) -> 744975 | D46: =IFERROR(D23+D38,0) -> 370468 | E46: =IFERROR(E23+E38,0) -> 601934 | F46: =IFERROR(F23+F38,0) -> 5673 | G46: =IFERROR(G23+G38,0) -> 4169107 | I46: =IFERROR(I23+I38,0) -> 2893976.9 | J46: =IFERROR(J23+J38,0) -> 1100825.8 | K46: =IFERROR(K23+K38,0) -> 441367.47 | L46: =IFERROR(L23+L38,0) -> 481798.04 | M46: =IFERROR(M23+M38,0) -> 0 | N46: =IFERROR(N23+N38,0) -> 4917968.2 | W46: =IFERROR(W23+W38,0) -> 3443368.7 | X46: =IFERROR(X23+X38,0) -> 1582420.9 | Y46: =IFERROR(Y23+Y38,0) -> 499723.84 | Z46: =IFERROR(Z23+Z38,0) -> 388534.78 | AA46: =IFERROR(AA23+AA38,0) -> 0 | AB46: =IFERROR(AB23+AB38,0) -> 5914048.2 | AK46: 3316546 | AL46: 1601363.3 | AM46: 538203.77 | AN46: 254100.16 | AO46: =IFERROR(AO23+AO38,0) -> 0 | AP46: 5681536 | AY46: 3229453.6 | AZ46: 2660767.4 | BA46: 588473.96 | BB46: 1067385.9 | BC46: =IFERROR(BC23+BC38,0) -> 0 | BD46: 6651127.8
A47: Marketplace CM2 | B47: =IFERROR(B24+B39,0) -> 933990 | C47: =IFERROR(C24+C39,0) -> 264399 | D47: =IFERROR(D24+D39,0) -> 0 | E47: =IFERROR(E24+E39,0) -> 38331 | F47: =IFERROR(F24+F39,0) -> -176 | G47: =IFERROR(G24+G39,0) -> 1237365 | I47: =IFERROR(I24+I39,0) -> 968483.37 | J47: =IFERROR(J24+J39,0) -> 321433.84 | K47: =IFERROR(K24+K39,0) -> 0 | L47: =IFERROR(L24+L39,0) -> 49256.516 | M47: =IFERROR(M24+M39,0) -> 0 | N47: =IFERROR(N24+N39,0) -> 1339173.7 | W47: =IFERROR(W24+W39,0) -> 978168.2 | X47: =IFERROR(X24+X39,0) -> 389233.87 | Y47: =IFERROR(Y24+Y39,0) -> 0 | Z47: =IFERROR(Z24+Z39,0) -> 49256.516 | AA47: =IFERROR(AA24+AA39,0) -> 0 | AB47: =IFERROR(AB24+AB39,0) -> 1416658.6 | AK47: 1053150.8 | AL47: 515415.31 | AM47: 0 | AN47: 49256.516 | AO47: =IFERROR(AO24+AO39,0) -> 0 | AP47: 1617822.7 | AY47: 1063682.3 | AZ47: 903939.21 | BA47: 0 | BB47: 49256.516 | BC47: =IFERROR(BC24+BC39,0) -> 0 | BD47: 2016878.1
A48: TikTok CM2 | B48: =IFERROR(B25+B40,0) -> 43769 | C48: =IFERROR(C25+C40,0) -> -1531 | D48: =IFERROR(D25+D40,0) -> -6 | E48: =IFERROR(E25+E40,0) -> -87 | F48: =IFERROR(F25+F40,0) -> -526 | G48: =IFERROR(G25+G40,0) -> 41619 | I48: =IFERROR(I25+I40,0) -> 0 | J48: =IFERROR(J25+J40,0) -> 0 | K48: =IFERROR(K25+K40,0) -> 0 | L48: =IFERROR(L25+L40,0) -> 0 | M48: =IFERROR(M25+M40,0) -> 0 | N48: =IFERROR(N25+N40,0) -> 0 | W48: =IFERROR(W25+W40,0) -> 0 | X48: =IFERROR(X25+X40,0) -> 0 | Y48: =IFERROR(Y25+Y40,0) -> 0 | Z48: =IFERROR(Z25+Z40,0) -> 0 | AA48: =IFERROR(AA25+AA40,0) -> 0 | AB48: =IFERROR(AB25+AB40,0) -> 0 | AK48: 0 | AL48: 0 | AM48: 0 | AN48: 0 | AO48: =IFERROR(AO25+AO40,0) -> 0 | AP48: 0 | AY48: 0 | AZ48: 0 | BA48: 0 | BB48: 0 | BC48: =IFERROR(BC25+BC40,0) -> 0 | BD48: 0
A49: Total CM2 | B49: =IFERROR(B26+B42,0) -> 4773216 | C49: =IFERROR(C26+C42,0) -> 1652374 | D49: =IFERROR(D26+D42,0) -> 3217902 | E49: =IFERROR(E26+E42,0) -> 653221 | F49: =IFERROR(F26+F42,0) -> -351464 | G49: =IFERROR(G26+G42,0) -> 9947618 | I49: =IFERROR(I26+I42,0) -> 7023478.1 | J49: =IFERROR(J26+J42,0) -> 2366476 | K49: =IFERROR(K26+K42,0) -> 3854430.4 | L49: =IFERROR(L26+L42,0) -> 531054.56 | M49: =IFERROR(M26+M42,0) -> -300000 | N49: =IFERROR(N26+N42,0) -> 13475439 | W49: =IFERROR(W26+W42,0) -> 11790149 | X49: =IFERROR(X26+X42,0) -> 3945566 | Y49: =IFERROR(Y26+Y42,0) -> 4430314.8 | Z49: =IFERROR(Z26+Z42,0) -> 437791.3 | AA49: =IFERROR(AA26+AA42,0) -> -300000 | AB49: =IFERROR(AB26+AB42,0) -> 20303821 | AK49: 7639783.6 | AL49: 3342773.2 | AM49: 4186280 | AN49: 303356.67 | AO49: =IFERROR(AO26+AO42,0) -> -300000 | AP49: 15143516 | AY49: 11819230 | AZ49: 6481892.3 | BA49: 4819508.7 | BB49: 1116642.5 | BC49: =IFERROR(BC26+BC42,0) -> -300000 | BD49: 23042321
A51: DTC CM2% | B51: =IFERROR(B45/B6,0) -> 0.64000025 | C51: =IFERROR(C45/C6,0) -> 0.54673218 | D51: =IFERROR(D45/D6,0) -> 0.57515759 | E51: =IFERROR(E45/E6,0) -> 0.28263016 | F51: =IFERROR(F45/F6,0) -> 0 | G51: =IFERROR(G45/G6,0) -> 0.5806428 | I51: =IFERROR(I45/I6,0) -> 0.65337476 | J51: =IFERROR(J45/J6,0) -> 0.56668903 | K51: =IFERROR(K45/K6,0) -> 0.56668903 | L51: =IFERROR(L45/L6,0) -> 0 | M51: =IFERROR(M45/M6,0) -> 0 | N51: =IFERROR(N45/N6,0) -> 0.60016747 | W51: =IFERROR(W45/W6,0) -> 0.66337476 | X51: =IFERROR(X45/X6,0) -> 0.56668903 | Y51: =IFERROR(Y45/Y6,0) -> 0.56668903 | Z51: =IFERROR(Z45/Z6,0) -> 0 | AA51: =IFERROR(AA45/AA6,0) -> 0 | AB51: =IFERROR(AB45/AB6,0) -> 0.61657797 | AK51: 0.65337476 | AL51: 0.56668903 | AM51: 0.56668903 | AN51: 0 | AO51: =IFERROR(AO45/AO6,0) -> 0 | AP51: 0.59857634 | AY51: 0.66337476 | AZ51: 0.56668903 | BA51: 0.56668903 | BB51: 0 | BC51: =IFERROR(BC45/BC6,0) -> 0 | BD51: 0.61247172
A52: B2B CM2% | B52: =IFERROR(B46/B7,0) -> 0.66574576 | C52: =IFERROR(C46/C7,0) -> 0.5993358 | D52: =IFERROR(D46/D7,0) -> 0.57628368 | E52: =IFERROR(E46/E7,0) -> 0.52516029 | F52: =IFERROR(F46/F7,0) -> 0 | G52: =IFERROR(G46/G7,0) -> 0.62892296 | I52: =IFERROR(I46/I7,0) -> 0.69265368 | J52: =IFERROR(J46/J7,0) -> 0.61030414 | K52: =IFERROR(K46/K7,0) -> 0.54 | L52: =IFERROR(L46/L7,0) -> 0.62683735 | M52: =IFERROR(M46/M7,0) -> 0 | N52: =IFERROR(N46/N7,0) -> 0.64985454 | W52: =IFERROR(W46/W7,0) -> 0.69265368 | X52: =IFERROR(X46/X7,0) -> 0.61030414 | Y52: =IFERROR(Y46/Y7,0) -> 0.54 | Z52: =IFERROR(Z46/Z7,0) -> 0.48846395 | AA52: =IFERROR(AA46/AA7,0) -> 0 | AB52: =IFERROR(AB46/AB7,0) -> 0.63695017 | AK52: 0.69265368 | AL52: 0.68030414 | AM52: 0.64 | AN52: 0.60889344 | AO52: =IFERROR(AO46/AO7,0) -> 0 | AP52: 0.67866402 | AY52: 0.69265368 | AZ52: 0.68030414 | BA52: 0.64 | BB52: 0.58 | BC52: =IFERROR(BC46/BC7,0) -> 0 | BD52: 0.63717653
A53: Marketplace CM2% | B53: =IFERROR(B47/B8,0) -> 0.42125968 | C53: =IFERROR(C47/C8,0) -> 0.43635526 | D53: =IFERROR(D47/D8,0) -> 0 | E53: =IFERROR(E47/E8,0) -> 0.2914085 | F53: =IFERROR(F47/F8,0) -> 0 | G53: =IFERROR(G47/G8,0) -> 0.4186152 | I53: =IFERROR(I47/I8,0) -> 0.41281221 | J53: =IFERROR(J47/J8,0) -> 0.38630346 | K53: =IFERROR(K47/K8,0) -> 0 | L53: =IFERROR(L47/L8,0) -> 0.39 | M53: =IFERROR(M47/M8,0) -> 0 | N53: =IFERROR(N47/N8,0) -> 0.40526525 | W53: =IFERROR(W47/W8,0) -> 0.41281221 | X53: =IFERROR(X47/X8,0) -> 0.38630346 | Y53: =IFERROR(Y47/Y8,0) -> 0 | Z53: =IFERROR(Z47/Z8,0) -> 0.39 | AA53: =IFERROR(AA47/AA8,0) -> 0 | AB53: =IFERROR(AB47/AB8,0) -> 0.40436587 | AK53: 0.41281221 | AL53: 0.38630346 | AM53: 0 | AN53: 0.39 | AO53: =IFERROR(AO47/AO8,0) -> 0 | AP53: 0.40327762 | AY53: 0.41281221 | AZ53: 0.38630346 | BA53: 0 | BB53: 0.39 | BC53: =IFERROR(BC47/BC8,0) -> 0 | BD53: 0.39994059
A54: TikTok CM2% | B54: =IFERROR(B48/B9,0) -> 0.48701487 | C54: =IFERROR(C48/C9,0) -> 0 | D54: =IFERROR(D48/D9,0) -> 0 | E54: =IFERROR(E48/E9,0) -> 0 | F54: =IFERROR(F48/F9,0) -> 0 | G54: =IFERROR(G48/G9,0) -> 0.46309195 | I54: =IFERROR(I48/I9,0) -> 0 | J54: =IFERROR(J48/J9,0) -> 0 | K54: =IFERROR(K48/K9,0) -> 0 | L54: =IFERROR(L48/L9,0) -> 0 | M54: =IFERROR(M48/M9,0) -> 0 | N54: =IFERROR(N48/N9,0) -> 0 | W54: =IFERROR(W48/W9,0) -> 0 | X54: =IFERROR(X48/X9,0) -> 0 | Y54: =IFERROR(Y48/Y9,0) -> 0 | Z54: =IFERROR(Z48/Z9,0) -> 0 | AA54: =IFERROR(AA48/AA9,0) -> 0 | AB54: =IFERROR(AB48/AB9,0) -> 0 | AK54: 0 | AL54: 0 | AM54: 0 | AN54: 0 | AO54: =IFERROR(AO48/AO9,0) -> 0 | AP54: 0 | AY54: 0 | AZ54: 0 | BA54: 0 | BB54: 0 | BC54: =IFERROR(BC48/BC9,0) -> 0 | BD54: 0
A55: Total CM2% | B55: =IFERROR(B49/B11,0) -> 0.58880434 | C55: =IFERROR(C49/C11,0) -> 0.55045409 | D55: =IFERROR(D49/D11,0) -> 0.57528611 | E55: =IFERROR(E49/E11,0) -> 0.49324789 | F55: =IFERROR(F49/F11,0) -> 0 | G55: =IFERROR(G49/G11,0) -> 0.55179623 | I55: =IFERROR(I49/I11,0) -> 0.61814696 | J55: =IFERROR(J49/J11,0) -> 0.55008643 | K55: =IFERROR(K49/K11,0) -> 0.56349989 | L55: =IFERROR(L49/L11,0) -> 0.59341269 | M55: =IFERROR(M49/M11,0) -> 0 | N55: =IFERROR(N49/N11,0) -> 0.5758923 | W55: =IFERROR(W49/W11,0) -> 0.63908233 | X55: =IFERROR(X49/X11,0) -> 0.55699532 | Y55: =IFERROR(Y49/Y11,0) -> 0.56354733 | Z55: =IFERROR(Z49/Z11,0) -> 0.47497192 | AA55: =IFERROR(AA49/AA11,0) -> 0 | AB55: =IFERROR(AB49/AB11,0) -> 0.59168214 | AK55: 0.61889396 | AL55: 0.5712627 | AM55: 0.57515927 | AN55: 0.55803751 | AO55: =IFERROR(AO49/AO11,0) -> 0 | AP55: 0.58268471 | AY55: 0.63598026 | AZ55: 0.56864254 | BA55: 0.57472754 | BB55: 0.56779796 | BC55: =IFERROR(BC49/BC11,0) -> 0 | BD55: 0.58422914
A57: Marketing
A59: D2C Model Marketing | B59: -29357 | C59: -22170 | D59: -45584 | E59: -1803 | F59: - | G59: -102084 | I59: -1983035.5 | J59: -454126.8 | K59: -1668508.6 | L59: 0 | N59: -4105670.9 | P59: =IFERROR((I59-B59)/B59,0) -> 66.548982 | Q59: =IFERROR((J59-C59)/C59,0) -> 19.483843 | R59: =IFERROR((K59-D59)/D59,0) -> 35.602945 | S59: =IFERROR((L59-E59)/E59,0) -> -1 | T59: =IFERROR((M59-F59)/F59,0) -> 0 | U59: =IFERROR((N59-G59)/G59,0) -> 39.218554 | W59: -3631417.9 | X59: -894498 | Y59: -2010460.3 | Z59: 0 | AB59: -6536376.2 | AD59: =IFERROR((W59-I59)/I59,0) -> 0.83124202 | AE59: =IFERROR((X59-J59)/J59,0) -> 0.96970978 | AF59: =IFERROR((Y59-K59)/K59,0) -> 0.20494451 | AG59: =IFERROR((Z59-L59)/L59,0) -> 0 | AH59: =IFERROR((AA59-M59)/M59,0) -> 0 | AI59: =IFERROR((AB59-N59)/N59,0) -> 0.59203608 | AK59: -2012017.9 | AL59: -528569 | AM59: -1826611.1 | AN59: 0 | AP59: -4367198 | AR59: =IFERROR((AK59-B59)/B59,0) -> 67.536223 | AS59: =IFERROR((AL59-C59)/C59,0) -> 22.841633 | AT59: =IFERROR((AM59-D59)/D59,0) -> 39.071322 | AU59: =IFERROR((AN59-E59)/E59,0) -> -1 | AV59: =IFERROR((AO59-F59)/F59,0) -> 0 | AW59: =IFERROR((AP59-G59)/G59,0) -> 41.780436 | AY59: -3631417.9 | AZ59: -1043382.4 | BA59: -2198601.7 | BB59: 0 | BD59: -6873402 | BF59: =IFERROR((AY59-I59)/I59,0) -> 0.83124202 | BG59: =IFERROR((AZ59-J59)/J59,0) -> 1.2975574 | BH59: =IFERROR((BA59-K59)/K59,0) -> 0.31770473 | BI59: =IFERROR((BB59-L59)/L59,0) -> 0 | BJ59: =IFERROR((BC59-M59)/M59,0) -> 0 | BK59: =IFERROR((BD59-N59)/N59,0) -> 0.67412395
A60: D2C Model Brand | B60: -157532 | C60: -6667 | D60: -38669 | E60: -141 | F60: -33062 | G60: -238036 | I60: -300000 | J60: -97500 | K60: -65000 | L60: 0 | N60: -462500 | P60: =IFERROR((I60-B60)/B60,0) -> 0.90437498 | Q60: =IFERROR((J60-C60)/C60,0) -> 13.624269 | R60: =IFERROR((K60-D60)/D60,0) -> 0.68093305 | S60: =IFERROR((L60-E60)/E60,0) -> -1 | T60: =IFERROR((M60-F60)/F60,0) -> -1 | U60: =IFERROR((N60-G60)/G60,0) -> 0.94298341 | W60: -300000 | X60: -50000 | Y60: -47500 | Z60: 0 | AB60: -397500 | AD60: =IFERROR((W60-I60)/I60,0) -> 0 | AE60: =IFERROR((X60-J60)/J60,0) -> -0.48717949 | AF60: =IFERROR((Y60-K60)/K60,0) -> -0.26923077 | AG60: =IFERROR((Z60-L60)/L60,0) -> 0 | AH60: =IFERROR((AA60-M60)/M60,0) -> 0 | AI60: =IFERROR((AB60-N60)/N60,0) -> -0.14054054 | AK60: -300000 | AL60: -46000 | AM60: -36600 | AN60: 0 | AP60: -382600 | AR60: =IFERROR((AK60-B60)/B60,0) -> 0.90437498 | AS60: =IFERROR((AL60-C60)/C60,0) -> 5.899655 | AT60: =IFERROR((AM60-D60)/D60,0) -> -0.053505392 | AU60: =IFERROR((AN60-E60)/E60,0) -> -1 | AV60: =IFERROR((AO60-F60)/F60,0) -> -1 | AW60: =IFERROR((AP60-G60)/G60,0) -> 0.6073199 | AY60: -300000 | AZ60: -50000 | BA60: -47500 | BB60: 0 | BD60: -397500 | BF60: =IFERROR((AY60-I60)/I60,0) -> 0 | BG60: =IFERROR((AZ60-J60)/J60,0) -> -0.48717949 | BH60: =IFERROR((BA60-K60)/K60,0) -> -0.26923077 | BI60: =IFERROR((BB60-L60)/L60,0) -> 0 | BJ60: =IFERROR((BC60-M60)/M60,0) -> 0 | BK60: =IFERROR((BD60-N60)/N60,0) -> -0.14054054
A61: Influencers | B61: -384535 | C61: -171284 | D61: -550373 | E61: -875 | F61: -2788 | G61: -1291522 | I61: 0 | J61: 0 | K61: 0 | L61: 0 | N61: 0 | P61: =IFERROR((I61-B61)/B61,0) -> -1 | Q61: =IFERROR((J61-C61)/C61,0) -> -1 | R61: =IFERROR((K61-D61)/D61,0) -> -1 | S61: =IFERROR((L61-E61)/E61,0) -> -1 | T61: =IFERROR((M61-F61)/F61,0) -> -1 | U61: =IFERROR((N61-G61)/G61,0) -> -1 | W61: 0 | X61: 0 | Y61: 0 | Z61: 0 | AB61: 0 | AD61: =IFERROR((W61-I61)/I61,0) -> 0 | AE61: =IFERROR((X61-J61)/J61,0) -> 0 | AF61: =IFERROR((Y61-K61)/K61,0) -> 0 | AG61: =IFERROR((Z61-L61)/L61,0) -> 0 | AH61: =IFERROR((AA61-M61)/M61,0) -> 0 | AI61: =IFERROR((AB61-N61)/N61,0) -> 0 | AK61: 0 | AL61: 0 | AM61: 0 | AN61: 0 | AP61: 0 | AR61: =IFERROR((AK61-B61)/B61,0) -> -1 | AS61: =IFERROR((AL61-C61)/C61,0) -> -1 | AT61: =IFERROR((AM61-D61)/D61,0) -> -1 | AU61: =IFERROR((AN61-E61)/E61,0) -> -1 | AV61: =IFERROR((AO61-F61)/F61,0) -> -1 | AW61: =IFERROR((AP61-G61)/G61,0) -> -1 | AY61: 0 | AZ61: 0 | BA61: 0 | BB61: 0 | BD61: 0 | BF61: =IFERROR((AY61-I61)/I61,0) -> 0 | BG61: =IFERROR((AZ61-J61)/J61,0) -> 0 | BH61: =IFERROR((BA61-K61)/K61,0) -> 0 | BI61: =IFERROR((BB61-L61)/L61,0) -> 0 | BJ61: =IFERROR((BC61-M61)/M61,0) -> 0 | BK61: =IFERROR((BD61-N61)/N61,0) -> 0
A62: PPC | B62: -98264 | C62: -128238 | D62: -291773 | E62: -4670 | F62: -1111 | G62: -390858 | I62: 0 | J62: 0 | K62: 0 | L62: 0 | N62: 0 | P62: =IFERROR((I62-B62)/B62,0) -> -1 | Q62: =IFERROR((J62-C62)/C62,0) -> -1 | R62: =IFERROR((K62-D62)/D62,0) -> -1 | S62: =IFERROR((L62-E62)/E62,0) -> -1 | T62: =IFERROR((M62-F62)/F62,0) -> -1 | U62: =IFERROR((N62-G62)/G62,0) -> -1 | W62: 0 | X62: 0 | Y62: 0 | Z62: 0 | AB62: 0 | AD62: =IFERROR((W62-I62)/I62,0) -> 0 | AE62: =IFERROR((X62-J62)/J62,0) -> 0 | AF62: =IFERROR((Y62-K62)/K62,0) -> 0 | AG62: =IFERROR((Z62-L62)/L62,0) -> 0 | AH62: =IFERROR((AA62-M62)/M62,0) -> 0 | AI62: =IFERROR((AB62-N62)/N62,0) -> 0 | AK62: 0 | AL62: 0 | AM62: 0 | AN62: 0 | AP62: 0 | AR62: =IFERROR((AK62-B62)/B62,0) -> -1 | AS62: =IFERROR((AL62-C62)/C62,0) -> -1 | AT62: =IFERROR((AM62-D62)/D62,0) -> -1 | AU62: =IFERROR((AN62-E62)/E62,0) -> -1 | AV62: =IFERROR((AO62-F62)/F62,0) -> -1 | AW62: =IFERROR((AP62-G62)/G62,0) -> -1 | AY62: 0 | AZ62: 0 | BA62: 0 | BB62: 0 | BD62: 0 | BF62: =IFERROR((AY62-I62)/I62,0) -> 0 | BG62: =IFERROR((AZ62-J62)/J62,0) -> 0 | BH62: =IFERROR((BA62-K62)/K62,0) -> 0 | BI62: =IFERROR((BB62-L62)/L62,0) -> 0 | BJ62: =IFERROR((BC62-M62)/M62,0) -> 0 | BK62: =IFERROR((BD62-N62)/N62,0) -> 0
A63: Paid Social | B63: -471592 | C63: -36523 | D63: -473860 | E63: - | F63: -7048 | G63: -1037672 | I63: 0 | J63: 0 | K63: 0 | L63: 0 | N63: 0 | P63: =IFERROR((I63-B63)/B63,0) -> -1 | Q63: =IFERROR((J63-C63)/C63,0) -> -1 | R63: =IFERROR((K63-D63)/D63,0) -> -1 | S63: =IFERROR((L63-E63)/E63,0) -> 0 | T63: =IFERROR((M63-F63)/F63,0) -> -1 | U63: =IFERROR((N63-G63)/G63,0) -> -1 | W63: 0 | X63: 0 | Y63: 0 | Z63: 0 | AB63: 0 | AD63: =IFERROR((W63-I63)/I63,0) -> 0 | AE63: =IFERROR((X63-J63)/J63,0) -> 0 | AF63: =IFERROR((Y63-K63)/K63,0) -> 0 | AG63: =IFERROR((Z63-L63)/L63,0) -> 0 | AH63: =IFERROR((AA63-M63)/M63,0) -> 0 | AI63: =IFERROR((AB63-N63)/N63,0) -> 0 | AK63: 0 | AL63: 0 | AM63: 0 | AN63: 0 | AP63: 0 | AR63: =IFERROR((AK63-B63)/B63,0) -> -1 | AS63: =IFERROR((AL63-C63)/C63,0) -> -1 | AT63: =IFERROR((AM63-D63)/D63,0) -> -1 | AU63: =IFERROR((AN63-E63)/E63,0) -> 0 | AV63: =IFERROR((AO63-F63)/F63,0) -> -1 | AW63: =IFERROR((AP63-G63)/G63,0) -> -1 | AY63: 0 | AZ63: 0 | BA63: 0 | BB63: 0 | BD63: 0 | BF63: =IFERROR((AY63-I63)/I63,0) -> 0 | BG63: =IFERROR((AZ63-J63)/J63,0) -> 0 | BH63: =IFERROR((BA63-K63)/K63,0) -> 0 | BI63: =IFERROR((BB63-L63)/L63,0) -> 0 | BJ63: =IFERROR((BC63-M63)/M63,0) -> 0 | BK63: =IFERROR((BD63-N63)/N63,0) -> 0
A64: Retail Partnerships | B64: -304795 | C64: -19396 | D64: -71770 | E64: -12882 | F64: -16852 | G64: -399083 | I64: -418980.69 | J64: -106918.74 | K64: -22359.666 | L64: 0 | N64: -548259.09 | P64: =IFERROR((I64-B64)/B64,0) -> 0.37463111 | Q64: =IFERROR((J64-C64)/C64,0) -> 4.5124117 | R64: =IFERROR((K64-D64)/D64,0) -> -0.68845386 | S64: =IFERROR((L64-E64)/E64,0) -> -1 | T64: =IFERROR((M64-F64)/F64,0) -> -1 | U64: =IFERROR((N64-G64)/G64,0) -> 0.37379716 | W64: -609545.44 | X64: -170209.31 | Y64: -17450.65 | Z64: 0 | AB64: -797205.4 | AD64: =IFERROR((W64-I64)/I64,0) -> 0.45482944 | AE64: =IFERROR((X64-J64)/J64,0) -> 0.59195026 | AF64: =IFERROR((Y64-K64)/K64,0) -> -0.21954785 | AG64: =IFERROR((Z64-L64)/L64,0) -> 0 | AH64: =IFERROR((AA64-M64)/M64,0) -> 0 | AI64: =IFERROR((AB64-N64)/N64,0) -> 0.4540669 | AK64: -460809.5 | AL64: -156938.62 | AM64: -22214.786 | AN64: 0 | AP64: -639962.91 | AR64: =IFERROR((AK64-B64)/B64,0) -> 0.51186701 | AS64: =IFERROR((AL64-C64)/C64,0) -> 7.0912877 | AT64: =IFERROR((AM64-D64)/D64,0) -> -0.69047253 | AU64: =IFERROR((AN64-E64)/E64,0) -> -1 | AV64: =IFERROR((AO64-F64)/F64,0) -> -1 | AW64: =IFERROR((AP64-G64)/G64,0) -> 0.60358348 | AY64: -610077.18 | AZ64: -236845.7 | BA64: -15820.197 | BB64: 0 | BD64: -862743.08 | BF64: =IFERROR((AY64-I64)/I64,0) -> 0.45609857 | BG64: =IFERROR((AZ64-J64)/J64,0) -> 1.2151936 | BH64: =IFERROR((BA64-K64)/K64,0) -> -0.29246723 | BI64: =IFERROR((BB64-L64)/L64,0) -> 0 | BJ64: =IFERROR((BC64-M64)/M64,0) -> 0 | BK64: =IFERROR((BD64-N64)/N64,0) -> 0.57360469
A65: Retros | B65: -1067456 | C65: -37303 | D65: - | E65: - | F65: - | G65: -1096909 | I65: -1202967.7 | J65: -71789.991 | K65: -22359.666 | L65: 0 | N65: -1297117.4 | P65: =IFERROR((I65-B65)/B65,0) -> 0.12694829 | Q65: =IFERROR((J65-C65)/C65,0) -> 0.92450985 | R65: =IFERROR((K65-D65)/D65,0) -> 0 | S65: =IFERROR((L65-E65)/E65,0) -> 0 | T65: =IFERROR((M65-F65)/F65,0) -> 0 | U65: =IFERROR((N65-G65)/G65,0) -> 0.18252049 | W65: -1140003.7 | X65: -100217.43 | Y65: -15873.2 | Z65: 0 | AB65: -1256094.3 | AD65: =IFERROR((W65-I65)/I65,0) -> -0.052340571 | AE65: =IFERROR((X65-J65)/J65,0) -> 0.3959806 | AF65: =IFERROR((Y65-K65)/K65,0) -> -0.29009675 | AG65: =IFERROR((Z65-L65)/L65,0) -> 0 | AH65: =IFERROR((AA65-M65)/M65,0) -> 0 | AI65: =IFERROR((AB65-N65)/N65,0) -> -0.031626313 | AK65: -1222235.5 | AL65: -98364.13 | AM65: -16041.854 | AN65: 0 | AP65: -1336641.5 | AR65: =IFERROR((AK65-B65)/B65,0) -> 0.14499852 | AS65: =IFERROR((AL65-C65)/C65,0) -> 1.636896 | AT65: =IFERROR((AM65-D65)/D65,0) -> 0 | AU65: =IFERROR((AN65-E65)/E65,0) -> 0 | AV65: =IFERROR((AO65-F65)/F65,0) -> 0 | AW65: =IFERROR((AP65-G65)/G65,0) -> 0.21855279 | AY65: -1124167.7 | AZ65: -135178.04 | BA65: -14242.747 | BB65: 0 | BD65: -1273588.5 | BF65: =IFERROR((AY65-I65)/I65,0) -> -0.065504703 | BG65: =IFERROR((AZ65-J65)/J65,0) -> 0.882965 | BH65: =IFERROR((BA65-K65)/K65,0) -> -0.36301613 | BI65: =IFERROR((BB65-L65)/L65,0) -> 0 | BJ65: =IFERROR((BC65-M65)/M65,0) -> 0 | BK65: =IFERROR((BD65-N65)/N65,0) -> -0.018139386
A66: Promo Funding | I66: -3274.9814 | J66: -72202.491 | K66: -33402.512 | L66: -36688.871 | N66: -145568.86 | P66: =IFERROR((I66-B66)/B66,0) -> 0 | Q66: =IFERROR((J66-C66)/C66,0) -> 0 | R66: =IFERROR((K66-D66)/D66,0) -> 0 | S66: =IFERROR((L66-E66)/E66,0) -> 0 | T66: =IFERROR((M66-F66)/F66,0) -> 0 | U66: =IFERROR((N66-G66)/G66,0) -> 0 | W66: -210406.34 | X66: -68597.728 | Y66: -35072.638 | Z66: -26002.131 | AB66: -340078.83 | AD66: =IFERROR((W66-I66)/I66,0) -> 63.246574 | AE66: =IFERROR((X66-J66)/J66,0) -> -0.049925744 | AF66: =IFERROR((Y66-K66)/K66,0) -> 0.05 | AG66: =IFERROR((Z66-L66)/L66,0) -> -0.29128015 | AH66: =IFERROR((AA66-M66)/M66,0) -> 0 | AI66: =IFERROR((AB66-N66)/N66,0) -> 1.336206 | AK66: 0 | AR66: =IFERROR((AK66-B66)/B66,0) -> 0 | AS66: =IFERROR((AL66-C66)/C66,0) -> 0 | AT66: =IFERROR((AM66-D66)/D66,0) -> 0 | AU66: =IFERROR((AN66-E66)/E66,0) -> 0 | AV66: =IFERROR((AO66-F66)/F66,0) -> 0 | AW66: =IFERROR((AP66-G66)/G66,0) -> 0 | AY66: 0 | BF66: =IFERROR((AY66-I66)/I66,0) -> -1 | BG66: =IFERROR((AZ66-J66)/J66,0) -> -1 | BH66: =IFERROR((BA66-K66)/K66,0) -> -1 | BI66: =IFERROR((BB66-L66)/L66,0) -> -1 | BJ66: =IFERROR((BC66-M66)/M66,0) -> 0 | BK66: =IFERROR((BD66-N66)/N66,0) -> -1
A67: Trade Shows | B67: -187 | C67: -32114 | D67: -441 | E67: -8024 | F67: -32935 | G67: -47333 | I67: 0 | J67: -39500 | K67: 0 | L67: -15000 | N67: -54500 | P67: =IFERROR((I67-B67)/B67,0) -> -1 | Q67: =IFERROR((J67-C67)/C67,0) -> 0.22999315 | R67: =IFERROR((K67-D67)/D67,0) -> -1 | S67: =IFERROR((L67-E67)/E67,0) -> 0.86939182 | T67: =IFERROR((M67-F67)/F67,0) -> -1 | U67: =IFERROR((N67-G67)/G67,0) -> 0.15141656 | W67: 0 | X67: -39500 | Y67: 0 | Z67: -15000 | AB67: -54500 | AD67: =IFERROR((W67-I67)/I67,0) -> 0 | AE67: =IFERROR((X67-J67)/J67,0) -> 0 | AF67: =IFERROR((Y67-K67)/K67,0) -> 0 | AG67: =IFERROR((Z67-L67)/L67,0) -> 0 | AH67: =IFERROR((AA67-M67)/M67,0) -> 0 | AI67: =IFERROR((AB67-N67)/N67,0) -> 0 | AK67: 0 | AL67: 0 | AM67: 0 | AN67: -15000 | AP67: -15000 | AR67: =IFERROR((AK67-B67)/B67,0) -> -1 | AS67: =IFERROR((AL67-C67)/C67,0) -> -1 | AT67: =IFERROR((AM67-D67)/D67,0) -> -1 | AU67: =IFERROR((AN67-E67)/E67,0) -> 0.86939182 | AV67: =IFERROR((AO67-F67)/F67,0) -> -1 | AW67: =IFERROR((AP67-G67)/G67,0) -> -0.68309636 | AY67: 0 | AZ67: 0 | BA67: 0 | BB67: -15000 | BD67: -15000 | BF67: =IFERROR((AY67-I67)/I67,0) -> 0 | BG67: =IFERROR((AZ67-J67)/J67,0) -> -1 | BH67: =IFERROR((BA67-K67)/K67,0) -> 0 | BI67: =IFERROR((BB67-L67)/L67,0) -> 0 | BJ67: =IFERROR((BC67-M67)/M67,0) -> 0 | BK67: =IFERROR((BD67-N67)/N67,0) -> -0.72477064
A68: Marketplace Marketing | B68: -526944 | C68: -131693 | D68: -18 | E68: -10227 | F68: -2309 | G68: -688261 | I68: -539594.44 | J68: -262885.97 | K68: 0 | L68: -10852.122 | N68: -813332.52 | P68: =IFERROR((I68-B68)/B68,0) -> 0.024007176 | Q68: =IFERROR((J68-C68)/C68,0) -> 0.99620303 | R68: =IFERROR((K68-D68)/D68,0) -> -1 | S68: =IFERROR((L68-E68)/E68,0) -> 0.061124709 | T68: =IFERROR((M68-F68)/F68,0) -> -1 | U68: =IFERROR((N68-G68)/G68,0) -> 0.18172107 | W68: -523615.8 | X68: -261124 | Y68: 0 | Z68: -14790.781 | AB68: -799530.58 | AD68: =IFERROR((W68-I68)/I68,0) -> -0.029612303 | AE68: =IFERROR((X68-J68)/J68,0) -> -0.0067023928 | AF68: =IFERROR((Y68-K68)/K68,0) -> 0 | AG68: =IFERROR((Z68-L68)/L68,0) -> 0.36293903 | AH68: =IFERROR((AA68-M68)/M68,0) -> 0 | AI68: =IFERROR((AB68-N68)/N68,0) -> -0.016969616 | AK68: -649895 | AL68: -556385.97 | AM68: 0 | AN68: -10852.122 | AP68: -1217133.1 | AR68: =IFERROR((AK68-B68)/B68,0) -> 0.2333284 | AS68: =IFERROR((AL68-C68)/C68,0) -> 3.2248712 | AT68: =IFERROR((AM68-D68)/D68,0) -> -1 | AU68: =IFERROR((AN68-E68)/E68,0) -> 0.061124709 | AV68: =IFERROR((AO68-F68)/F68,0) -> -1 | AW68: =IFERROR((AP68-G68)/G68,0) -> 0.76841792 | AY68: -569930.85 | AZ68: -735124 | BA68: 0 | BB68: -14790.781 | BD68: -1319845.6 | BF68: =IFERROR((AY68-I68)/I68,0) -> 0.056220766 | BG68: =IFERROR((AZ68-J68)/J68,0) -> 1.7963608 | BH68: =IFERROR((BA68-K68)/K68,0) -> 0 | BI68: =IFERROR((BB68-L68)/L68,0) -> 0.36293903 | BJ68: =IFERROR((BC68-M68)/M68,0) -> 0 | BK68: =IFERROR((BD68-N68)/N68,0) -> 0.62276264
A69: TikTok Marketing | B69: -1747 | C69: -15535 | D69: - | E69: - | F69: - | G69: -1752 | I69: 0 | J69: 0 | K69: 0 | L69: 0 | N69: 0 | P69: =IFERROR((I69-B69)/B69,0) -> -1 | Q69: =IFERROR((J69-C69)/C69,0) -> -1 | R69: =IFERROR((K69-D69)/D69,0) -> 0 | S69: =IFERROR((L69-E69)/E69,0) -> 0 | T69: =IFERROR((M69-F69)/F69,0) -> 0 | U69: =IFERROR((N69-G69)/G69,0) -> -1 | W69: 0 | X69: 0 | Y69: 0 | Z69: 0 | AB69: 0 | AD69: =IFERROR((W69-I69)/I69,0) -> 0 | AE69: =IFERROR((X69-J69)/J69,0) -> 0 | AF69: =IFERROR((Y69-K69)/K69,0) -> 0 | AG69: =IFERROR((Z69-L69)/L69,0) -> 0 | AH69: =IFERROR((AA69-M69)/M69,0) -> 0 | AI69: =IFERROR((AB69-N69)/N69,0) -> 0 | AK69: 0 | AL69: 0 | AM69: 0 | AN69: 0 | AP69: 0 | AR69: =IFERROR((AK69-B69)/B69,0) -> -1 | AS69: =IFERROR((AL69-C69)/C69,0) -> -1 | AT69: =IFERROR((AM69-D69)/D69,0) -> 0 | AU69: =IFERROR((AN69-E69)/E69,0) -> 0 | AV69: =IFERROR((AO69-F69)/F69,0) -> 0 | AW69: =IFERROR((AP69-G69)/G69,0) -> -1 | AY69: 0 | AZ69: 0 | BA69: 0 | BB69: 0 | BD69: 0 | BF69: =IFERROR((AY69-I69)/I69,0) -> 0 | BG69: =IFERROR((AZ69-J69)/J69,0) -> 0 | BH69: =IFERROR((BA69-K69)/K69,0) -> 0 | BI69: =IFERROR((BB69-L69)/L69,0) -> 0 | BJ69: =IFERROR((BC69-M69)/M69,0) -> 0 | BK69: =IFERROR((BD69-N69)/N69,0) -> 0
A71: Total Marketing | B71: =SUM(B59:B69) -> -3042409 | C71: =SUM(C59:C69) -> -600923 | D71: =SUM(D59:D69) -> -1472488 | E71: =SUM(E59:E69) -> -38622 | F71: =SUM(F59:F69) -> -96105 | G71: =SUM(G59:G69) -> -5293510 | I71: -4447853.3 | J71: -1104924 | K71: -1811630.5 | L71: -62540.993 | N71: -7426948.8 | P71: =IFERROR((I71-B71)/B71,0) -> 0.46195113 | Q71: =IFERROR((J71-C71)/C71,0) -> 0.83871142 | R71: =IFERROR((K71-D71)/D71,0) -> 0.23031936 | S71: =IFERROR((L71-E71)/E71,0) -> 0.61931007 | T71: =IFERROR((M71-F71)/F71,0) -> -1 | U71: =IFERROR((N71-G71)/G71,0) -> 0.40302914 | W71: -6414989.1 | X71: -1584146.5 | Y71: -2126356.8 | Z71: -55792.912 | AB71: -10181285 | AD71: =IFERROR((W71-I71)/I71,0) -> 0.44226636 | AE71: =IFERROR((X71-J71)/J71,0) -> 0.43371535 | AF71: =IFERROR((Y71-K71)/K71,0) -> 0.17372546 | AG71: =IFERROR((Z71-L71)/L71,0) -> -0.10789852 | AH71: =IFERROR((AA71-M71)/M71,0) -> 0 | AI71: =IFERROR((AB71-N71)/N71,0) -> 0.37085709 | AK71: -4644957.9 | AL71: -1386257.7 | AM71: -1901467.8 | AN71: -25852.122 | AP71: -7958535.6 | AR71: =IFERROR((AK71-B71)/B71,0) -> 0.52673685 | AS71: =IFERROR((AL71-C71)/C71,0) -> 1.3068808 | AT71: =IFERROR((AM71-D71)/D71,0) -> 0.29132991 | AU71: =IFERROR((AN71-E71)/E71,0) -> -0.3306374 | AV71: =IFERROR((AO71-F71)/F71,0) -> -1 | AW71: =IFERROR((AP71-G71)/G71,0) -> 0.5034515 | AY71: -6235593.6 | AZ71: -2200530.1 | BA71: -2276164.7 | BB71: -29790.781 | BD71: -10742079 | BF71: =IFERROR((AY71-I71)/I71,0) -> 0.40193329 | BG71: =IFERROR((AZ71-J71)/J71,0) -> 0.991567 | BH71: =IFERROR((BA71-K71)/K71,0) -> 0.25641773 | BI71: =IFERROR((BB71-L71)/L71,0) -> -0.52365993 | BJ71: =IFERROR((BC71-M71)/M71,0) -> 0 | BK71: =IFERROR((BD71-N71)/N71,0) -> 0.44636506
A72: Market % of Rev | B72: =B71/B11 -> -0.37529909 | C72: =C71/C11 -> -0.20018502 | D72: =D71/D11 -> -0.26324664 | E72: =E71/E11 -> -0.029163514 | G72: =G71/G11 -> -0.29363199 | I72: =I71/I11 -> -0.39146231 | J72: =J71/J11 -> -0.25683916 | K72: =K71/K11 -> -0.264852 | L72: =L71/L11 -> -0.069884759 | N72: =N71/N11 -> -0.31740135 | AK72: -0.37628505 | AM72: -0.2612455 | AP72: -0.30622458
A73: DTC CM3 | B73: =IFERROR(B45+SUM(B59:B63),0) -> 268510 | C73: =IFERROR(C45+SUM(C59:C63),0) -> 265451 | D73: =IFERROR(D45+SUM(D59:D63),0) -> 1447180 | E73: =IFERROR(E45+SUM(E59:E63),0) -> 5681 | F73: =IFERROR(F45+SUM(F59:F63),0) -> -60051 | G73: =IFERROR(G45+SUM(G59:G63),0) -> 1789946 | I73: =IFERROR(I45+SUM(I59:I63),0) -> 877982.38 | J73: =IFERROR(J45+SUM(J59:J63),0) -> 392589.5 | K73: =IFERROR(K45+SUM(K59:K63),0) -> 1679554.3 | L73: =IFERROR(L45+SUM(L59:L63),0) -> 0 | M73: =IFERROR(M45+SUM(M59:M63),0) -> -300000 | N73: =IFERROR(N45+SUM(N59:N63),0) -> 2950126.1 | W73: =IFERROR(W45+SUM(W59:W63),0) -> 3437194 | X73: =IFERROR(X45+SUM(X59:X63),0) -> 1029413.2 | Y73: =IFERROR(Y45+SUM(Y59:Y63),0) -> 1872630.6 | Z73: =IFERROR(Z45+SUM(Z59:Z63),0) -> 0 | AA73: =IFERROR(AA45+SUM(AA59:AA63),0) -> -300000 | AB73: =IFERROR(AB45+SUM(AB59:AB63),0) -> 6339237.7 | AK73: 958068.9 | AL73: 651425.6 | AM73: 1784865.1 | AN73: 0 | AP73: 3394359.6 | AY73: 3594676.5 | AZ73: 1823803.3 | BA73: 1984933 | BB73: 0 | BD73: 7403412.7
A74: B2B CM3 | B74: =IFERROR(B46+SUM(B64:B66),0) -> 1022318 | C74: =IFERROR(C46+SUM(C64:C66),0) -> 688276 | D74: =IFERROR(D46+SUM(D64:D66),0) -> 298698 | E74: =IFERROR(E46+SUM(E64:E66),0) -> 589052 | F74: =IFERROR(F46+SUM(F64:F66),0) -> -11179 | G74: =IFERROR(G46+SUM(G64:G66),0) -> 2673115 | I74: =IFERROR(I46+SUM(I64:I66),0) -> 1268753.5 | J74: =IFERROR(J46+SUM(J64:J66),0) -> 849914.63 | K74: =IFERROR(K46+SUM(K64:K66),0) -> 363245.62 | L74: =IFERROR(L46+SUM(L64:L66),0) -> 445109.17 | M74: =IFERROR(M46+SUM(M64:M66),0) -> 0 | N74: =IFERROR(N46+SUM(N64:N66),0) -> 2927022.9 | W74: =IFERROR(W46+SUM(W64:W66),0) -> 1483413.2 | X74: =IFERROR(X46+SUM(X64:X66),0) -> 1243396.4 | Y74: =IFERROR(Y46+SUM(Y64:Y66),0) -> 431327.35 | Z74: =IFERROR(Z46+SUM(Z64:Z66),0) -> 362532.65 | AA74: =IFERROR(AA46+SUM(AA64:AA66),0) -> 0 | AB74: =IFERROR(AB46+SUM(AB64:AB66),0) -> 3520669.6 | AK74: 1633500.9 | AL74: 1346060.6 | AM74: 499947.13 | AN74: 239100.16 | AP74: 3689931.6 | AY74: 1495208.7 | AZ74: 2288743.7 | BA74: 558411.02 | BB74: 1052385.9 | BD74: 4499796.2
A75: Marketplace CM3 | B75: =IFERROR(B47+SUM(B68),0) -> 407046 | C75: =IFERROR(C47+SUM(C68),0) -> 132706 | D75: =IFERROR(D47+SUM(D68),0) -> -18 | E75: =IFERROR(E47+SUM(E68),0) -> 28104 | F75: =IFERROR(F47+SUM(F68),0) -> -2485 | G75: =IFERROR(G47+SUM(G68),0) -> 549104 | I75: =IFERROR(I47+SUM(I68),0) -> 428888.93 | J75: =IFERROR(J47+SUM(J68),0) -> 58547.875 | K75: =IFERROR(K47+SUM(K68),0) -> 0 | L75: =IFERROR(L47+SUM(L68),0) -> 38404.394 | M75: =IFERROR(M47+SUM(M68),0) -> 0 | N75: =IFERROR(N47+SUM(N68),0) -> 525841.2 | W75: =IFERROR(W47+SUM(W68),0) -> 454552.4 | X75: =IFERROR(X47+SUM(X68),0) -> 128109.87 | Y75: =IFERROR(Y47+SUM(Y68),0) -> 0 | Z75: =IFERROR(Z47+SUM(Z68),0) -> 34465.735 | AA75: =IFERROR(AA47+SUM(AA68),0) -> 0 | AB75: =IFERROR(AB47+SUM(AB68),0) -> 617128 | AK75: 403255.83 | AL75: -40970.654 | AM75: 0 | AN75: 38404.394 | AP75: 400689.57 | AY75: 493751.49 | AZ75: 168815.21 | BA75: 0 | BB75: 34465.735 | BD75: 697032.44
A76: TikTok CM3 | B76: =IFERROR(B48+SUM(B69),0) -> 42022 | C76: =IFERROR(C48+SUM(C69),0) -> -17066 | D76: =IFERROR(D48+SUM(D69),0) -> -6 | E76: =IFERROR(E48+SUM(E69),0) -> -87 | F76: =IFERROR(F48+SUM(F69),0) -> -526 | G76: =IFERROR(G48+SUM(G69),0) -> 39867 | I76: =IFERROR(I48+SUM(I69),0) -> 0 | J76: =IFERROR(J48+SUM(J69),0) -> 0 | K76: =IFERROR(K48+SUM(K69),0) -> 0 | L76: =IFERROR(L48+SUM(L69),0) -> 0 | M76: =IFERROR(M48+SUM(M69),0) -> 0 | N76: =IFERROR(N48+SUM(N69),0) -> 0 | W76: =IFERROR(W48+SUM(W69),0) -> 0 | X76: =IFERROR(X48+SUM(X69),0) -> 0 | Y76: =IFERROR(Y48+SUM(Y69),0) -> 0 | Z76: =IFERROR(Z48+SUM(Z69),0) -> 0 | AA76: =IFERROR(AA48+SUM(AA69),0) -> 0 | AB76: =IFERROR(AB48+SUM(AB69),0) -> 0 | AK76: 0 | AL76: 0 | AM76: 0 | AN76: 0 | AP76: 0 | AY76: 0 | AZ76: 0 | BA76: 0 | BB76: 0 | BD76: 0
A77: Total CM3 | B77: =IFERROR(B49+SUM(B71),0) -> 1730807 | C77: =IFERROR(C49+SUM(C71),0) -> 1051451 | D77: =IFERROR(D49+SUM(D71),0) -> 1745414 | E77: =IFERROR(E49+SUM(E71),0) -> 614599 | F77: =IFERROR(F49+SUM(F71),0) -> -447569 | G77: =IFERROR(G49+SUM(G71),0) -> 4654108 | I77: =IFERROR(I49+SUM(I71),0) -> 2575624.8 | J77: =IFERROR(J49+SUM(J71),0) -> 1261552 | K77: =IFERROR(K49+SUM(K71),0) -> 2042799.9 | L77: =IFERROR(L49+SUM(L71),0) -> 468513.56 | M77: =IFERROR(M49+SUM(M71),0) -> -300000 | N77: =IFERROR(N49+SUM(N71),0) -> 6048490.2 | W77: =IFERROR(W49+SUM(W71),0) -> 5375159.5 | X77: =IFERROR(X49+SUM(X71),0) -> 2361419.5 | Y77: =IFERROR(Y49+SUM(Y71),0) -> 2303957.9 | Z77: =IFERROR(Z49+SUM(Z71),0) -> 381998.39 | AA77: =IFERROR(AA49+SUM(AA71),0) -> -300000 | AB77: =IFERROR(AB49+SUM(AB71),0) -> 10122535 | AK77: 2994825.7 | AL77: 1956515.5 | AM77: 2284812.2 | AN77: 277504.55 | AP77: 7184980.7 | AY77: 5583636.7 | AZ77: 4281362.2 | BA77: 2543344 | BB77: 1086851.7 | BD77: 12300241
A79: DTC CM3% | B79: =IFERROR(B73/B6,0) -> 0.12189508 | C79: =IFERROR(C73/C6,0) -> 0.23024434 | D79: =IFERROR(D73/D6,0) -> 0.29231761 | E79: =IFERROR(E73/E6,0) -> 0.1219151 | F79: =IFERROR(F73/F6,0) -> 0 | G79: =IFERROR(G73/G6,0) -> 0.21428742 | I79: =IFERROR(I73/I6,0) -> 0.18147684 | J79: =IFERROR(J73/J6,0) -> 0.23561991 | K79: =IFERROR(K73/K6,0) -> 0.27886535 | L79: =IFERROR(L73/L6,0) -> 0 | M79: =IFERROR(M73/M6,0) -> 0 | N79: =IFERROR(N73/N6,0) -> 0.23550143 | W79: =IFERROR(W73/W6,0) -> 0.30944061 | X79: =IFERROR(X73/X6,0) -> 0.29553364 | Y79: =IFERROR(Y73/Y6,0) -> 0.26998465 | Z79: =IFERROR(Z73/Z6,0) -> 0 | AA79: =IFERROR(AA73/AA6,0) -> 0 | AB79: =IFERROR(AB73/AB6,0) -> 0.29447757 | AK79: 0.19142551 | AL79: 0.30110715 | AM79: 0.27725941 | AN79: 0 | AP79: 0.24947741 | AY79: 0.31684663 | AZ79: 0.35428986 | BA79: 0.26585453 | BB79: 0 | BD79: 0.3090012
A80: B2B CM3% | B80: =IFERROR(B74/B7,0) -> 0.28422813 | C80: =IFERROR(C74/C7,0) -> 0.5537212 | D80: =IFERROR(D74/D7,0) -> 0.46464144 | E80: =IFERROR(E74/E7,0) -> 0.51392133 | F80: =IFERROR(F74/F7,0) -> 0 | G80: =IFERROR(G74/G7,0) -> 0.40324784 | I80: =IFERROR(I74/I7,0) -> 0.30366752 | J80: =IFERROR(J74/J7,0) -> 0.47119752 | K80: =IFERROR(K74/K7,0) -> 0.44442024 | L80: =IFERROR(L74/L7,0) -> 0.57910375 | M80: =IFERROR(M74/M7,0) -> 0 | N80: =IFERROR(N74/N7,0) -> 0.38677337 | W80: =IFERROR(W74/W7,0) -> 0.29839721 | X80: =IFERROR(X74/X7,0) -> 0.47955003 | Y80: =IFERROR(Y74/Y7,0) -> 0.46609097 | Z80: =IFERROR(Z74/Z7,0) -> 0.4557742 | AA80: =IFERROR(AA74/AA7,0) -> 0 | AB80: =IFERROR(AB74/AB7,0) -> 0.3791804 | AK80: 0.34115325 | AL80: 0.57184436 | AM80: 0.59450747 | AN80: 0.57294934 | AP80: 0.44076528 | AY80: 0.32069258 | AZ80: 0.58518523 | BA80: 0.60730478 | BB80: 0.57184925 | BD80: 0.43107945
A81: Marketplace CM3% | B81: =IFERROR(B75/B8,0) -> 0.1835909 | C81: =IFERROR(C75/C8,0) -> 0.21901354 | D81: =IFERROR(D75/D8,0) -> 0 | E81: =IFERROR(E75/E8,0) -> 0.21365851 | F81: =IFERROR(F75/F8,0) -> 0 | G81: =IFERROR(G75/G8,0) -> 0.18576837 | I81: =IFERROR(I75/I8,0) -> 0.18281221 | J81: =IFERROR(J75/J8,0) -> 0.070363613 | K81: =IFERROR(K75/K8,0) -> 0 | L81: =IFERROR(L75/L8,0) -> 0.30407578 | M81: =IFERROR(M75/M8,0) -> 0 | N81: =IFERROR(N75/N8,0) -> 0.15913183 | W81: =IFERROR(W75/W8,0) -> 0.19183284 | X81: =IFERROR(X75/X8,0) -> 0.12714537 | Y81: =IFERROR(Y75/Y8,0) -> 0 | Z81: =IFERROR(Z75/Z8,0) -> 0.27289053 | AA81: =IFERROR(AA75/AA8,0) -> 0 | AB81: =IFERROR(AB75/AB8,0) -> 0.17615077 | AK81: 0.15806751 | AL81: -0.03070748 | AM81: 0 | AN81: 0.30407578 | AP81: 0.099880625 | AY81: 0.19162361 | AZ81: 0.072144122 | BA81: 0 | BB81: 0.27289053 | BD81: 0.13821934
A82: TikTok CM3% | B82: =IFERROR(B76/B9,0) -> 0.46757611 | C82: =IFERROR(C76/C9,0) -> 0 | D82: =IFERROR(D76/D9,0) -> 0 | E82: =IFERROR(E76/E9,0) -> 0 | F82: =IFERROR(F76/F9,0) -> 0 | G82: =IFERROR(G76/G9,0) -> 0.44359756 | I82: =IFERROR(I76/I9,0) -> 0 | J82: =IFERROR(J76/J9,0) -> 0 | K82: =IFERROR(K76/K9,0) -> 0 | L82: =IFERROR(L76/L9,0) -> 0 | M82: =IFERROR(M76/M9,0) -> 0 | N82: =IFERROR(N76/N9,0) -> 0 | W82: =IFERROR(W76/W9,0) -> 0 | X82: =IFERROR(X76/X9,0) -> 0 | Y82: =IFERROR(Y76/Y9,0) -> 0 | Z82: =IFERROR(Z76/Z9,0) -> 0 | AA82: =IFERROR(AA76/AA9,0) -> 0 | AB82: =IFERROR(AB76/AB9,0) -> 0 | AK82: 0 | AL82: 0 | AM82: 0 | AN82: 0 | AP82: 0 | AY82: 0 | AZ82: 0 | BA82: 0 | BB82: 0 | BD82: 0
A83: Total CM3% | B83: =IFERROR(B77/B11,0) -> 0.21350525 | C83: =IFERROR(C77/C11,0) -> 0.35026907 | D83: =IFERROR(D77/D11,0) -> 0.31203947 | E83: =IFERROR(E77/E11,0) -> 0.46408437 | F83: =IFERROR(F77/F11,0) -> 0 | G83: =IFERROR(G77/G11,0) -> 0.25816424 | I83: =IFERROR(I77/I11,0) -> 0.22668464 | J83: =IFERROR(J77/J11,0) -> 0.29324728 | K83: =IFERROR(K77/K11,0) -> 0.29864789 | L83: =IFERROR(L77/L11,0) -> 0.52352794 | M83: =IFERROR(M77/M11,0) -> 0 | N83: =IFERROR(N77/N11,0) -> 0.25849094 | W83: =IFERROR(W77/W11,0) -> 0.2913593 | X83: =IFERROR(X77/X11,0) -> 0.33336145 | Y83: =IFERROR(Y77/Y11,0) -> 0.29306932 | Z83: =IFERROR(Z77/Z11,0) -> 0.41444064 | AA83: =IFERROR(AA77/AA11,0) -> 0 | AB83: =IFERROR(AB77/AB11,0) -> 0.29498504 | AK83: 0.2426089 | AL83: 0.33435841 | AM83: 0.31391377 | AN83: 0.51048143 | AP83: 0.27646012 | AY83: 0.30044958 | AZ83: 0.37559474 | BA83: 0.30329437 | BB83: 0.55264974 | BD83: 0.31186787
A85: Other Revenue | B85: 504 | C85: ='CE P&L'!Q84 -> 0 | D85: ='EE P&L'!Q84 -> 0 | E85: ='ROW P&L'!Q85 -> 0 | G85: =SUM(B85:F85) -> 504
N86: 0 | AB86: 0
A87: Other Overheads
A89: Staff Costs | B89: -25039 | C89: -57608 | D89: -58594 | E89: -201 | F89: -2111149 | G89: -2240925 | I89: 0 | J89: -82204.894 | K89: -237812.42 | L89: 0 | M89: -2788763.7 | N89: -3108781 | P89: =IFERROR((I89-B89)/B89,0) -> -1 | Q89: =IFERROR((J89-C89)/C89,0) -> 0.42697011 | R89: =IFERROR((K89-D89)/D89,0) -> 3.0586479 | S89: =IFERROR((L89-E89)/E89,0) -> -1 | T89: =IFERROR((M89-F89)/F89,0) -> 0.32096961 | U89: =IFERROR((N89-G89)/G89,0) -> 0.38727578 | W89: 0 | X89: -156792.39 | Y89: -243662.42 | Z89: 0 | AA89: -2765812.5 | AB89: -3166267.3 | AD89: =IFERROR((W89-I89)/I89,0) -> 0 | AE89: =IFERROR((X89-J89)/J89,0) -> 0.90733649 | AF89: =IFERROR((Y89-K89)/K89,0) -> 0.02459922 | AG89: =IFERROR((Z89-L89)/L89,0) -> 0 | AH89: =IFERROR((AA89-M89)/M89,0) -> -0.0082298862 | AI89: =IFERROR((AB89-N89)/N89,0) -> 0.018491587 | AK89: 0 | AL89: -82204.894 | AM89: -237812.42 | AO89: -2788763.7 | AP89: -3108781 | AR89: =IFERROR((AK89-B89)/B89,0) -> -1 | AS89: =IFERROR((AL89-C89)/C89,0) -> 0.42697011 | AT89: =IFERROR((AM89-D89)/D89,0) -> 3.0586479 | AU89: =IFERROR((AN89-E89)/E89,0) -> -1 | AV89: =IFERROR((AO89-F89)/F89,0) -> 0.32096961 | AW89: =IFERROR((AP89-G89)/G89,0) -> 0.38727578 | AY89: 0 | AZ89: -156792.39 | BA89: -243662.42 | BC89: -2765812.5 | BD89: -3166267.3 | BF89: =IFERROR((AY89-I89)/I89,0) -> 0 | BG89: =IFERROR((AZ89-J89)/J89,0) -> 0.90733649 | BH89: =IFERROR((BA89-K89)/K89,0) -> 0.02459922 | BI89: =IFERROR((BB89-L89)/L89,0) -> 0 | BJ89: =IFERROR((BC89-M89)/M89,0) -> -0.0082298862 | BK89: =IFERROR((BD89-N89)/N89,0) -> 0.018491587
A90: Freelancers | B90: -7275 | C90: - | D90: -100866 | E90: - | F90: -495610 | G90: -603748 | I90: -9000 | J90: 0 | K90: -214056.69 | L90: 0 | M90: -186421.95 | N90: -409478.64 | P90: =IFERROR((I90-B90)/B90,0) -> 0.2371134 | Q90: =IFERROR((J90-C90)/C90,0) -> 0 | R90: =IFERROR((K90-D90)/D90,0) -> 1.1221888 | S90: =IFERROR((L90-E90)/E90,0) -> 0 | T90: =IFERROR((M90-F90)/F90,0) -> -0.62385354 | U90: =IFERROR((N90-G90)/G90,0) -> -0.32177226 | W90: -9000 | X90: 0 | Y90: -214056.69 | Z90: 0 | AA90: -175489.75 | AB90: -398546.44 | AD90: =IFERROR((W90-I90)/I90,0) -> 0 | AE90: =IFERROR((X90-J90)/J90,0) -> 0 | AF90: =IFERROR((Y90-K90)/K90,0) -> 0 | AG90: =IFERROR((Z90-L90)/L90,0) -> 0 | AH90: =IFERROR((AA90-M90)/M90,0) -> -0.058642255 | AI90: =IFERROR((AB90-N90)/N90,0) -> -0.02669786 | AK90: -9000 | AL90: 0 | AM90: -214056.69 | AO90: -186421.95 | AP90: -409478.64 | AR90: =IFERROR((AK90-B90)/B90,0) -> 0.2371134 | AS90: =IFERROR((AL90-C90)/C90,0) -> 0 | AT90: =IFERROR((AM90-D90)/D90,0) -> 1.1221888 | AU90: =IFERROR((AN90-E90)/E90,0) -> 0 | AV90: =IFERROR((AO90-F90)/F90,0) -> -0.62385354 | AW90: =IFERROR((AP90-G90)/G90,0) -> -0.32177226 | AY90: -9000 | AZ90: 0 | BA90: -214056.69 | BC90: -175489.75 | BD90: -398546.44 | BF90: =IFERROR((AY90-I90)/I90,0) -> 0 | BG90: =IFERROR((AZ90-J90)/J90,0) -> 0 | BH90: =IFERROR((BA90-K90)/K90,0) -> 0 | BI90: =IFERROR((BB90-L90)/L90,0) -> 0 | BJ90: =IFERROR((BC90-M90)/M90,0) -> -0.058642255 | BK90: =IFERROR((BD90-N90)/N90,0) -> -0.02669786
A91: Consultancy | I91: 0 | N91: 0 | P91: =IFERROR((I91-B91)/B91,0) -> 0 | Q91: =IFERROR((J91-C91)/C91,0) -> 0 | R91: =IFERROR((K91-D91)/D91,0) -> 0 | S91: =IFERROR((L91-E91)/E91,0) -> 0 | T91: =IFERROR((M91-F91)/F91,0) -> 0 | U91: =IFERROR((N91-G91)/G91,0) -> 0 | W91: 0 | X91: 0 | Y91: 0 | Z91: 0 | AA91: 0 | AB91: -553036.57 | AD91: =IFERROR((W91-I91)/I91,0) -> 0 | AE91: =IFERROR((X91-J91)/J91,0) -> 0 | AF91: =IFERROR((Y91-K91)/K91,0) -> 0 | AG91: =IFERROR((Z91-L91)/L91,0) -> 0 | AH91: =IFERROR((AA91-M91)/M91,0) -> 0 | AI91: =IFERROR((AB91-N91)/N91,0) -> 0 | AK91: 0 | AP91: 0 | AR91: =IFERROR((AK91-B91)/B91,0) -> 0 | AS91: =IFERROR((AL91-C91)/C91,0) -> 0 | AT91: =IFERROR((AM91-D91)/D91,0) -> 0 | AU91: =IFERROR((AN91-E91)/E91,0) -> 0 | AV91: =IFERROR((AO91-F91)/F91,0) -> 0 | AW91: =IFERROR((AP91-G91)/G91,0) -> 0 | AY91: 0 | AZ91: 0 | BA91: 0 | BD91: -1168052.7 | BF91: =IFERROR((AY91-I91)/I91,0) -> 0 | BG91: =IFERROR((AZ91-J91)/J91,0) -> 0 | BH91: =IFERROR((BA91-K91)/K91,0) -> 0 | BI91: =IFERROR((BB91-L91)/L91,0) -> 0 | BJ91: =IFERROR((BC91-M91)/M91,0) -> 0 | BK91: =IFERROR((BD91-N91)/N91,0) -> 0
A92: Software | I92: 0 | N92: 0 | P92: =IFERROR((I92-B92)/B92,0) -> 0 | Q92: =IFERROR((J92-C92)/C92,0) -> 0 | R92: =IFERROR((K92-D92)/D92,0) -> 0 | S92: =IFERROR((L92-E92)/E92,0) -> 0 | T92: =IFERROR((M92-F92)/F92,0) -> 0 | U92: =IFERROR((N92-G92)/G92,0) -> 0 | W92: 0 | X92: 0 | Y92: 0 | Z92: 0 | AA92: 0 | AB92: 0 | AD92: =IFERROR((W92-I92)/I92,0) -> 0 | AE92: =IFERROR((X92-J92)/J92,0) -> 0 | AF92: =IFERROR((Y92-K92)/K92,0) -> 0 | AG92: =IFERROR((Z92-L92)/L92,0) -> 0 | AH92: =IFERROR((AA92-M92)/M92,0) -> 0 | AI92: =IFERROR((AB92-N92)/N92,0) -> 0 | AK92: 0 | AP92: 0 | AR92: =IFERROR((AK92-B92)/B92,0) -> 0 | AS92: =IFERROR((AL92-C92)/C92,0) -> 0 | AT92: =IFERROR((AM92-D92)/D92,0) -> 0 | AU92: =IFERROR((AN92-E92)/E92,0) -> 0 | AV92: =IFERROR((AO92-F92)/F92,0) -> 0 | AW92: =IFERROR((AP92-G92)/G92,0) -> 0 | AY92: 0 | AZ92: 0 | BA92: 0 | BD92: 0 | BF92: =IFERROR((AY92-I92)/I92,0) -> 0 | BG92: =IFERROR((AZ92-J92)/J92,0) -> 0 | BH92: =IFERROR((BA92-K92)/K92,0) -> 0 | BI92: =IFERROR((BB92-L92)/L92,0) -> 0 | BJ92: =IFERROR((BC92-M92)/M92,0) -> 0 | BK92: =IFERROR((BD92-N92)/N92,0) -> 0
A93: Telephone & Computer | I93: 0 | N93: 0 | P93: =IFERROR((I93-B93)/B93,0) -> 0 | Q93: =IFERROR((J93-C93)/C93,0) -> 0 | R93: =IFERROR((K93-D93)/D93,0) -> 0 | S93: =IFERROR((L93-E93)/E93,0) -> 0 | T93: =IFERROR((M93-F93)/F93,0) -> 0 | U93: =IFERROR((N93-G93)/G93,0) -> 0 | W93: 0 | X93: 0 | Y93: 0 | Z93: 0 | AA93: 0 | AB93: 0 | AD93: =IFERROR((W93-I93)/I93,0) -> 0 | AE93: =IFERROR((X93-J93)/J93,0) -> 0 | AF93: =IFERROR((Y93-K93)/K93,0) -> 0 | AG93: =IFERROR((Z93-L93)/L93,0) -> 0 | AH93: =IFERROR((AA93-M93)/M93,0) -> 0 | AI93: =IFERROR((AB93-N93)/N93,0) -> 0 | AK93: 0 | AP93: 0 | AR93: =IFERROR((AK93-B93)/B93,0) -> 0 | AS93: =IFERROR((AL93-C93)/C93,0) -> 0 | AT93: =IFERROR((AM93-D93)/D93,0) -> 0 | AU93: =IFERROR((AN93-E93)/E93,0) -> 0 | AV93: =IFERROR((AO93-F93)/F93,0) -> 0 | AW93: =IFERROR((AP93-G93)/G93,0) -> 0 | AY93: 0 | AZ93: 0 | BA93: 0 | BD93: 0 | BF93: =IFERROR((AY93-I93)/I93,0) -> 0 | BG93: =IFERROR((AZ93-J93)/J93,0) -> 0 | BH93: =IFERROR((BA93-K93)/K93,0) -> 0 | BI93: =IFERROR((BB93-L93)/L93,0) -> 0 | BJ93: =IFERROR((BC93-M93)/M93,0) -> 0 | BK93: =IFERROR((BD93-N93)/N93,0) -> 0
A94: Insurance | I94: 0 | N94: 0 | P94: =IFERROR((I94-B94)/B94,0) -> 0 | Q94: =IFERROR((J94-C94)/C94,0) -> 0 | R94: =IFERROR((K94-D94)/D94,0) -> 0 | S94: =IFERROR((L94-E94)/E94,0) -> 0 | T94: =IFERROR((M94-F94)/F94,0) -> 0 | U94: =IFERROR((N94-G94)/G94,0) -> 0 | W94: 0 | X94: 0 | Y94: 0 | Z94: 0 | AA94: 0 | AB94: 0 | AD94: =IFERROR((W94-I94)/I94,0) -> 0 | AE94: =IFERROR((X94-J94)/J94,0) -> 0 | AF94: =IFERROR((Y94-K94)/K94,0) -> 0 | AG94: =IFERROR((Z94-L94)/L94,0) -> 0 | AH94: =IFERROR((AA94-M94)/M94,0) -> 0 | AI94: =IFERROR((AB94-N94)/N94,0) -> 0 | AK94: 0 | AP94: 0 | AR94: =IFERROR((AK94-B94)/B94,0) -> 0 | AS94: =IFERROR((AL94-C94)/C94,0) -> 0 | AT94: =IFERROR((AM94-D94)/D94,0) -> 0 | AU94: =IFERROR((AN94-E94)/E94,0) -> 0 | AV94: =IFERROR((AO94-F94)/F94,0) -> 0 | AW94: =IFERROR((AP94-G94)/G94,0) -> 0 | AY94: 0 | AZ94: 0 | BA94: 0 | BD94: 0 | BF94: =IFERROR((AY94-I94)/I94,0) -> 0 | BG94: =IFERROR((AZ94-J94)/J94,0) -> 0 | BH94: =IFERROR((BA94-K94)/K94,0) -> 0 | BI94: =IFERROR((BB94-L94)/L94,0) -> 0 | BJ94: =IFERROR((BC94-M94)/M94,0) -> 0 | BK94: =IFERROR((BD94-N94)/N94,0) -> 0
A95: Office Costs | I95: 0 | N95: 0 | P95: =IFERROR((I95-B95)/B95,0) -> 0 | Q95: =IFERROR((J95-C95)/C95,0) -> 0 | R95: =IFERROR((K95-D95)/D95,0) -> 0 | S95: =IFERROR((L95-E95)/E95,0) -> 0 | T95: =IFERROR((M95-F95)/F95,0) -> 0 | U95: =IFERROR((N95-G95)/G95,0) -> 0 | W95: 0 | X95: 0 | Y95: 0 | Z95: 0 | AA95: 0 | AB95: 0 | AD95: =IFERROR((W95-I95)/I95,0) -> 0 | AE95: =IFERROR((X95-J95)/J95,0) -> 0 | AF95: =IFERROR((Y95-K95)/K95,0) -> 0 | AG95: =IFERROR((Z95-L95)/L95,0) -> 0 | AH95: =IFERROR((AA95-M95)/M95,0) -> 0 | AI95: =IFERROR((AB95-N95)/N95,0) -> 0 | AK95: 0 | AP95: 0 | AR95: =IFERROR((AK95-B95)/B95,0) -> 0 | AS95: =IFERROR((AL95-C95)/C95,0) -> 0 | AT95: =IFERROR((AM95-D95)/D95,0) -> 0 | AU95: =IFERROR((AN95-E95)/E95,0) -> 0 | AV95: =IFERROR((AO95-F95)/F95,0) -> 0 | AW95: =IFERROR((AP95-G95)/G95,0) -> 0 | AY95: 0 | AZ95: 0 | BA95: 0 | BD95: 0 | BF95: =IFERROR((AY95-I95)/I95,0) -> 0 | BG95: =IFERROR((AZ95-J95)/J95,0) -> 0 | BH95: =IFERROR((BA95-K95)/K95,0) -> 0 | BI95: =IFERROR((BB95-L95)/L95,0) -> 0 | BJ95: =IFERROR((BC95-M95)/M95,0) -> 0 | BK95: =IFERROR((BD95-N95)/N95,0) -> 0
A96: Travel & Entertainment | I96: 0 | N96: 0 | P96: =IFERROR((I96-B96)/B96,0) -> 0 | Q96: =IFERROR((J96-C96)/C96,0) -> 0 | R96: =IFERROR((K96-D96)/D96,0) -> 0 | S96: =IFERROR((L96-E96)/E96,0) -> 0 | T96: =IFERROR((M96-F96)/F96,0) -> 0 | U96: =IFERROR((N96-G96)/G96,0) -> 0 | W96: 0 | X96: 0 | Y96: 0 | Z96: 0 | AA96: 0 | AB96: 0 | AD96: =IFERROR((W96-I96)/I96,0) -> 0 | AE96: =IFERROR((X96-J96)/J96,0) -> 0 | AF96: =IFERROR((Y96-K96)/K96,0) -> 0 | AG96: =IFERROR((Z96-L96)/L96,0) -> 0 | AH96: =IFERROR((AA96-M96)/M96,0) -> 0 | AI96: =IFERROR((AB96-N96)/N96,0) -> 0 | AK96: 0 | AP96: 0 | AR96: =IFERROR((AK96-B96)/B96,0) -> 0 | AS96: =IFERROR((AL96-C96)/C96,0) -> 0 | AT96: =IFERROR((AM96-D96)/D96,0) -> 0 | AU96: =IFERROR((AN96-E96)/E96,0) -> 0 | AV96: =IFERROR((AO96-F96)/F96,0) -> 0 | AW96: =IFERROR((AP96-G96)/G96,0) -> 0 | AY96: 0 | AZ96: 0 | BA96: 0 | BD96: 0 | BF96: =IFERROR((AY96-I96)/I96,0) -> 0 | BG96: =IFERROR((AZ96-J96)/J96,0) -> 0 | BH96: =IFERROR((BA96-K96)/K96,0) -> 0 | BI96: =IFERROR((BB96-L96)/L96,0) -> 0 | BJ96: =IFERROR((BC96-M96)/M96,0) -> 0 | BK96: =IFERROR((BD96-N96)/N96,0) -> 0
A97: Other Overheads | B97: -564152.27 | C97: -208902.44 | D97: -389264.84 | E97: -92161.846 | F97: 0 | G97: =SUM(B97:E97) -> -1254481.4 | I97: -659831.22 | J97: -149358.87 | K97: -422337.81 | L97: -92395.18 | M97: 0 | N97: -1323923.1 | P97: =IFERROR((I97-B97)/B97,0) -> 0.16959773 | Q97: =IFERROR((J97-C97)/C97,0) -> -0.28503052 | R97: =IFERROR((K97-D97)/D97,0) -> 0.084962642 | S97: =IFERROR((L97-E97)/E97,0) -> 0.0025317889 | T97: =IFERROR((M97-F97)/F97,0) -> 0 | U97: =IFERROR((N97-G97)/G97,0) -> 0.055354891 | W97: -662720.8 | X97: -198522.95 | Y97: -440058.25 | Z97: -149564.55 | AA97: 0 | AB97: -1450866.5 | AD97: =IFERROR((W97-I97)/I97,0) -> 0.0043792668 | AE97: =IFERROR((X97-J97)/J97,0) -> 0.32916745 | AF97: =IFERROR((Y97-K97)/K97,0) -> 0.041957977 | AG97: =IFERROR((Z97-L97)/L97,0) -> 0.61874836 | AH97: =IFERROR((AA97-M97)/M97,0) -> 0 | AI97: =IFERROR((AB97-N97)/N97,0) -> 0.095884318 | AK97: -659831.22 | AL97: -149358.87 | AM97: -422337.81 | AN97: -92395.18 | AP97: -1323923.1 | AR97: =IFERROR((AK97-B97)/B97,0) -> 0.16959773 | AS97: =IFERROR((AL97-C97)/C97,0) -> -0.28503052 | AT97: =IFERROR((AM97-D97)/D97,0) -> 0.084962642 | AU97: =IFERROR((AN97-E97)/E97,0) -> 0.0025317889 | AV97: =IFERROR((AO97-F97)/F97,0) -> 0 | AW97: =IFERROR((AP97-G97)/G97,0) -> 0.055354891 | AY97: -627599.76 | AZ97: -186755.05 | BA97: -412993.14 | BB97: -140593.73 | BD97: -1367941.7 | BF97: =IFERROR((AY97-I97)/I97,0) -> -0.048848042 | BG97: =IFERROR((AZ97-J97)/J97,0) -> 0.25037805 | BH97: =IFERROR((BA97-K97)/K97,0) -> -0.02212607 | BI97: =IFERROR((BB97-L97)/L97,0) -> 0.52165651 | BJ97: =IFERROR((BC97-M97)/M97,0) -> 0 | BK97: =IFERROR((BD97-N97)/N97,0) -> 0.033248601
A99: Total Other Overheads | B99: -81523 | C99: -80265 | D99: -180350 | E99: -2150 | F99: -3771505 | G99: -4099247 | I99: -668831.22 | J99: -231563.76 | K99: -874206.92 | L99: -92395.18 | M99: -2975185.6 | N99: -4842182.7 | P99: =IFERROR((I99-B99)/B99,0) -> 7.2042027 | Q99: =IFERROR((J99-C99)/C99,0) -> 1.8849905 | R99: =IFERROR((K99-D99)/D99,0) -> 3.8472799 | S99: =IFERROR((L99-E99)/E99,0) -> 41.974502 | T99: =IFERROR((M99-F99)/F99,0) -> -0.21114101 | U99: =IFERROR((N99-G99)/G99,0) -> 0.18123712 | W99: -671720.8 | X99: -355315.34 | Y99: -897777.36 | Z99: -149564.55 | AA99: -2941302.2 | AB99: -5568716.8 | AD99: =IFERROR((W99-I99)/I99,0) -> 0.004320338 | AE99: =IFERROR((X99-J99)/J99,0) -> 0.53441686 | AF99: =IFERROR((Y99-K99)/K99,0) -> 0.026962084 | AG99: =IFERROR((Z99-L99)/L99,0) -> 0.61874836 | AH99: =IFERROR((AA99-M99)/M99,0) -> -0.011388671 | AI99: =IFERROR((AB99-N99)/N99,0) -> 0.15004269 | AK99: -668831.22 | AL99: -231563.76 | AM99: -874206.92 | AN99: -92395.18 | AO99: -2975185.6 | AP99: -4842182.7 | AR99: =IFERROR((AK99-B99)/B99,0) -> 7.2042027 | AS99: =IFERROR((AL99-C99)/C99,0) -> 1.8849905 | AT99: =IFERROR((AM99-D99)/D99,0) -> 3.8472799 | AU99: =IFERROR((AN99-E99)/E99,0) -> 41.974502 | AV99: =IFERROR((AO99-F99)/F99,0) -> -0.21114101 | AW99: =IFERROR((AP99-G99)/G99,0) -> 0.18123712 | AY99: -636599.76 | AZ99: -343547.44 | BA99: -870712.25 | BB99: -140593.73 | BC99: -2941302.2 | BD99: -6100808.1 | BF99: =IFERROR((AY99-I99)/I99,0) -> -0.048190727 | BG99: =IFERROR((AZ99-J99)/J99,0) -> 0.48359761 | BH99: =IFERROR((BA99-K99)/K99,0) -> -0.0039975389 | BI99: =IFERROR((BB99-L99)/L99,0) -> 0.52165651 | BJ99: =IFERROR((BC99-M99)/M99,0) -> -0.011388671 | BK99: =IFERROR((BD99-N99)/N99,0) -> 0.25992935
W100: 0.036410473 | X100: 0.050159846 | Y100: 0.11419957 | Z100: 0.16226672 | AB100: 0.16228031 | AK100: 0.054181587 | AL100: 0.039573052 | AM100: 0.1201086 | AN100: 0.16996486 | AP100: 0.1863151 | AY100: 0.034254759 | AZ100: 0.030138682 | BA100: 0.10383264 | BB100: 0.071490056 | BD100: 0.15468363
A101: EBITDA | B101: =B11+B20+B42+B71+B99+B85 -> 1649788 | C101: =C11+C20+C42+C71+C99+C85 -> 971186 | D101: =D11+D20+D42+D71+D99+D85 -> 1565064 | E101: =E11+E20+E42+E71+E99+E85 -> 612449 | F101: =F11+F20+F42+F71+F99+F85 -> -4219074 | G101: =G11+G20+G42+G71+G99+G85 -> 555365 | I101: =I11+I20+I42+I71+I99+I85 -> 1906793.6 | J101: =J11+J20+J42+J71+J99+J85 -> 1029988.2 | K101: =K11+K20+K42+K71+K99+K85 -> 1168593 | L101: =L11+L20+L42+L71+L99+L85 -> 376118.38 | M101: =M11+M20+M42+M71+M99+M85 -> -3275185.6 | N101: =N11+N20+N42+N71+N99+N85 -> 1206307.5 | P101: =IFERROR((I101-B101)/B101,0) -> 0.15578097 | Q101: =IFERROR((J101-C101)/C101,0) -> 0.060546841 | R101: =IFERROR((K101-D101)/D101,0) -> -0.25332577 | S101: =IFERROR((L101-E101)/E101,0) -> -0.38587804 | T101: =IFERROR((M101-F101)/F101,0) -> -0.22371932 | U101: =IFERROR((N101-G101)/G101,0) -> 1.1720986 | W101: 4703438.7 | X101: 2006104.1 | Y101: 1406180.6 | Z101: 232433.84 | AA101: -3241302.2 | AB101: 4553818.5 | AD101: =IFERROR((W101-I101)/I101,0) -> 1.4666743 | AE101: =IFERROR((X101-J101)/J101,0) -> 0.94769615 | AF101: =IFERROR((Y101-K101)/K101,0) -> 0.20331084 | AG101: =IFERROR((Z101-L101)/L101,0) -> -0.38201946 | AH101: =IFERROR((AA101-M101)/M101,0) -> -0.010345493 | AI101: =IFERROR((AB101-N101)/N101,0) -> 2.7750063 | AK101: 2325994.5 | AL101: 1724951.8 | AM101: 1410605.3 | AN101: 185109.37 | AO101: -3275185.6 | AP101: 2342798 | AR101: =IFERROR((AK101-B101)/B101,0) -> 0.40987476 | AS101: =IFERROR((AL101-C101)/C101,0) -> 0.77612914 | AT101: =IFERROR((AM101-D101)/D101,0) -> -0.098691617 | AU101: =IFERROR((AN101-E101)/E101,0) -> -0.69775545 | AV101: =IFERROR((AO101-F101)/F101,0) -> -0.22371932 | AW101: =IFERROR((AP101-G101)/G101,0) -> 3.2184834 | AY101: 4947036.9 | AZ101: 3937814.7 | BA101: 1672631.7 | BB101: 946257.94 | BC101: -3241302.2 | BD101: 6199433.3 | BF101: =IFERROR((AY101-I101)/I101,0) -> 1.5944271 | BG101: =IFERROR((AZ101-J101)/J101,0) -> 2.8231647 | BH101: =IFERROR((BA101-K101)/K101,0) -> 0.43132108 | BI101: =IFERROR((BB101-L101)/L101,0) -> 1.5158514 | BJ101: =IFERROR((BC101-M101)/M101,0) -> -0.010345493 | BK101: =IFERROR((BD101-N101)/N101,0) -> 4.1391814
W102: 0.25494883 | X102: 0.28320161 | Y102: 0.17886975 | Z102: 0.25217392 | AA102: 0 | AB102: 0.13270473 | AK102: 0.18842732 | AL102: 0.29478536 | AM102: 0.19380517 | AN102: 0.34051656 | AO102: 0 | AP102: 0.09014502 | AY102: 0.26619482 | AZ102: 0.34545606 | BA102: 0.19946173 | BB102: 0.48115969 | BC102: 0 | BD102: 0.15718424
BC104: -9015.6
A105: Sales % for overheads | B105: =B11/$G$11 -> 0.449676 | C105: =C11/$G$11 -> 0.16651252 | D105: =D11/$G$11 -> 0.31027626 | E105: =E11/$G$11 -> 0.073460611 | F105: =F11/$G$11 -> 0 | I105: =I11/$G$11 -> 0.63026055 | J105: =J11/$G$11 -> 0.23863316 | K105: =K11/$G$11 -> 0.37942505 | L105: =L11/$G$11 -> 0.049641162 | M105: =M11/$G$11 -> 0 | BC105: 0
B106: =SUM(G91:G97)*B105 -> -564110.18 | C106: =SUM(G91:G97)*C105 -> -208886.85 | D106: =SUM(G91:G97)*D105 -> -389235.8 | E106: =SUM(G91:G97)*E105 -> -92154.97 | F106: =$G$99*F105 -> 0 | I106: =$G$99*I105 -> -2583593.7 | J106: =$G$99*J105 -> -978216.28 | K106: =$G$99*K105 -> -1555357 | L106: =$G$99*L105 -> -203491.38 | M106: =$G$99*M105 -> 0
A109: Total D2C Marketing | B109: =SUM(B59:B63) -> -1141280 | C109: =SUM(C59:C63) -> -364882 | D109: =SUM(D59:D63) -> -1400259 | E109: =SUM(E59:E63) -> -7489 | F109: =SUM(F59:F63) -> -44009 | G109: =SUM(G59:G63) -> -3060172 | I109: =SUM(I59:I63) -> -2283035.5 | J109: =SUM(J59:J63) -> -551626.8 | K109: =SUM(K59:K63) -> -1733508.6 | L109: =SUM(L59:L63) -> 0 | M109: =SUM(M59:M63) -> 0 | N109: =SUM(N59:N63) -> -4568170.9 | W109: =SUM(W59:W63) -> -3931417.9 | X109: =SUM(X59:X63) -> -944498 | Y109: =SUM(Y59:Y63) -> -2057960.3 | Z109: =SUM(Z59:Z63) -> 0 | AA109: =SUM(AA59:AA63) -> 0 | AB109: =SUM(AB59:AB63) -> -6933876.2 | AK109: =SUM(AK59:AK63) -> -2312017.9 | AL109: =SUM(AL59:AL63) -> -574569 | AM109: =SUM(AM59:AM63) -> -1863211.1 | AN109: =SUM(AN59:AN63) -> 0 | AO109: =SUM(AO59:AO63) -> 0 | AP109: =SUM(AP59:AP63) -> -4749798 | AY109: =SUM(AY59:AY63) -> -3931417.9 | AZ109: =SUM(AZ59:AZ63) -> -1093382.4 | BA109: =SUM(BA59:BA63) -> -2246101.7 | BB109: =SUM(BB59:BB63) -> 0 | BC109: =SUM(BC59:BC63) -> 0 | BD109: =SUM(BD59:BD63) -> -7270902
A110: Total B2B Marketing | B110: =SUM(B64:B67) -> -1372438 | C110: =SUM(C64:C67) -> -88813 | D110: =SUM(D64:D67) -> -72211 | E110: =SUM(E64:E67) -> -20906 | F110: =SUM(F64:F67) -> -49787 | G110: =SUM(G64:G67) -> -1543325 | I110: =SUM(I64:I67) -> -1625223.4 | J110: =SUM(J64:J67) -> -290411.22 | K110: =SUM(K64:K67) -> -78121.845 | L110: =SUM(L64:L67) -> -51688.871 | M110: =SUM(M64:M67) -> 0 | N110: =SUM(N64:N67) -> -2045445.3 | W110: =SUM(W64:W67) -> -1959955.5 | X110: =SUM(X64:X67) -> -378524.47 | Y110: =SUM(Y64:Y67) -> -68396.488 | Z110: =SUM(Z64:Z67) -> -41002.131 | AA110: =SUM(AA64:AA67) -> 0 | AB110: =SUM(AB64:AB67) -> -2447878.6 | AK110: =SUM(AK64:AK67) -> -1683045 | AL110: =SUM(AL64:AL67) -> -255302.75 | AM110: =SUM(AM64:AM67) -> -38256.64 | AN110: =SUM(AN64:AN67) -> -15000 | AO110: =SUM(AO64:AO67) -> 0 | AP110: =SUM(AP64:AP67) -> -1991604.4 | AY110: =SUM(AY64:AY67) -> -1734244.9 | AZ110: =SUM(AZ64:AZ67) -> -372023.74 | BA110: =SUM(BA64:BA67) -> -30062.944 | BB110: =SUM(BB64:BB67) -> -15000 | BC110: =SUM(BC64:BC67) -> 0 | BD110: =SUM(BD64:BD67) -> -2151331.5
A111: Total Amazon Marketing | B111: =SUM(B68) -> -526944 | C111: =SUM(C68) -> -131693 | D111: =SUM(D68) -> -18 | E111: =SUM(E68) -> -10227 | F111: =SUM(F68) -> -2309 | G111: =SUM(G68) -> -688261 | I111: =SUM(I68) -> -539594.44 | J111: =SUM(J68) -> -262885.97 | K111: =SUM(K68) -> 0 | L111: =SUM(L68) -> -10852.122 | M111: =SUM(M68) -> 0 | N111: =SUM(N68) -> -813332.52 | W111: =SUM(W68) -> -523615.8 | X111: =SUM(X68) -> -261124 | Y111: =SUM(Y68) -> 0 | Z111: =SUM(Z68) -> -14790.781 | AA111: =SUM(AA68) -> 0 | AB111: =SUM(AB68) -> -799530.58 | AK111: =SUM(AK68) -> -649895 | AL111: =SUM(AL68) -> -556385.97 | AM111: =SUM(AM68) -> 0 | AN111: =SUM(AN68) -> -10852.122 | AO111: =SUM(AO68) -> 0 | AP111: =SUM(AP68) -> -1217133.1 | AY111: =SUM(AY68) -> -569930.85 | AZ111: =SUM(AZ68) -> -735124 | BA111: =SUM(BA68) -> 0 | BB111: =SUM(BB68) -> -14790.781 | BC111: =SUM(BC68) -> 0 | BD111: =SUM(BD68) -> -1319845.6

Sheet Combined P&L
B2: Combined P&L | D2: FY26 | S2: FY27 | AH2: FY28
D3: Q1 | E3: Q1 | F3: Q1 | G3: Q2 | H3: Q2 | I3: Q2 | J3: Q3 | K3: Q3 | L3: Q3 | M3: Q4 | N3: Q4 | O3: Q4 | S3: Q1 | T3: Q1 | U3: Q1 | V3: Q2 | W3: Q2 | X3: Q2 | Y3: Q3 | Z3: Q3 | AA3: Q3 | AB3: Q4 | AC3: Q4 | AD3: Q4 | AH3: Q1 | AI3: Q1 | AJ3: Q1 | AK3: Q2 | AL3: Q2 | AM3: Q2 | AN3: Q3 | AO3: Q3 | AP3: Q3 | AQ3: Q4 | AR3: Q4 | AS3: Q4
D4: 45716 | E4: 45747 | F4: 45777 | G4: 45808 | H4: 45838 | I4: =EOMONTH(H4,1) -> 45869 | J4: =EOMONTH(I4,1) -> 45900 | K4: =EOMONTH(J4,1) -> 45930 | L4: =EOMONTH(K4,1) -> 45961 | M4: =EOMONTH(L4,1) -> 45991 | N4: =EOMONTH(M4,1) -> 46022 | O4: =EOMONTH(N4,1) -> 46053 | Q4: FY26 | S4: 46081 | T4: =EOMONTH(S4,1) -> 46112 | U4: =EOMONTH(T4,1) -> 46142 | V4: =EOMONTH(U4,1) -> 46173 | W4: =EOMONTH(V4,1) -> 46203 | X4: =EOMONTH(W4,1) -> 46234 | Y4: =EOMONTH(X4,1) -> 46265 | Z4: =EOMONTH(Y4,1) -> 46295 | AA4: =EOMONTH(Z4,1) -> 46326 | ... AD4: =EOMONTH(AC4,1) -> 46418 | AF4: FY27 | AG4: YoY Growth % | AH4: 46446 | AI4: =EOMONTH(AH4,1) -> 46477 | AJ4: =EOMONTH(AI4,1) -> 46507 | AK4: =EOMONTH(AJ4,1) -> 46538 | AL4: =EOMONTH(AK4,1) -> 46568 | AM4: =EOMONTH(AL4,1) -> 46599 | AN4: =EOMONTH(AM4,1) -> 46630 | AO4: =EOMONTH(AN4,1) -> 46660 | AP4: =EOMONTH(AO4,1) -> 46691 | ... AS4: =EOMONTH(AR4,1) -> 46783 | AU4: FY28 | AV4: YoY Growth %
B5: Revenue | D5: Actual | E5: Actual | F5: Actual | G5: Actual | H5: Actual | I5: Actual | J5: Actual | K5: Actual | L5: Actual | M5: Forecast | N5: Forecast | O5: Forecast | S5: Forecast | T5: Forecast | U5: Forecast | V5: Forecast | W5: Forecast | X5: Forecast | Y5: Forecast | Z5: Forecast | AA5: Forecast | AB5: Forecast | AC5: Forecast | AD5: Forecast | AH5: Forecast | AI5: Forecast | AJ5: Forecast | AK5: Forecast | AL5: Forecast | AM5: Forecast | AN5: Forecast | AO5: Forecast | AP5: Forecast | AQ5: Forecast | AR5: Forecast | AS5: Forecast
B7: DTC Revenue | D7: 202799 | E7: 601303 | F7: 631785 | G7: 566075 | H7: 263390 | I7: 864744 | J7: 821520 | K7: 235662 | L7: 1394453 | M7: 1634636 | N7: 667657 | O7: 468991 | Q7: =SUM(D7:O7) -> 8353015 | S7: ='UK P&L'!S7+'CE P&L'!S7+'EE P&L'!S7+'ROW P&L'!S8 -> 587493.49 | T7: ='UK P&L'!T7+'CE P&L'!T7+'EE P&L'!T7+'ROW P&L'!T8 -> 1054223.4 | U7: ='UK P&L'!U7+'CE P&L'!U7+'EE P&L'!U7+'ROW P&L'!U8 -> 957195.88 | V7: ='UK P&L'!V7+'CE P&L'!V7+'EE P&L'!V7+'ROW P&L'!V8 -> 694824.41 | W7: ='UK P&L'!W7+'CE P&L'!W7+'EE P&L'!W7+'ROW P&L'!W8 -> 683629.96 | X7: ='UK P&L'!X7+'CE P&L'!X7+'EE P&L'!X7+'ROW P&L'!X8 -> 1434325 | Y7: ='UK P&L'!Y7+'CE P&L'!Y7+'EE P&L'!Y7+'ROW P&L'!Y8 -> 847776.86 | Z7: ='UK P&L'!Z7+'CE P&L'!Z7+'EE P&L'!Z7+'ROW P&L'!Z8 -> 823954.76 | ... AD7: ='UK P&L'!AD7+'CE P&L'!AD7+'EE P&L'!AD7+'ROW P&L'!AD8 -> 1045342.6 | AF7: =SUM(S7:AD7) -> 12526999 | AG7: =IFERROR(AF7/Q7-1,0) -> 0.49969785 | AH7: ='UK P&L'!AH7+'CE P&L'!AH7+'EE P&L'!AH7+'ROW P&L'!AH8 -> 1133474.9 | AI7: ='UK P&L'!AI7+'CE P&L'!AI7+'EE P&L'!AI7+'ROW P&L'!AI8 -> 1806900.2 | AJ7: ='UK P&L'!AJ7+'CE P&L'!AJ7+'EE P&L'!AJ7+'ROW P&L'!AJ8 -> 1644187.3 | AK7: ='UK P&L'!AK7+'CE P&L'!AK7+'EE P&L'!AK7+'ROW P&L'!AK8 -> 1390502 | AL7: ='UK P&L'!AL7+'CE P&L'!AL7+'EE P&L'!AL7+'ROW P&L'!AL8 -> 1402973.4 | AM7: ='UK P&L'!AM7+'CE P&L'!AM7+'EE P&L'!AM7+'ROW P&L'!AM8 -> 2408517.8 | AN7: ='UK P&L'!AN7+'CE P&L'!AN7+'EE P&L'!AN7+'ROW P&L'!AN8 -> 1529521.6 | AO7: ='UK P&L'!AO7+'CE P&L'!AO7+'EE P&L'!AO7+'ROW P&L'!AO8 -> 1526304.8 | ... AS7: ='UK P&L'!AS7+'CE P&L'!AS7+'EE P&L'!AS7+'ROW P&L'!AS8 -> 1795045.7 | AU7: =SUM(AH7:AS7) -> 21527065 | AV7: =IFERROR(AU7/AF7-1,0) -> 0.7184535
B8: B2B Revenue | D8: 664598 | E8: 511858 | F8: 289271 | G8: 509722 | H8: 591785 | I8: 418370 | J8: 329766 | K8: 506223 | L8: 705912 | M8: 764505 | N8: 767320 | O8: 569633 | Q8: =SUM(D8:O8) -> 6628963 | S8: =B2B!V113 -> 449360.45 | T8: =B2B!W113 -> 705870.76 | U8: =B2B!X113 -> 560120.97 | V8: =B2B!Y113 -> 588909.59 | W8: =B2B!Z113 -> 651637.07 | X8: =B2B!AA113 -> 438387.9 | Y8: =B2B!AB113 -> 565869.5 | Z8: =B2B!AC113 -> 1138090.5 | ... AD8: =B2B!AG113 -> 514690.97 | AF8: =SUM(S8:AD8) -> 7567798.5 | AG8: =IFERROR(AF8/Q8-1,0) -> 0.1416263 | AH8: =B2B!AK113 -> 550368.76 | AI8: =B2B!AL113 -> 623444.76 | AJ8: =B2B!AM113 -> 708143.05 | AK8: =B2B!AN113 -> 747837.53 | AL8: =B2B!AO113 -> 781870.6 | AM8: =B2B!AP113 -> 539331.02 | AN8: =B2B!AQ113 -> 685093.44 | AO8: =B2B!AR113 -> 1446716.8 | ... AS8: =B2B!AV113 -> 626230.55 | AU8: =SUM(AH8:AS8) -> 9284946.4 | AV8: =IFERROR(AU8/AF8-1,0) -> 0.2269019
B9: Marketplace Revenue | D9: 176029 | E9: 241390 | F9: 224283 | G9: 226436 | H9: 202175 | I9: 269729 | J9: 219995 | K9: 239633 | L9: 286625 | M9: 313378 | N9: 313378 | O9: 242801 | Q9: =SUM(D9:O9) -> 2955852 | S9: ='UK P&L'!S9+'CE P&L'!S9+'EE P&L'!S9+'ROW P&L'!S10 -> 195081.2 | T9: ='UK P&L'!T9+'CE P&L'!T9+'EE P&L'!T9+'ROW P&L'!T10 -> 269204 | U9: ='UK P&L'!U9+'CE P&L'!U9+'EE P&L'!U9+'ROW P&L'!U10 -> 252712.41 | V9: ='UK P&L'!V9+'CE P&L'!V9+'EE P&L'!V9+'ROW P&L'!V10 -> 250097.04 | W9: ='UK P&L'!W9+'CE P&L'!W9+'EE P&L'!W9+'ROW P&L'!W10 -> 242723.36 | X9: ='UK P&L'!X9+'CE P&L'!X9+'EE P&L'!X9+'ROW P&L'!X10 -> 310707.82 | Y9: ='UK P&L'!Y9+'CE P&L'!Y9+'EE P&L'!Y9+'ROW P&L'!Y10 -> 245213.4 | Z9: ='UK P&L'!Z9+'CE P&L'!Z9+'EE P&L'!Z9+'ROW P&L'!Z10 -> 269938.19 | ... AD9: ='UK P&L'!AD9+'CE P&L'!AD9+'EE P&L'!AD9+'ROW P&L'!AD10 -> 264740.71 | AF9: =SUM(S9:AD9) -> 3304437.5 | AG9: =IFERROR(AF9/Q9-1,0) -> 0.11793065 | AH9: ='UK P&L'!AH9+'CE P&L'!AH9+'EE P&L'!AH9+'ROW P&L'!AH10 -> 225060.35 | AI9: ='UK P&L'!AI9+'CE P&L'!AI9+'EE P&L'!AI9+'ROW P&L'!AI10 -> 284724.43 | AJ9: ='UK P&L'!AJ9+'CE P&L'!AJ9+'EE P&L'!AJ9+'ROW P&L'!AJ10 -> 267812.99 | AK9: ='UK P&L'!AK9+'CE P&L'!AK9+'EE P&L'!AK9+'ROW P&L'!AK10 -> 264511.47 | AL9: ='UK P&L'!AL9+'CE P&L'!AL9+'EE P&L'!AL9+'ROW P&L'!AL10 -> 256408.89 | AM9: ='UK P&L'!AM9+'CE P&L'!AM9+'EE P&L'!AM9+'ROW P&L'!AM10 -> 333411.13 | AN9: ='UK P&L'!AN9+'CE P&L'!AN9+'EE P&L'!AN9+'ROW P&L'!AN10 -> 262049.29 | AO9: ='UK P&L'!AO9+'CE P&L'!AO9+'EE P&L'!AO9+'ROW P&L'!AO10 -> 281913.69 | ... AS9: ='UK P&L'!AS9+'CE P&L'!AS9+'EE P&L'!AS9+'ROW P&L'!AS10 -> 288510.39 | AU9: =SUM(AH9:AS9) -> 3503407.9 | AV9: =IFERROR(AU9/AF9-1,0) -> 0.060213089
B10: TikTok Revenue | D10: 13626 | E10: 7932 | F10: 9528 | G10: 6522 | H10: 9097 | I10: 6971 | J10: 6370 | K10: 4379 | L10: 2185 | M10: 7754 | N10: 7754 | O10: 7754 | Q10: =SUM(D10:O10) -> 89872 | S10: ='UK P&L'!S10+'CE P&L'!S10+'EE P&L'!S10+'ROW P&L'!S11 -> 0 | T10: ='UK P&L'!T10+'CE P&L'!T10+'EE P&L'!T10+'ROW P&L'!T11 -> 0 | U10: ='UK P&L'!U10+'CE P&L'!U10+'EE P&L'!U10+'ROW P&L'!U11 -> 0 | V10: ='UK P&L'!V10+'CE P&L'!V10+'EE P&L'!V10+'ROW P&L'!V11 -> 0 | W10: ='UK P&L'!W10+'CE P&L'!W10+'EE P&L'!W10+'ROW P&L'!W11 -> 0 | X10: ='UK P&L'!X10+'CE P&L'!X10+'EE P&L'!X10+'ROW P&L'!X11 -> 0 | Y10: ='UK P&L'!Y10+'CE P&L'!Y10+'EE P&L'!Y10+'ROW P&L'!Y11 -> 0 | Z10: ='UK P&L'!Z10+'CE P&L'!Z10+'EE P&L'!Z10+'ROW P&L'!Z11 -> 0 | ... AD10: ='UK P&L'!AD10+'CE P&L'!AD10+'EE P&L'!AD10+'ROW P&L'!AD11 -> 0 | AF10: =SUM(S10:AD10) -> 0 | AG10: =IFERROR(AF10/Q10-1,0) -> -1 | AH10: ='UK P&L'!AH10+'CE P&L'!AH10+'EE P&L'!AH10+'ROW P&L'!AH11 -> 0 | AI10: ='UK P&L'!AI10+'CE P&L'!AI10+'EE P&L'!AI10+'ROW P&L'!AI11 -> 0 | AJ10: ='UK P&L'!AJ10+'CE P&L'!AJ10+'EE P&L'!AJ10+'ROW P&L'!AJ11 -> 0 | AK10: ='UK P&L'!AK10+'CE P&L'!AK10+'EE P&L'!AK10+'ROW P&L'!AK11 -> 0 | AL10: ='UK P&L'!AL10+'CE P&L'!AL10+'EE P&L'!AL10+'ROW P&L'!AL11 -> 0 | AM10: ='UK P&L'!AM10+'CE P&L'!AM10+'EE P&L'!AM10+'ROW P&L'!AM11 -> 0 | AN10: ='UK P&L'!AN10+'CE P&L'!AN10+'EE P&L'!AN10+'ROW P&L'!AN11 -> 0 | AO10: ='UK P&L'!AO10+'CE P&L'!AO10+'EE P&L'!AO10+'ROW P&L'!AO11 -> 0 | ... AS10: ='UK P&L'!AS10+'CE P&L'!AS10+'EE P&L'!AS10+'ROW P&L'!AS11 -> 0 | AU10: =SUM(AH10:AS10) -> 0 | AV10: =IFERROR(AU10/AF10-1,0) -> 0
B11: Other Income
B12: Total Revenue | D12: =SUM(D7:D11) -> 1057052 | E12: =SUM(E7:E11) -> 1362483 | F12: =SUM(F7:F11) -> 1154867 | G12: =SUM(G7:G11) -> 1308755 | H12: =SUM(H7:H11) -> 1066447 | I12: =SUM(I7:I11) -> 1559814 | J12: =SUM(J7:J11) -> 1377651 | K12: =SUM(K7:K11) -> 985897 | L12: =SUM(L7:L11) -> 2389175 | M12: =SUM(M7:M10) -> 2720273 | N12: =SUM(N7:N10) -> 1756109 | O12: =SUM(O7:O10) -> 1289179 | Q12: =SUM(D12:O12) -> 18027702 | S12: =SUM(S7:S11) -> 1231935.1 | T12: =SUM(T7:T11) -> 2029298.1 | U12: =SUM(U7:U11) -> 1770029.3 | V12: =SUM(V7:V11) -> 1533831 | W12: =SUM(W7:W11) -> 1577990.4 | X12: =SUM(X7:X11) -> 2183420.7 | Y12: =SUM(Y7:Y11) -> 1658859.8 | Z12: =SUM(Z7:Z11) -> 2231983.4 | ... AD12: =SUM(AD7:AD11) -> 1824774.3 | AF12: =SUM(S12:AD12) -> 23399235 | AG12: =IFERROR(AF12/Q12-1,0) -> 0.29795992 | AH12: =SUM(AH7:AH11) -> 1908904 | AI12: =SUM(AI7:AI11) -> 2715069.4 | AJ12: =SUM(AJ7:AJ11) -> 2620143.4 | AK12: =SUM(AK7:AK11) -> 2402851 | AL12: =SUM(AL7:AL11) -> 2441252.9 | AM12: =SUM(AM7:AM11) -> 3281259.9 | AN12: =SUM(AN7:AN11) -> 2476664.4 | AO12: =SUM(AO7:AO11) -> 3254935.3 | ... AS12: =SUM(AS7:AS11) -> 2709786.7 | AU12: =SUM(AH12:AS12) -> 34315419 | AV12: =IFERROR(AU12/AF12-1,0) -> 0.46651886
AG13: =IFERROR(AF13/Q13-1,0) -> 0
B14: Cost of Goods Sold (CoGS)
Q15: =SUM(D15:O15) -> 0
B16: DTC CoGS | D16: -46848 | E16: -139322 | F16: -162533 | G16: -131193 | H16: -50695 | I16: -215339 | J16: -214209 | K16: -49489 | L16: -376192 | M16: -441352 | N16: -160238 | O16: -107868 | Q16: =SUM(D16:O16) -> -2095278 | S16: ='UK P&L'!S16+'CE P&L'!S16+'EE P&L'!S16+'ROW P&L'!S17 -> -134375.57 | T16: ='UK P&L'!T16+'CE P&L'!T16+'EE P&L'!T16+'ROW P&L'!T17 -> -245828.87 | U16: ='UK P&L'!U16+'CE P&L'!U16+'EE P&L'!U16+'ROW P&L'!U17 -> -222180.01 | V16: ='UK P&L'!V16+'CE P&L'!V16+'EE P&L'!V16+'ROW P&L'!V17 -> -157409.27 | W16: ='UK P&L'!W16+'CE P&L'!W16+'EE P&L'!W16+'ROW P&L'!W17 -> -154331.33 | X16: ='UK P&L'!X16+'CE P&L'!X16+'EE P&L'!X16+'ROW P&L'!X17 -> -332657.67 | Y16: ='UK P&L'!Y16+'CE P&L'!Y16+'EE P&L'!Y16+'ROW P&L'!Y17 -> -190676.03 | Z16: ='UK P&L'!Z16+'CE P&L'!Z16+'EE P&L'!Z16+'ROW P&L'!Z17 -> -184455.53 | ... AD16: ='UK P&L'!AD16+'CE P&L'!AD16+'EE P&L'!AD16+'ROW P&L'!AD17 -> -232121.85 | AF16: =SUM(S16:AD16) -> -2861340.1 | AH16: ='UK P&L'!AH16+'CE P&L'!AH16+'EE P&L'!AH16+'ROW P&L'!AH17 -> -245580.05 | AI16: ='UK P&L'!AI16+'CE P&L'!AI16+'EE P&L'!AI16+'ROW P&L'!AI17 -> -405929.81 | AJ16: ='UK P&L'!AJ16+'CE P&L'!AJ16+'EE P&L'!AJ16+'ROW P&L'!AJ17 -> -363953.35 | AK16: ='UK P&L'!AK16+'CE P&L'!AK16+'EE P&L'!AK16+'ROW P&L'!AK17 -> -300927.59 | AL16: ='UK P&L'!AL16+'CE P&L'!AL16+'EE P&L'!AL16+'ROW P&L'!AL17 -> -303316.33 | AM16: ='UK P&L'!AM16+'CE P&L'!AM16+'EE P&L'!AM16+'ROW P&L'!AM17 -> -541767.55 | AN16: ='UK P&L'!AN16+'CE P&L'!AN16+'EE P&L'!AN16+'ROW P&L'!AN17 -> -329095.55 | AO16: ='UK P&L'!AO16+'CE P&L'!AO16+'EE P&L'!AO16+'ROW P&L'!AO17 -> -327283.43 | ... AS16: ='UK P&L'!AS16+'CE P&L'!AS16+'EE P&L'!AS16+'ROW P&L'!AS17 -> -382549.44 | AU16: =SUM(AH16:AS16) -> -4722184.9
B17: B2B CoGS | D17: -214784 | E17: -159354 | F17: -86260 | G17: -129464 | H17: -197763 | I17: -139316 | J17: -110842 | K17: -165406 | L17: -156835 | M17: -252287 | N17: -253216 | O17: -187979 | Q17: =SUM(D17:O17) -> -2053506 | S17: ='UK P&L'!S17+'CE P&L'!S17+'EE P&L'!S17+'ROW P&L'!S18 -> -124966.77 | T17: ='UK P&L'!T17+'CE P&L'!T17+'EE P&L'!T17+'ROW P&L'!T18 -> -218459.9 | U17: ='UK P&L'!U17+'CE P&L'!U17+'EE P&L'!U17+'ROW P&L'!U18 -> -177434.86 | V17: ='UK P&L'!V17+'CE P&L'!V17+'EE P&L'!V17+'ROW P&L'!V18 -> -185090.78 | W17: ='UK P&L'!W17+'CE P&L'!W17+'EE P&L'!W17+'ROW P&L'!W18 -> -197228.9 | X17: ='UK P&L'!X17+'CE P&L'!X17+'EE P&L'!X17+'ROW P&L'!X18 -> -133667.16 | Y17: ='UK P&L'!Y17+'CE P&L'!Y17+'EE P&L'!Y17+'ROW P&L'!Y18 -> -169805.96 | Z17: ='UK P&L'!Z17+'CE P&L'!Z17+'EE P&L'!Z17+'ROW P&L'!Z18 -> -323798.3 | ... AD17: ='UK P&L'!AD17+'CE P&L'!AD17+'EE P&L'!AD17+'ROW P&L'!AD18 -> -151428.94 | AF17: =SUM(S17:AD17) -> -2257204.1 | AH17: ='UK P&L'!AH17+'CE P&L'!AH17+'EE P&L'!AH17+'ROW P&L'!AH18 -> -153877.32 | AI17: ='UK P&L'!AI17+'CE P&L'!AI17+'EE P&L'!AI17+'ROW P&L'!AI18 -> -187279.11 | AJ17: ='UK P&L'!AJ17+'CE P&L'!AJ17+'EE P&L'!AJ17+'ROW P&L'!AJ18 -> -222558.33 | AK17: ='UK P&L'!AK17+'CE P&L'!AK17+'EE P&L'!AK17+'ROW P&L'!AK18 -> -233007.01 | AL17: ='UK P&L'!AL17+'CE P&L'!AL17+'EE P&L'!AL17+'ROW P&L'!AL18 -> -237655.54 | AM17: ='UK P&L'!AM17+'CE P&L'!AM17+'EE P&L'!AM17+'ROW P&L'!AM18 -> -162989.68 | AN17: ='UK P&L'!AN17+'CE P&L'!AN17+'EE P&L'!AN17+'ROW P&L'!AN18 -> -204780.94 | AO17: ='UK P&L'!AO17+'CE P&L'!AO17+'EE P&L'!AO17+'ROW P&L'!AO18 -> -414674.93 | ... AS17: ='UK P&L'!AS17+'CE P&L'!AS17+'EE P&L'!AS17+'ROW P&L'!AS18 -> -185522.15 | AU17: =SUM(AH17:AS17) -> -2765364.4
B18: Marketplace CoGS | D18: -24140 | E18: -39162 | F18: -38304 | G18: -37736 | H18: -32746 | I18: -45757 | J18: -37167 | K18: -45654 | L18: -51987 | M18: -55028 | N18: -55028 | O18: -42635 | Q18: =SUM(D18:O18) -> -505344 | S18: ='UK P&L'!S18+'CE P&L'!S18+'EE P&L'!S18+'ROW P&L'!S19 -> -35114.616 | T18: ='UK P&L'!T18+'CE P&L'!T18+'EE P&L'!T18+'ROW P&L'!T19 -> -48456.72 | U18: ='UK P&L'!U18+'CE P&L'!U18+'EE P&L'!U18+'ROW P&L'!U19 -> -45488.234 | V18: ='UK P&L'!V18+'CE P&L'!V18+'EE P&L'!V18+'ROW P&L'!V19 -> -45017.467 | W18: ='UK P&L'!W18+'CE P&L'!W18+'EE P&L'!W18+'ROW P&L'!W19 -> -43690.204 | X18: ='UK P&L'!X18+'CE P&L'!X18+'EE P&L'!X18+'ROW P&L'!X19 -> -55927.408 | Y18: ='UK P&L'!Y18+'CE P&L'!Y18+'EE P&L'!Y18+'ROW P&L'!Y19 -> -44138.412 | Z18: ='UK P&L'!Z18+'CE P&L'!Z18+'EE P&L'!Z18+'ROW P&L'!Z19 -> -48588.875 | ... AD18: ='UK P&L'!AD18+'CE P&L'!AD18+'EE P&L'!AD18+'ROW P&L'!AD19 -> -47653.328 | AF18: =SUM(S18:AD18) -> -594798.76 | AH18: ='UK P&L'!AH18+'CE P&L'!AH18+'EE P&L'!AH18+'ROW P&L'!AH19 -> -40510.863 | AI18: ='UK P&L'!AI18+'CE P&L'!AI18+'EE P&L'!AI18+'ROW P&L'!AI19 -> -51250.398 | AJ18: ='UK P&L'!AJ18+'CE P&L'!AJ18+'EE P&L'!AJ18+'ROW P&L'!AJ19 -> -48206.338 | AK18: ='UK P&L'!AK18+'CE P&L'!AK18+'EE P&L'!AK18+'ROW P&L'!AK19 -> -47612.064 | AL18: ='UK P&L'!AL18+'CE P&L'!AL18+'EE P&L'!AL18+'ROW P&L'!AL19 -> -46153.6 | AM18: ='UK P&L'!AM18+'CE P&L'!AM18+'EE P&L'!AM18+'ROW P&L'!AM19 -> -60014.004 | AN18: ='UK P&L'!AN18+'CE P&L'!AN18+'EE P&L'!AN18+'ROW P&L'!AN19 -> -47168.871 | AO18: ='UK P&L'!AO18+'CE P&L'!AO18+'EE P&L'!AO18+'ROW P&L'!AO19 -> -50744.465 | ... AS18: ='UK P&L'!AS18+'CE P&L'!AS18+'EE P&L'!AS18+'ROW P&L'!AS19 -> -51931.87 | AU18: =SUM(AH18:AS18) -> -630613.43
B19: TikTok CoGS | D19: -2332 | E19: -1768 | F19: -1984 | G19: -2229 | H19: -3048 | I19: -1398 | J19: -1099 | K19: -695 | L19: -249 | M19: -1396 | N19: -1396 | O19: -1396 | Q19: =SUM(D19:O19) -> -18990 | S19: ='UK P&L'!S19+'CE P&L'!S19+'EE P&L'!S19+'ROW P&L'!S20 -> 0 | T19: ='UK P&L'!T19+'CE P&L'!T19+'EE P&L'!T19+'ROW P&L'!T20 -> 0 | U19: ='UK P&L'!U19+'CE P&L'!U19+'EE P&L'!U19+'ROW P&L'!U20 -> 0 | V19: ='UK P&L'!V19+'CE P&L'!V19+'EE P&L'!V19+'ROW P&L'!V20 -> 0 | W19: ='UK P&L'!W19+'CE P&L'!W19+'EE P&L'!W19+'ROW P&L'!W20 -> 0 | X19: ='UK P&L'!X19+'CE P&L'!X19+'EE P&L'!X19+'ROW P&L'!X20 -> 0 | Y19: ='UK P&L'!Y19+'CE P&L'!Y19+'EE P&L'!Y19+'ROW P&L'!Y20 -> 0 | Z19: ='UK P&L'!Z19+'CE P&L'!Z19+'EE P&L'!Z19+'ROW P&L'!Z20 -> 0 | ... AD19: ='UK P&L'!AD19+'CE P&L'!AD19+'EE P&L'!AD19+'ROW P&L'!AD20 -> 0 | AF19: =SUM(S19:AD19) -> 0 | AH19: ='UK P&L'!AH19+'CE P&L'!AH19+'EE P&L'!AH19+'ROW P&L'!AH20 -> 0 | AI19: ='UK P&L'!AI19+'CE P&L'!AI19+'EE P&L'!AI19+'ROW P&L'!AI20 -> 0 | AJ19: ='UK P&L'!AJ19+'CE P&L'!AJ19+'EE P&L'!AJ19+'ROW P&L'!AJ20 -> 0 | AK19: ='UK P&L'!AK19+'CE P&L'!AK19+'EE P&L'!AK19+'ROW P&L'!AK20 -> 0 | AL19: ='UK P&L'!AL19+'CE P&L'!AL19+'EE P&L'!AL19+'ROW P&L'!AL20 -> 0 | AM19: ='UK P&L'!AM19+'CE P&L'!AM19+'EE P&L'!AM19+'ROW P&L'!AM20 -> 0 | AN19: ='UK P&L'!AN19+'CE P&L'!AN19+'EE P&L'!AN19+'ROW P&L'!AN20 -> 0 | AO19: ='UK P&L'!AO19+'CE P&L'!AO19+'EE P&L'!AO19+'ROW P&L'!AO20 -> 0 | ... AS19: ='UK P&L'!AS19+'CE P&L'!AS19+'EE P&L'!AS19+'ROW P&L'!AS20 -> 0 | AU19: =SUM(AH19:AS19) -> 0
B21: Total CoGS | D21: =SUM(D15:D20) -> -288104 | E21: =SUM(E15:E20) -> -339606 | F21: =SUM(F15:F20) -> -289081 | G21: =SUM(G15:G20) -> -300622 | H21: =SUM(H15:H20) -> -284252 | I21: =SUM(I15:I20) -> -401810 | J21: =SUM(J15:J20) -> -363317 | K21: =SUM(K15:K20) -> -261244 | L21: =SUM(L15:L20)+0.5 -> -585262.5 | M21: =SUM(M16:M20)+1 -> -750062 | N21: =SUM(N16:N20)+1 -> -469877 | O21: =SUM(O16:O20)+0.5 -> -339877.5 | Q21: =SUM(D21:O21) -> -4673115 | S21: =SUM(S16:S20) -> -294456.96 | T21: =SUM(T16:T20) -> -512745.49 | U21: =SUM(U16:U20) -> -445103.11 | V21: =SUM(V16:V20) -> -387517.52 | W21: =SUM(W16:W20) -> -395250.44 | X21: =SUM(X16:X20) -> -522252.23 | Y21: =SUM(Y16:Y20) -> -404620.4 | Z21: =SUM(Z16:Z20) -> -556842.71 | ... AD21: =SUM(AD16:AD20) -> -431204.12 | AF21: =SUM(S21:AD21) -> -5713342.9 | AH21: =SUM(AH16:AH20) -> -439968.23 | AI21: =SUM(AI16:AI20) -> -644459.32 | AJ21: =SUM(AJ16:AJ20) -> -634718.02 | AK21: =SUM(AK16:AK20) -> -581546.66 | AL21: =SUM(AL16:AL20) -> -587125.47 | AM21: =SUM(AM16:AM20) -> -764771.23 | AN21: =SUM(AN16:AN20) -> -581045.37 | AO21: =SUM(AO16:AO20) -> -792702.82 | ... AS21: =SUM(AS16:AS20) -> -620003.47 | AU21: =SUM(AH21:AS21) -> -8118162.7
D22: =D21/D12 -> -0.27255424 | E22: =E21/E12 -> -0.24925522 | F22: =F21/F12 -> -0.2503154 | G22: =G21/G12 -> -0.22970075 | H22: =H21/H12 -> -0.26654114 | I22: =I21/I12 -> -0.25760123 | J22: =J21/J12 -> -0.26372209 | K22: =K21/K12 -> -0.26498103 | ... O22: =O21/O12 -> -0.26363872 | Q22: =Q21/Q12 -> -0.25921856 | S22: =S21/S12 -> -0.23901985 | T22: =T21/T12 -> -0.25267135 | U22: =U21/U12 -> -0.25146653 | V22: =V21/V12 -> -0.25264681 | W22: =W21/W12 -> -0.25047709 | X22: =X21/X12 -> -0.23918992 | Y22: =Y21/Y12 -> -0.24391477 | Z22: =Z21/Z12 -> -0.24948335 | ... AD22: =AD21/AD12 -> -0.23630546 | AF22: =AF21/AF12 -> -0.24416794 | AH22: =AH21/AH12 -> -0.23048212 | AI22: =AI21/AI12 -> -0.23736385 | AJ22: =AJ21/AJ12 -> -0.24224553 | AK22: =AK21/AK12 -> -0.24202361 | AL22: =AL21/AL12 -> -0.2405017 | AM22: =AM21/AM12 -> -0.23307243 | AN22: =AN21/AN12 -> -0.23460804 | AO22: =AO21/AO12 -> -0.24353873 | ... AS22: =AS21/AS12 -> -0.22880158 | AU22: =AU21/AU12 -> -0.23657478
B23: DTC CM1 | D23: =D7+D16 -> 155951 | E23: =E7+E16 -> 461981 | F23: =F7+F16 -> 469252 | G23: =G7+G16 -> 434882 | H23: =H7+H16 -> 212695 | I23: =I7+I16 -> 649405 | J23: =J7+J16 -> 607311 | K23: =K7+K16 -> 186173 | ... O23: =O7+O16 -> 361123 | Q23: =Q7+Q16 -> 6257737 | S23: =S7+S16 -> 453117.92 | T23: =T7+T16 -> 808394.48 | U23: =U7+U16 -> 735015.86 | V23: =V7+V16 -> 537415.14 | W23: =W7+W16 -> 529298.63 | X23: =X7+X16 -> 1101667.3 | Y23: =Y7+Y16 -> 657100.83 | Z23: =Z7+Z16 -> 639499.23 | ... AD23: =AD7+AD16 -> 813220.75 | AF23: =AF7+AF16 -> 9665658.6 | AH23: =AH7+AH16 -> 887894.82 | AI23: =AI7+AI16 -> 1400970.4 | AJ23: =AJ7+AJ16 -> 1280234 | AK23: =AK7+AK16 -> 1089574.4 | AL23: =AL7+AL16 -> 1099657.1 | AM23: =AM7+AM16 -> 1866750.2 | AN23: =AN7+AN16 -> 1200426.1 | AO23: =AO7+AO16 -> 1199021.4 | ... AS23: =AS7+AS16 -> 1412496.3 | AU23: =AU7+AU16 -> 16804880
B24: B2B CM1 | D24: =D8+D17 -> 449814 | E24: =E8+E17 -> 352504 | F24: =F8+F17 -> 203011 | G24: =G8+G17 -> 380258 | H24: =H8+H17 -> 394022 | I24: =I8+I17 -> 279054 | J24: =J8+J17 -> 218924 | K24: =K8+K17 -> 340817 | ... O24: =O8+O17 -> 381654 | Q24: =Q8+Q17 -> 4575457 | S24: =S8+S17 -> 324393.68 | T24: =T8+T17 -> 487410.86 | U24: =U8+U17 -> 382686.11 | V24: =V8+V17 -> 403818.8 | W24: =W8+W17 -> 454408.17 | X24: =X8+X17 -> 304720.74 | Y24: =Y8+Y17 -> 396063.54 | Z24: =Z8+Z17 -> 814292.19 | ... AD24: =AD8+AD17 -> 363262.03 | AF24: =AF8+AF17 -> 5310594.4 | AH24: =AH8+AH17 -> 396491.44 | AI24: =AI8+AI17 -> 436165.65 | AJ24: =AJ8+AJ17 -> 485584.72 | AK24: =AK8+AK17 -> 514830.52 | AL24: =AL8+AL17 -> 544215.07 | AM24: =AM8+AM17 -> 376341.34 | AN24: =AN8+AN17 -> 480312.5 | AO24: =AO8+AO17 -> 1032041.9 | ... AS24: =AS8+AS17 -> 440708.39 | AU24: =AU8+AU17 -> 6519582
B25: Marketplace CM1 | D25: =D9+D18 -> 151889 | E25: =E9+E18 -> 202228 | F25: =F9+F18 -> 185979 | G25: =G9+G18 -> 188700 | H25: =H9+H18 -> 169429 | I25: =I9+I18 -> 223972 | J25: =J9+J18 -> 182828 | K25: =K9+K18 -> 193979 | ... O25: =O9+O18 -> 200166 | Q25: =Q9+Q18 -> 2450508 | S25: =S9+S18 -> 159966.58 | T25: =T9+T18 -> 220747.28 | U25: =U9+U18 -> 207224.18 | V25: =V9+V18 -> 205079.57 | W25: =W9+W18 -> 199033.15 | X25: =X9+X18 -> 254780.41 | Y25: =Y9+Y18 -> 201074.99 | Z25: =Z9+Z18 -> 221349.32 | ... AD25: =AD9+AD18 -> 217087.38 | AF25: =AF9+AF18 -> 2709638.8 | AH25: =AH9+AH18 -> 184549.49 | AI25: =AI9+AI18 -> 233474.04 | AJ25: =AJ9+AJ18 -> 219606.65 | AK25: =AK9+AK18 -> 216899.4 | AL25: =AL9+AL18 -> 210255.29 | AM25: =AM9+AM18 -> 273397.13 | AN25: =AN9+AN18 -> 214880.41 | AO25: =AO9+AO18 -> 231169.23 | ... AS25: =AS9+AS18 -> 236578.52 | AU25: =AU9+AU18 -> 2872794.5
B26: TikTok CM1 | D26: =D10+D19 -> 11294 | E26: =E10+E19 -> 6164 | F26: =F10+F19 -> 7544 | G26: =G10+G19 -> 4293 | H26: =H10+H19 -> 6049 | I26: =I10+I19 -> 5573 | J26: =J10+J19 -> 5271 | K26: =K10+K19 -> 3684 | ... O26: =O10+O19 -> 6358 | Q26: =Q10+Q19 -> 70882 | S26: =S10+S19 -> 0 | T26: =T10+T19 -> 0 | U26: =U10+U19 -> 0 | V26: =V10+V19 -> 0 | W26: =W10+W19 -> 0 | X26: =X10+X19 -> 0 | Y26: =Y10+Y19 -> 0 | Z26: =Z10+Z19 -> 0 | ... AD26: =AD10+AD19 -> 0 | AF26: =AF10+AF19 -> 0 | AH26: =AH10+AH19 -> 0 | AI26: =AI10+AI19 -> 0 | AJ26: =AJ10+AJ19 -> 0 | AK26: =AK10+AK19 -> 0 | AL26: =AL10+AL19 -> 0 | AM26: =AM10+AM19 -> 0 | AN26: =AN10+AN19 -> 0 | AO26: =AO10+AO19 -> 0 | ... AS26: =AS10+AS19 -> 0 | AU26: =AU10+AU19 -> 0
B27: Total CM1 | D27: =D12+D21 -> 768948 | E27: =E12+E21 -> 1022877 | F27: =F12+F21 -> 865786 | G27: =G12+G21 -> 1008133 | H27: =H12+H21 -> 782195 | I27: =I12+I21 -> 1158004 | J27: =J12+J21 -> 1014334 | K27: =K12+K21 -> 724653 | ... O27: =O12+O21 -> 949301.5 | Q27: =Q12+Q21 -> 13354587 | S27: =S12+S21 -> 937478.19 | T27: =T12+T21 -> 1516552.6 | U27: =U12+U21 -> 1324926.1 | V27: =V12+V21 -> 1146313.5 | W27: =W12+W21 -> 1182739.9 | X27: =X12+X21 -> 1661168.5 | Y27: =Y12+Y21 -> 1254239.4 | Z27: =Z12+Z21 -> 1675140.7 | ... AD27: =AD12+AD21 -> 1393570.2 | AF27: =AF12+AF21 -> 17685892 | AH27: =AH12+AH21 -> 1468935.7 | AI27: =AI12+AI21 -> 2070610.1 | AJ27: =AJ12+AJ21 -> 1985425.3 | AK27: =AK12+AK21 -> 1821304.3 | AL27: =AL12+AL21 -> 1854127.4 | AM27: =AM12+AM21 -> 2516488.7 | AN27: =AN12+AN21 -> 1895619 | AO27: =AO12+AO21 -> 2462232.5 | ... AS27: =AS12+AS21 -> 2089783.2 | AU27: =AU12+AU21 -> 26197256
B29: DTC CM1% | D29: =IFERROR(D23/D7,0) -> 0.76899294 | E29: =IFERROR(E23/E7,0) -> 0.76829984 | F29: =IFERROR(F23/F7,0) -> 0.74274001 | G29: =IFERROR(G23/G7,0) -> 0.76824096 | H29: =IFERROR(H23/H7,0) -> 0.80752876 | I29: =IFERROR(I23/I7,0) -> 0.75097948 | J29: =IFERROR(J23/J7,0) -> 0.73925285 | K29: =IFERROR(K23/K7,0) -> 0.79000008 | ... O29: =IFERROR(O23/O7,0) -> 0.76999985 | Q29: =IFERROR(Q23/Q7,0) -> 0.74915908 | S29: =IFERROR(S23/S7,0) -> 0.7712731 | T29: =IFERROR(T23/T7,0) -> 0.76681519 | U29: =IFERROR(U23/U7,0) -> 0.76788448 | V29: =IFERROR(V23/V7,0) -> 0.77345461 | W29: =IFERROR(W23/W7,0) -> 0.77424726 | X29: =IFERROR(X23/X7,0) -> 0.76807372 | Y29: =IFERROR(Y23/Y7,0) -> 0.77508701 | Z29: =IFERROR(Z23/Z7,0) -> 0.77613391 | ... AD29: =IFERROR(AD23/AD7,0) -> 0.77794663 | AF29: =IFERROR(AF23/AF7,0) -> 0.77158614 | AH29: =IFERROR(AH23/AH7,0) -> 0.78333878 | AI29: =IFERROR(AI23/AI7,0) -> 0.77534464 | AJ29: =IFERROR(AJ23/AJ7,0) -> 0.7786424 | AK29: =IFERROR(AK23/AK7,0) -> 0.78358349 | AL29: =IFERROR(AL23/AL7,0) -> 0.78380465 | AM29: =IFERROR(AM23/AM7,0) -> 0.77506184 | AN29: =IFERROR(AN23/AN7,0) -> 0.7848376 | AO29: =IFERROR(AO23/AO7,0) -> 0.78557138 | ... AS29: =IFERROR(AS23/AS7,0) -> 0.78688596 | AU29: =IFERROR(AU23/AU7,0) -> 0.78063963
B30: B2B CM1% | D30: =IFERROR(D24/D8,0) -> 0.67682118 | E30: =IFERROR(E24/E8,0) -> 0.68867537 | F30: =IFERROR(F24/F8,0) -> 0.70180212 | G30: =IFERROR(G24/G8,0) -> 0.74601057 | H30: =IFERROR(H24/H8,0) -> 0.66581951 | I30: =IFERROR(I24/I8,0) -> 0.66700289 | J30: =IFERROR(J24/J8,0) -> 0.66387681 | K30: =IFERROR(K24/K8,0) -> 0.67325467 | ... O30: =IFERROR(O24/O8,0) -> 0.66999981 | Q30: =IFERROR(Q24/Q8,0) -> 0.69022214 | S30: =IFERROR(S24/S8,0) -> 0.72190083 | T30: =IFERROR(T24/T8,0) -> 0.69051006 | U30: =IFERROR(U24/U8,0) -> 0.68322046 | V30: =IFERROR(V24/V8,0) -> 0.68570594 | W30: =IFERROR(W24/W8,0) -> 0.69733321 | X30: =IFERROR(X24/X8,0) -> 0.69509387 | Y30: =IFERROR(Y24/Y8,0) -> 0.69992029 | Z30: =IFERROR(Z24/Z8,0) -> 0.71548984 | ... AD30: =IFERROR(AD24/AD8,0) -> 0.70578667 | AF30: =IFERROR(AF24/AF8,0) -> 0.7017357 | AH30: =IFERROR(AH24/AH8,0) -> 0.72041051 | AI30: =IFERROR(AI24/AI8,0) -> 0.69960593 | AJ30: =IFERROR(AJ24/AJ8,0) -> 0.68571558 | AK30: =IFERROR(AK24/AK8,0) -> 0.68842563 | AL30: =IFERROR(AL24/AL8,0) -> 0.69604237 | AM30: =IFERROR(AM24/AM8,0) -> 0.69779287 | AN30: =IFERROR(AN24/AN8,0) -> 0.70109049 | AO30: =IFERROR(AO24/AO8,0) -> 0.71336828 | ... AS30: =IFERROR(AS24/AS8,0) -> 0.70374784 | AU30: =IFERROR(AU24/AU8,0) -> 0.7021669
B31: Marketplace CM1% | D31: =IFERROR(D25/D9,0) -> 0.86286351 | E31: =IFERROR(E25/E9,0) -> 0.83776461 | F31: =IFERROR(F25/F9,0) -> 0.82921577 | G31: =IFERROR(G25/G9,0) -> 0.83334805 | H31: =IFERROR(H25/H9,0) -> 0.83803141 | I31: =IFERROR(I25/I9,0) -> 0.83035936 | J31: =IFERROR(J25/J9,0) -> 0.83105525 | K31: =IFERROR(K25/K9,0) -> 0.80948367 | ... O31: =IFERROR(O25/O9,0) -> 0.82440352 | Q31: =IFERROR(Q25/Q9,0) -> 0.8290361 | S31: =IFERROR(S25/S9,0) -> 0.82 | T31: =IFERROR(T25/T9,0) -> 0.82 | U31: =IFERROR(U25/U9,0) -> 0.82 | V31: =IFERROR(V25/V9,0) -> 0.82 | W31: =IFERROR(W25/W9,0) -> 0.82 | X31: =IFERROR(X25/X9,0) -> 0.82 | Y31: =IFERROR(Y25/Y9,0) -> 0.82 | Z31: =IFERROR(Z25/Z9,0) -> 0.82 | ... AD31: =IFERROR(AD25/AD9,0) -> 0.82 | AF31: =IFERROR(AF25/AF9,0) -> 0.82 | AH31: =IFERROR(AH25/AH9,0) -> 0.82 | AI31: =IFERROR(AI25/AI9,0) -> 0.82 | AJ31: =IFERROR(AJ25/AJ9,0) -> 0.82 | AK31: =IFERROR(AK25/AK9,0) -> 0.82 | AL31: =IFERROR(AL25/AL9,0) -> 0.82 | AM31: =IFERROR(AM25/AM9,0) -> 0.82 | AN31: =IFERROR(AN25/AN9,0) -> 0.82 | AO31: =IFERROR(AO25/AO9,0) -> 0.82 | ... AS31: =IFERROR(AS25/AS9,0) -> 0.82 | AU31: =IFERROR(AU25/AU9,0) -> 0.82
B32: TikTok CM1% | D32: =IFERROR(D26/D10,0) -> 0.8288566 | E32: =IFERROR(E26/E10,0) -> 0.7771054 | F32: =IFERROR(F26/F10,0) -> 0.79177162 | G32: =IFERROR(G26/G10,0) -> 0.65823367 | H32: =IFERROR(H26/H10,0) -> 0.66494449 | I32: =IFERROR(I26/I10,0) -> 0.79945488 | J32: =IFERROR(J26/J10,0) -> 0.82747253 | K32: =IFERROR(K26/K10,0) -> 0.84128797 | ... O32: =IFERROR(O26/O10,0) -> 0.81996389 | Q32: =IFERROR(Q26/Q10,0) -> 0.78869948 | S32: =IFERROR(S26/S10,0) -> 0 | T32: =IFERROR(T26/T10,0) -> 0 | U32: =IFERROR(U26/U10,0) -> 0 | V32: =IFERROR(V26/V10,0) -> 0 | W32: =IFERROR(W26/W10,0) -> 0 | X32: =IFERROR(X26/X10,0) -> 0 | Y32: =IFERROR(Y26/Y10,0) -> 0 | Z32: =IFERROR(Z26/Z10,0) -> 0 | ... AD32: =IFERROR(AD26/AD10,0) -> 0 | AF32: =IFERROR(AF26/AF10,0) -> 0 | AH32: =IFERROR(AH26/AH10,0) -> 0 | AI32: =IFERROR(AI26/AI10,0) -> 0 | AJ32: =IFERROR(AJ26/AJ10,0) -> 0 | AK32: =IFERROR(AK26/AK10,0) -> 0 | AL32: =IFERROR(AL26/AL10,0) -> 0 | AM32: =IFERROR(AM26/AM10,0) -> 0 | AN32: =IFERROR(AN26/AN10,0) -> 0 | AO32: =IFERROR(AO26/AO10,0) -> 0 | ... AS32: =IFERROR(AS26/AS10,0) -> 0 | AU32: =IFERROR(AU26/AU10,0) -> 0
B33: Total CM1% | D33: =IFERROR(D27/D12,0) -> 0.72744576 | E33: =IFERROR(E27/E12,0) -> 0.75074478 | F33: =IFERROR(F27/F12,0) -> 0.7496846 | G33: =IFERROR(G27/G12,0) -> 0.77029925 | H33: =IFERROR(H27/H12,0) -> 0.73345886 | I33: =IFERROR(I27/I12,0) -> 0.74239877 | J33: =IFERROR(J27/J12,0) -> 0.73627791 | K33: =IFERROR(K27/K12,0) -> 0.73501897 | ... O33: =IFERROR(O27/O12,0) -> 0.73636128 | Q33: =IFERROR(Q27/Q12,0) -> 0.74078144 | S33: =IFERROR(S27/S12,0) -> 0.76098015 | T33: =IFERROR(T27/T12,0) -> 0.74732865 | U33: =IFERROR(U27/U12,0) -> 0.74853347 | V33: =IFERROR(V27/V12,0) -> 0.74735319 | W33: =IFERROR(W27/W12,0) -> 0.74952291 | X33: =IFERROR(X27/X12,0) -> 0.76081008 | Y33: =IFERROR(Y27/Y12,0) -> 0.75608523 | Z33: =IFERROR(Z27/Z12,0) -> 0.75051665 | ... AD33: =IFERROR(AD27/AD12,0) -> 0.76369454 | AF33: =IFERROR(AF27/AF12,0) -> 0.75583206 | AH33: =IFERROR(AH27/AH12,0) -> 0.76951788 | AI33: =IFERROR(AI27/AI12,0) -> 0.76263615 | AJ33: =IFERROR(AJ27/AJ12,0) -> 0.75775447 | AK33: =IFERROR(AK27/AK12,0) -> 0.75797639 | AL33: =IFERROR(AL27/AL12,0) -> 0.7594983 | AM33: =IFERROR(AM27/AM12,0) -> 0.76692757 | AN33: =IFERROR(AN27/AN12,0) -> 0.76539196 | AO33: =IFERROR(AO27/AO12,0) -> 0.75646127 | ... AS33: =IFERROR(AS27/AS12,0) -> 0.77119842 | AU33: =IFERROR(AU27/AU12,0) -> 0.76342522
B35: Fulfilment
B37: Fulfilment | D37: -21484 | E37: -41137 | F37: -22843 | G37: -29571 | H37: -27976 | I37: -39178 | J37: -36148 | K37: -25470 | L37: 8633 | M37: -37451 | N37: -41453 | O37: -36510 | Q37: =SUM(D37:O37) -> -350588 | S37: ='CE P&L'!S37+'EE P&L'!S37+'ROW P&L'!S39+'Non Rev P&L'!S19 -> -25000 | T37: ='CE P&L'!T37+'EE P&L'!T37+'ROW P&L'!T39+'Non Rev P&L'!T19 -> -25000 | U37: ='CE P&L'!U37+'EE P&L'!U37+'ROW P&L'!U39+'Non Rev P&L'!U19 -> -25000 | V37: ='CE P&L'!V37+'EE P&L'!V37+'ROW P&L'!V39+'Non Rev P&L'!V19 -> -25000 | W37: ='CE P&L'!W37+'EE P&L'!W37+'ROW P&L'!W39+'Non Rev P&L'!W19 -> -25000 | X37: ='CE P&L'!X37+'EE P&L'!X37+'ROW P&L'!X39+'Non Rev P&L'!X19 -> -25000 | Y37: ='CE P&L'!Y37+'EE P&L'!Y37+'ROW P&L'!Y39+'Non Rev P&L'!Y19 -> -25000 | Z37: ='CE P&L'!Z37+'EE P&L'!Z37+'ROW P&L'!Z39+'Non Rev P&L'!Z19 -> -25000 | ... AD37: ='CE P&L'!AD37+'EE P&L'!AD37+'ROW P&L'!AD39+'Non Rev P&L'!AD19 -> -25000 | AF37: =SUM(S37:AD37) -> -300000 | AH37: ='CE P&L'!AH37+'EE P&L'!AH37+'ROW P&L'!AH39+'Non Rev P&L'!AH19 -> -25000 | AI37: ='CE P&L'!AI37+'EE P&L'!AI37+'ROW P&L'!AI39+'Non Rev P&L'!AI19 -> -25000 | AJ37: ='CE P&L'!AJ37+'EE P&L'!AJ37+'ROW P&L'!AJ39+'Non Rev P&L'!AJ19 -> -25000 | AK37: ='CE P&L'!AK37+'EE P&L'!AK37+'ROW P&L'!AK39+'Non Rev P&L'!AK19 -> -25000 | AL37: ='CE P&L'!AL37+'EE P&L'!AL37+'ROW P&L'!AL39+'Non Rev P&L'!AL19 -> -25000 | AM37: ='CE P&L'!AM37+'EE P&L'!AM37+'ROW P&L'!AM39+'Non Rev P&L'!AM19 -> -25000 | AN37: ='CE P&L'!AN37+'EE P&L'!AN37+'ROW P&L'!AN39+'Non Rev P&L'!AN19 -> -25000 | AO37: ='CE P&L'!AO37+'EE P&L'!AO37+'ROW P&L'!AO39+'Non Rev P&L'!AO19 -> -25000 | ... AS37: ='CE P&L'!AS37+'EE P&L'!AS37+'ROW P&L'!AS39+'Non Rev P&L'!AS19 -> -25000 | AU37: =SUM(AH37:AS37) -> -300000
B38: DTC Fulfilment | D38: -40829 | E38: -94343 | F38: -113544 | G38: -108470 | H38: -45402 | I38: -140331 | J38: -142567 | K38: -40966 | L38: -280842 | M38: -241231 | N38: -90137 | O38: -68958 | Q38: =SUM(D38:O38) -> -1407620 | S38: ='UK P&L'!S38+'CE P&L'!S38+'EE P&L'!S38+'ROW P&L'!S39 -> -101054.86 | T38: ='UK P&L'!T38+'CE P&L'!T38+'EE P&L'!T38+'ROW P&L'!T39 -> -190217.21 | U38: ='UK P&L'!U38+'CE P&L'!U38+'EE P&L'!U38+'ROW P&L'!U39 -> -170776.23 | V38: ='UK P&L'!V38+'CE P&L'!V38+'EE P&L'!V38+'ROW P&L'!V39 -> -116652.79 | W38: ='UK P&L'!W38+'CE P&L'!W38+'EE P&L'!W38+'ROW P&L'!W39 -> -113749.47 | X38: ='UK P&L'!X38+'CE P&L'!X38+'EE P&L'!X38+'ROW P&L'!X39 -> -255389.43 | Y38: ='UK P&L'!Y38+'CE P&L'!Y38+'EE P&L'!Y38+'ROW P&L'!Y39 -> -139716.76 | Z38: ='UK P&L'!Z38+'CE P&L'!Z38+'EE P&L'!Z38+'ROW P&L'!Z39 -> -134160.88 | ... AD38: ='UK P&L'!AD38+'CE P&L'!AD38+'EE P&L'!AD38+'ROW P&L'!AD39 -> -166628.01 | AF38: =SUM(S38:AD38) -> -2147361.5 | AH38: ='UK P&L'!AH38+'CE P&L'!AH38+'EE P&L'!AH38+'ROW P&L'!AH39 -> -181624.13 | AI38: ='UK P&L'!AI38+'CE P&L'!AI38+'EE P&L'!AI38+'ROW P&L'!AI39 -> -310001.58 | AJ38: ='UK P&L'!AJ38+'CE P&L'!AJ38+'EE P&L'!AJ38+'ROW P&L'!AJ39 -> -274401.73 | AK38: ='UK P&L'!AK38+'CE P&L'!AK38+'EE P&L'!AK38+'ROW P&L'!AK39 -> -222327.07 | AL38: ='UK P&L'!AL38+'CE P&L'!AL38+'EE P&L'!AL38+'ROW P&L'!AL39 -> -223881.41 | AM38: ='UK P&L'!AM38+'CE P&L'!AM38+'EE P&L'!AM38+'ROW P&L'!AM39 -> -414183.6 | AN38: ='UK P&L'!AN38+'CE P&L'!AN38+'EE P&L'!AN38+'ROW P&L'!AN39 -> -241836.54 | AO38: ='UK P&L'!AO38+'CE P&L'!AO38+'EE P&L'!AO38+'ROW P&L'!AO39 -> -239740.75 | ... AS38: ='UK P&L'!AS38+'CE P&L'!AS38+'EE P&L'!AS38+'ROW P&L'!AS39 -> -278608.52 | AU38: =SUM(AH38:AS38) -> -3531765.9
B39: B2B Fulfilment | D39: -32660 | E39: -30638 | F39: -23207 | G39: -29777 | H39: -15861 | I39: -19713 | J39: -31149 | K39: -22662 | L39: -32567 | M39: -61160 | N39: -61386 | O39: -45571 | Q39: =SUM(D39:O39) -> -406351 | S39: ='UK P&L'!S39+'CE P&L'!S39+'EE P&L'!S39+'ROW P&L'!S40 -> -25014.398 | T39: ='UK P&L'!T39+'CE P&L'!T39+'EE P&L'!T39+'ROW P&L'!T40 -> -40705.69 | U39: ='UK P&L'!U39+'CE P&L'!U39+'EE P&L'!U39+'ROW P&L'!U40 -> -25069.384 | V39: ='UK P&L'!V39+'CE P&L'!V39+'EE P&L'!V39+'ROW P&L'!V40 -> -28119.403 | W39: ='UK P&L'!W39+'CE P&L'!W39+'EE P&L'!W39+'ROW P&L'!W40 -> -33425.733 | X39: ='UK P&L'!X39+'CE P&L'!X39+'EE P&L'!X39+'ROW P&L'!X40 -> -22222.436 | Y39: ='UK P&L'!Y39+'CE P&L'!Y39+'EE P&L'!Y39+'ROW P&L'!Y40 -> -26585.333 | Z39: ='UK P&L'!Z39+'CE P&L'!Z39+'EE P&L'!Z39+'ROW P&L'!Z40 -> -56219.429 | ... AD39: ='UK P&L'!AD39+'CE P&L'!AD39+'EE P&L'!AD39+'ROW P&L'!AD40 -> -28295.181 | AF39: =SUM(S39:AD39) -> -392626.17 | AH39: ='UK P&L'!AH39+'CE P&L'!AH39+'EE P&L'!AH39+'ROW P&L'!AH40 -> -31175.85 | AI39: ='UK P&L'!AI39+'CE P&L'!AI39+'EE P&L'!AI39+'ROW P&L'!AI40 -> -39783.995 | AJ39: ='UK P&L'!AJ39+'CE P&L'!AJ39+'EE P&L'!AJ39+'ROW P&L'!AJ40 -> -53718.706 | AK39: ='UK P&L'!AK39+'CE P&L'!AK39+'EE P&L'!AK39+'ROW P&L'!AK40 -> -53970.49 | AL39: ='UK P&L'!AL39+'CE P&L'!AL39+'EE P&L'!AL39+'ROW P&L'!AL40 -> -53819.177 | AM39: ='UK P&L'!AM39+'CE P&L'!AM39+'EE P&L'!AM39+'ROW P&L'!AM40 -> -35429.574 | AN39: ='UK P&L'!AN39+'CE P&L'!AN39+'EE P&L'!AN39+'ROW P&L'!AN40 -> -46714.256 | AO39: ='UK P&L'!AO39+'CE P&L'!AO39+'EE P&L'!AO39+'ROW P&L'!AO40 -> -95660.341 | ... AS39: ='UK P&L'!AS39+'CE P&L'!AS39+'EE P&L'!AS39+'ROW P&L'!AS40 -> -38127.997 | AU39: =SUM(AH39:AS39) -> -605533.76
B40: Marketplace Fulfilment | D40: -68191 | E40: -98632 | F40: -97042 | G40: -97653 | H40: -74893 | I40: -114084 | J40: -93476 | K40: -99890 | L40: -118384 | M40: -126370 | N40: -126370 | O40: -98160 | Q40: =SUM(D40:O40) -> -1213145 | S40: ='UK P&L'!S40+'CE P&L'!S40+'EE P&L'!S40+'ROW P&L'!S41 -> -80771.182 | T40: ='UK P&L'!T40+'CE P&L'!T40+'EE P&L'!T40+'ROW P&L'!T41 -> -111689.22 | U40: ='UK P&L'!U40+'CE P&L'!U40+'EE P&L'!U40+'ROW P&L'!U41 -> -104700.56 | V40: ='UK P&L'!V40+'CE P&L'!V40+'EE P&L'!V40+'ROW P&L'!V41 -> -103564.46 | W40: ='UK P&L'!W40+'CE P&L'!W40+'EE P&L'!W40+'ROW P&L'!W41 -> -100447.14 | X40: ='UK P&L'!X40+'CE P&L'!X40+'EE P&L'!X40+'ROW P&L'!X41 -> -128762.07 | Y40: ='UK P&L'!Y40+'CE P&L'!Y40+'EE P&L'!Y40+'ROW P&L'!Y41 -> -101511.08 | Z40: ='UK P&L'!Z40+'CE P&L'!Z40+'EE P&L'!Z40+'ROW P&L'!Z41 -> -111891.11 | ... AD40: ='UK P&L'!AD40+'CE P&L'!AD40+'EE P&L'!AD40+'ROW P&L'!AD41 -> -110165.88 | AF40: =SUM(S40:AD40) -> -1370465.1 | AH40: ='UK P&L'!AH40+'CE P&L'!AH40+'EE P&L'!AH40+'ROW P&L'!AH41 -> -93734.916 | AI40: ='UK P&L'!AI40+'CE P&L'!AI40+'EE P&L'!AI40+'ROW P&L'!AI41 -> -118370.12 | AJ40: ='UK P&L'!AJ40+'CE P&L'!AJ40+'EE P&L'!AJ40+'ROW P&L'!AJ41 -> -111200.99 | AK40: ='UK P&L'!AK40+'CE P&L'!AK40+'EE P&L'!AK40+'ROW P&L'!AK41 -> -109767.29 | AL40: ='UK P&L'!AL40+'CE P&L'!AL40+'EE P&L'!AL40+'ROW P&L'!AL41 -> -106334.65 | AM40: ='UK P&L'!AM40+'CE P&L'!AM40+'EE P&L'!AM40+'ROW P&L'!AM41 -> -138548.95 | AN40: ='UK P&L'!AN40+'CE P&L'!AN40+'EE P&L'!AN40+'ROW P&L'!AN41 -> -108764.73 | AO40: ='UK P&L'!AO40+'CE P&L'!AO40+'EE P&L'!AO40+'ROW P&L'!AO41 -> -117033.43 | ... AS40: ='UK P&L'!AS40+'CE P&L'!AS40+'EE P&L'!AS40+'ROW P&L'!AS41 -> -120428.55 | AU40: =SUM(AH40:AS40) -> -1456135.9
B41: TikTok Fulfilment | D41: -3216 | E41: -3283 | F41: -3955 | G41: -3000 | H41: -2896 | I41: -2362 | J41: -1735 | K41: -1155 | L41: -350 | M41: -2303 | N41: -2433 | O41: -2576 | Q41: =SUM(D41:O41) -> -29264 | S41: ='UK P&L'!S41+'CE P&L'!S41+'EE P&L'!S41+'ROW P&L'!S42 -> 0 | T41: ='UK P&L'!T41+'CE P&L'!T41+'EE P&L'!T41+'ROW P&L'!T42 -> 0 | U41: ='UK P&L'!U41+'CE P&L'!U41+'EE P&L'!U41+'ROW P&L'!U42 -> 0 | V41: ='UK P&L'!V41+'CE P&L'!V41+'EE P&L'!V41+'ROW P&L'!V42 -> 0 | W41: ='UK P&L'!W41+'CE P&L'!W41+'EE P&L'!W41+'ROW P&L'!W42 -> 0 | X41: ='UK P&L'!X41+'CE P&L'!X41+'EE P&L'!X41+'ROW P&L'!X42 -> 0 | Y41: ='UK P&L'!Y41+'CE P&L'!Y41+'EE P&L'!Y41+'ROW P&L'!Y42 -> 0 | Z41: ='UK P&L'!Z41+'CE P&L'!Z41+'EE P&L'!Z41+'ROW P&L'!Z42 -> 0 | ... AD41: ='UK P&L'!AD41+'CE P&L'!AD41+'EE P&L'!AD41+'ROW P&L'!AD42 -> 0 | AF41: =SUM(S41:AD41) -> 0 | AH41: ='UK P&L'!AH41+'CE P&L'!AH41+'EE P&L'!AH41+'ROW P&L'!AH42 -> 0 | AI41: ='UK P&L'!AI41+'CE P&L'!AI41+'EE P&L'!AI41+'ROW P&L'!AI42 -> 0 | AJ41: ='UK P&L'!AJ41+'CE P&L'!AJ41+'EE P&L'!AJ41+'ROW P&L'!AJ42 -> 0 | AK41: ='UK P&L'!AK41+'CE P&L'!AK41+'EE P&L'!AK41+'ROW P&L'!AK42 -> 0 | AL41: ='UK P&L'!AL41+'CE P&L'!AL41+'EE P&L'!AL41+'ROW P&L'!AL42 -> 0 | AM41: ='UK P&L'!AM41+'CE P&L'!AM41+'EE P&L'!AM41+'ROW P&L'!AM42 -> 0 | AN41: ='UK P&L'!AN41+'CE P&L'!AN41+'EE P&L'!AN41+'ROW P&L'!AN42 -> 0 | AO41: ='UK P&L'!AO41+'CE P&L'!AO41+'EE P&L'!AO41+'ROW P&L'!AO42 -> 0 | ... AS41: ='UK P&L'!AS41+'CE P&L'!AS41+'EE P&L'!AS41+'ROW P&L'!AS42 -> 0 | AU41: =SUM(AH41:AS41) -> 0
B43: Total Fulfilment | D43: =SUM(D37:D42) -> -166380 | E43: =SUM(E37:E42) -> -268033 | F43: =SUM(F37:F42) -> -260591 | G43: =SUM(G37:G42)-1 -> -268472 | H43: =SUM(H37:H42) -> -167028 | I43: =SUM(I37:I42) -> -315668 | J43: =SUM(J37:J42)-1 -> -305076 | K43: =SUM(K37:K42) -> -190143 | L43: =SUM(L37:L42) -> -423510 | M43: =SUM(M37:M42) -> -468515 | N43: =SUM(N37:N42)+1 -> -321778 | O43: =SUM(O37:O42) -> -251775 | Q43: =SUM(D43:O43) -> -3406969 | S43: =SUM(S37:S42) -> -231840.44 | T43: =SUM(T37:T42) -> -367612.12 | U43: =SUM(U37:U42) -> -325546.17 | V43: =SUM(V37:V42) -> -273336.65 | W43: =SUM(W37:W42) -> -272622.34 | X43: =SUM(X37:X42) -> -431373.93 | Y43: =SUM(Y37:Y42) -> -292813.17 | Z43: =SUM(Z37:Z42) -> -327271.42 | ... AD43: =SUM(AD37:AD42) -> -330089.06 | AF43: =SUM(S43:AD43) -> -4210452.7 | AH43: =SUM(AH37:AH42) -> -331534.9 | AI43: =SUM(AI37:AI42) -> -493155.7 | AJ43: =SUM(AJ37:AJ42) -> -464321.43 | AK43: =SUM(AK37:AK42) -> -411064.85 | AL43: =SUM(AL37:AL42) -> -409035.24 | AM43: =SUM(AM37:AM42) -> -613162.12 | AN43: =SUM(AN37:AN42) -> -422315.54 | AO43: =SUM(AO37:AO42) -> -477434.53 | ... AS43: =SUM(AS37:AS42) -> -462165.07 | AU43: =SUM(AH43:AS43) -> -5893435.6
Q44: =-Q43/Q12 -> 0.18898521 | AF44: =-AF43/AF12 -> 0.17993976 | AU44: =-AU43/AU12 -> 0.17174308
B45: DTC CM2 | D45: =D23+D38 -> 115122 | E45: =E23+E38 -> 367638 | F45: =F23+F38 -> 355708 | G45: =G23+G38 -> 326412 | H45: =H23+H38 -> 167293 | I45: =I23+I38 -> 509074 | J45: =J23+J38 -> 464744 | K45: =K23+K38 -> 145207 | ... O45: =O23+O38 -> 292165 | Q45: =Q23+Q38 -> 4850117 | S45: =S23+S38 -> 352063.06 | T45: =T23+T38 -> 618177.27 | U45: =U23+U38 -> 564239.63 | V45: =V23+V38 -> 420762.35 | W45: =W23+W38 -> 415549.15 | X45: =X23+X38 -> 846277.91 | Y45: =Y23+Y38 -> 517384.07 | Z45: =Z23+Z38 -> 505338.35 | ... AD45: =AD23+AD38 -> 646592.75 | AF45: =AF23+AF38 -> 7518297 | AH45: =AH23+AH38 -> 706270.69 | AI45: =AI23+AI38 -> 1090968.8 | AJ45: =AJ23+AJ38 -> 1005832.2 | AK45: =AK23+AK38 -> 867247.33 | AL45: =AL23+AL38 -> 875775.66 | AM45: =AM23+AM38 -> 1452566.6 | AN45: =AN23+AN38 -> 958589.55 | AO45: =AO23+AO38 -> 959280.62 | ... AS45: =AS23+AS38 -> 1133887.8 | AU45: =AU23+AU38 -> 13273114
B46: B2B CM2 | D46: =D24+D39 -> 417154 | E46: =E24+E39 -> 321866 | F46: =F24+F39 -> 179804 | G46: =G24+G39 -> 350481 | H46: =H24+H39 -> 378161 | I46: =I24+I39 -> 259341 | J46: =J24+J39 -> 187775 | K46: =K24+K39 -> 318155 | ... O46: =O24+O39 -> 336083 | Q46: =Q24+Q39 -> 4169106 | S46: =S24+S39 -> 299379.29 | T46: =T24+T39 -> 446705.17 | U46: =U24+U39 -> 357616.73 | V46: =V24+V39 -> 375699.4 | W46: =W24+W39 -> 420982.43 | X46: =X24+X39 -> 282498.31 | Y46: =Y24+Y39 -> 369478.21 | Z46: =Z24+Z39 -> 758072.76 | ... AD46: =AD24+AD39 -> 334966.85 | AF46: =AF24+AF39 -> 4917968.2 | AH46: =AH24+AH39 -> 365315.59 | AI46: =AI24+AI39 -> 396381.66 | AJ46: =AJ24+AJ39 -> 431866.01 | AK46: =AK24+AK39 -> 460860.03 | AL46: =AL24+AL39 -> 490395.89 | AM46: =AM24+AM39 -> 340911.77 | AN46: =AN24+AN39 -> 433598.24 | AO46: =AO24+AO39 -> 936381.53 | ... AS46: =AS24+AS39 -> 402580.4 | AU46: =AU24+AU39 -> 5914048.2
B47: Marketplace CM2 | D47: =D25+D40 -> 83698 | E47: =E25+E40 -> 103596 | F47: =F25+F40 -> 88937 | G47: =G25+G40 -> 91047 | H47: =H25+H40 -> 94536 | I47: =I25+I40 -> 109888 | J47: =J25+J40 -> 89352 | K47: =K25+K40 -> 94089 | ... O47: =O25+O40 -> 102006 | Q47: =Q25+Q40 -> 1237363 | S47: =S25+S40 -> 79195.402 | T47: =T25+T40 -> 109058.06 | U47: =U25+U40 -> 102523.62 | V47: =V25+V40 -> 101515.11 | W47: =W25+W40 -> 98586.015 | X47: =X25+X40 -> 126018.35 | Y47: =Y25+Y40 -> 99563.909 | Z47: =Z25+Z40 -> 109458.21 | ... AD47: =AD25+AD40 -> 106921.51 | AF47: =AF25+AF40 -> 1339173.7 | AH47: =AH25+AH40 -> 90814.57 | AI47: =AI25+AI40 -> 115103.91 | AJ47: =AJ25+AJ40 -> 108405.66 | AK47: =AK25+AK40 -> 107132.11 | AL47: =AL25+AL40 -> 103920.64 | AM47: =AM25+AM40 -> 134848.18 | AN47: =AN25+AN40 -> 106115.68 | AO47: =AO25+AO40 -> 114135.8 | ... AS47: =AS25+AS40 -> 116149.97 | AU47: =AU25+AU40 -> 1416658.6
B48: TikTok CM2 | D48: =D26+D41 -> 8078 | E48: =E26+E41 -> 2881 | F48: =F26+F41 -> 3589 | G48: =G26+G41 -> 1293 | H48: =H26+H41 -> 3153 | I48: =I26+I41 -> 3211 | J48: =J26+J41 -> 3536 | K48: =K26+K41 -> 2529 | ... O48: =O26+O41 -> 3782 | Q48: =Q26+Q41 -> 41618 | S48: =S26+S41 -> 0 | T48: =T26+T41 -> 0 | U48: =U26+U41 -> 0 | V48: =V26+V41 -> 0 | W48: =W26+W41 -> 0 | X48: =X26+X41 -> 0 | Y48: =Y26+Y41 -> 0 | Z48: =Z26+Z41 -> 0 | ... AD48: =AD26+AD41 -> 0 | AF48: =AF26+AF41 -> 0 | AH48: =AH26+AH41 -> 0 | AI48: =AI26+AI41 -> 0 | AJ48: =AJ26+AJ41 -> 0 | AK48: =AK26+AK41 -> 0 | AL48: =AL26+AL41 -> 0 | AM48: =AM26+AM41 -> 0 | AN48: =AN26+AN41 -> 0 | AO48: =AO26+AO41 -> 0 | ... AS48: =AS26+AS41 -> 0 | AU48: =AU26+AU41 -> 0
B49: Total CM2 | D49: =D27+D43 -> 602568 | E49: =E27+E43 -> 754844 | F49: =F27+F43-1 -> 605194 | G49: =G27+G43 -> 739661 | H49: =H27+H43 -> 615167 | I49: =I27+I43 -> 842336 | J49: =J27+J43 -> 709258 | K49: =K27+K43 -> 534510 | L49: =L27+L43 -> 1380402.5 | M49: =M27+M43 -> 1501696 | N49: =N27+N43 -> 964454 | O49: =O27+O43 -> 697526.5 | Q49: =Q27+Q43 -> 9947618 | S49: =S27+S43 -> 705637.75 | T49: =T27+T43 -> 1148940.5 | U49: =U27+U43 -> 999379.97 | V49: =V27+V43 -> 872976.86 | W49: =W27+W43 -> 910117.6 | X49: =X27+X43 -> 1229794.6 | Y49: =Y27+Y43 -> 961426.19 | Z49: =Z27+Z43 -> 1347869.3 | ... AD49: =AD27+AD43 -> 1063481.1 | AF49: =AF27+AF43 -> 13475439 | AH49: =AH27+AH43 -> 1137400.8 | AI49: =AI27+AI43 -> 1577454.4 | AJ49: =AJ27+AJ43 -> 1521103.9 | AK49: =AK27+AK43 -> 1410239.5 | AL49: =AL27+AL43 -> 1445092.2 | AM49: =AM27+AM43 -> 1903326.6 | AN49: =AN27+AN43 -> 1473303.5 | AO49: =AO27+AO43 -> 1984797.9 | ... AS49: =AS27+AS43 -> 1627618.1 | AU49: =AU27+AU43 -> 20303821
B51: DTC CM2% | D51: =IFERROR(D45/D7,0) -> 0.56766552 | E51: =IFERROR(E45/E7,0) -> 0.61140224 | F51: =IFERROR(F45/F7,0) -> 0.56302065 | G51: =IFERROR(G45/G7,0) -> 0.57662324 | H51: =IFERROR(H45/H7,0) -> 0.63515319 | I51: =IFERROR(I45/I7,0) -> 0.58869908 | J51: =IFERROR(J45/J7,0) -> 0.56571234 | K51: =IFERROR(K45/K7,0) -> 0.61616637 | ... O51: =IFERROR(O45/O7,0) -> 0.62296505 | Q51: =IFERROR(Q45/Q7,0) -> 0.58064268 | S51: =IFERROR(S45/S7,0) -> 0.59926291 | T51: =IFERROR(T45/T7,0) -> 0.58638169 | U51: =IFERROR(U45/U7,0) -> 0.58947144 | V51: =IFERROR(V45/V7,0) -> 0.60556645 | W51: =IFERROR(W45/W7,0) -> 0.60785685 | X51: =IFERROR(X45/X7,0) -> 0.59001824 | Y51: =IFERROR(Y45/Y7,0) -> 0.61028332 | Z51: =IFERROR(Z45/Z7,0) -> 0.61330837 | ... AD51: =IFERROR(AD45/AD7,0) -> 0.61854625 | AF51: =IFERROR(AF45/AF7,0) -> 0.60016747 | AH51: =IFERROR(AH45/AH7,0) -> 0.62310221 | AI51: =IFERROR(AI45/AI7,0) -> 0.60377923 | AJ51: =IFERROR(AJ45/AJ7,0) -> 0.61175039 | AK51: =IFERROR(AK45/AK7,0) -> 0.6236937 | AL51: =IFERROR(AL45/AL7,0) -> 0.62422827 | AM51: =IFERROR(AM45/AM7,0) -> 0.60309567 | AN51: =IFERROR(AN45/AN7,0) -> 0.62672506 | AO51: =IFERROR(AO45/AO7,0) -> 0.62849872 | ... AS51: =IFERROR(AS45/AS7,0) -> 0.63167626 | AU51: =IFERROR(AU45/AU7,0) -> 0.61657797
B52: B2B CM2% | D52: =IFERROR(D46/D8,0) -> 0.62767869 | E52: =IFERROR(E46/E8,0) -> 0.62881893 | F52: =IFERROR(F46/F8,0) -> 0.62157631 | G52: =IFERROR(G46/G8,0) -> 0.68759245 | H52: =IFERROR(H46/H8,0) -> 0.63901755 | I52: =IFERROR(I46/I8,0) -> 0.61988431 | J52: =IFERROR(J46/J8,0) -> 0.56941892 | K52: =IFERROR(K46/K8,0) -> 0.62848784 | ... O52: =IFERROR(O46/O8,0) -> 0.58999917 | Q52: =IFERROR(Q46/Q8,0) -> 0.6289228 | S52: =IFERROR(S46/S8,0) -> 0.66623416 | T52: =IFERROR(T46/T8,0) -> 0.63284272 | U52: =IFERROR(U46/U8,0) -> 0.63846338 | V52: =IFERROR(V46/V8,0) -> 0.63795769 | W52: =IFERROR(W46/W8,0) -> 0.64603819 | X52: =IFERROR(X46/X8,0) -> 0.64440261 | Y52: =IFERROR(Y46/Y8,0) -> 0.6529389 | Z52: =IFERROR(Z46/Z8,0) -> 0.66609181 | ... AD52: =IFERROR(AD46/AD8,0) -> 0.65081159 | AF52: =IFERROR(AF46/AF8,0) -> 0.64985454 | AH52: =IFERROR(AH46/AH8,0) -> 0.66376512 | AI52: =IFERROR(AI46/AI8,0) -> 0.63579274 | AJ52: =IFERROR(AJ46/AJ8,0) -> 0.60985702 | AK52: =IFERROR(AK46/AK8,0) -> 0.61625689 | AL52: =IFERROR(AL46/AL8,0) -> 0.6272085 | AM52: =IFERROR(AM46/AM8,0) -> 0.63210117 | AN52: =IFERROR(AN46/AN8,0) -> 0.6329038 | AO52: =IFERROR(AO46/AO8,0) -> 0.64724591 | ... AS52: =IFERROR(AS46/AS8,0) -> 0.64286292 | AU52: =IFERROR(AU46/AU8,0) -> 0.63695017
B53: Marketplace CM2% | D53: =IFERROR(D47/D9,0) -> 0.47547847 | E53: =IFERROR(E47/E9,0) -> 0.42916442 | F53: =IFERROR(F47/F9,0) -> 0.39653919 | G53: =IFERROR(G47/G9,0) -> 0.40208712 | H53: =IFERROR(H47/H9,0) -> 0.46759491 | I53: =IFERROR(I47/I9,0) -> 0.4074015 | J53: =IFERROR(J47/J9,0) -> 0.40615469 | K53: =IFERROR(K47/K9,0) -> 0.39263791 | ... O53: =IFERROR(O47/O9,0) -> 0.42012183 | Q53: =IFERROR(Q47/Q9,0) -> 0.41861467 | S53: =IFERROR(S47/S9,0) -> 0.40596122 | T53: =IFERROR(T47/T9,0) -> 0.40511307 | U53: =IFERROR(U47/U9,0) -> 0.40569285 | V53: =IFERROR(V47/V9,0) -> 0.4059029 | W53: =IFERROR(W47/W9,0) -> 0.40616617 | X53: =IFERROR(X47/X9,0) -> 0.40558473 | Y53: =IFERROR(Y47/Y9,0) -> 0.40602964 | Z53: =IFERROR(Z47/Z9,0) -> 0.4054936 | ... AD53: =IFERROR(AD47/AD9,0) -> 0.40387256 | AF53: =IFERROR(AF47/AF9,0) -> 0.40526525 | AH53: =IFERROR(AH47/AH9,0) -> 0.40351208 | AI53: =IFERROR(AI47/AI9,0) -> 0.40426427 | AJ53: =IFERROR(AJ47/AJ9,0) -> 0.40478119 | AK53: =IFERROR(AK47/AK9,0) -> 0.40501878 | AL53: =IFERROR(AL47/AL9,0) -> 0.40529266 | AM53: =IFERROR(AM47/AM9,0) -> 0.40445015 | AN53: =IFERROR(AN47/AN9,0) -> 0.4049455 | AO53: =IFERROR(AO47/AO9,0) -> 0.40486077 | ... AS53: =IFERROR(AS47/AS9,0) -> 0.40258504 | AU53: =IFERROR(AU47/AU9,0) -> 0.40436587
B54: TikTok CM2% | D54: =IFERROR(D48/D10,0) -> 0.59283722 | E54: =IFERROR(E48/E10,0) -> 0.3632123 | F54: =IFERROR(F48/F10,0) -> 0.37667926 | G54: =IFERROR(G48/G10,0) -> 0.19825207 | H54: =IFERROR(H48/H10,0) -> 0.34659778 | I54: =IFERROR(I48/I10,0) -> 0.46062258 | J54: =IFERROR(J48/J10,0) -> 0.55510204 | K54: =IFERROR(K48/K10,0) -> 0.57752912 | ... O54: =IFERROR(O48/O10,0) -> 0.48774826 | Q54: =IFERROR(Q48/Q10,0) -> 0.46308083 | S54: =IFERROR(S48/S10,0) -> 0 | T54: =IFERROR(T48/T10,0) -> 0 | U54: =IFERROR(U48/U10,0) -> 0 | V54: =IFERROR(V48/V10,0) -> 0 | W54: =IFERROR(W48/W10,0) -> 0 | X54: =IFERROR(X48/X10,0) -> 0 | Y54: =IFERROR(Y48/Y10,0) -> 0 | Z54: =IFERROR(Z48/Z10,0) -> 0 | ... AD54: =IFERROR(AD48/AD10,0) -> 0 | AF54: =IFERROR(AF48/AF10,0) -> 0 | AH54: =IFERROR(AH48/AH10,0) -> 0 | AI54: =IFERROR(AI48/AI10,0) -> 0 | AJ54: =IFERROR(AJ48/AJ10,0) -> 0 | AK54: =IFERROR(AK48/AK10,0) -> 0 | AL54: =IFERROR(AL48/AL10,0) -> 0 | AM54: =IFERROR(AM48/AM10,0) -> 0 | AN54: =IFERROR(AN48/AN10,0) -> 0 | AO54: =IFERROR(AO48/AO10,0) -> 0 | ... AS54: =IFERROR(AS48/AS10,0) -> 0 | AU54: =IFERROR(AU48/AU10,0) -> 0
B55: Total CM2% | D55: =IFERROR(D49/D12,0) -> 0.57004575 | E55: =IFERROR(E49/E12,0) -> 0.55402086 | F55: =IFERROR(F49/F12,0) -> 0.52403783 | G55: =IFERROR(G49/G12,0) -> 0.56516384 | H55: =IFERROR(H49/H12,0) -> 0.57683786 | I55: =IFERROR(I49/I12,0) -> 0.54002336 | J55: =IFERROR(J49/J12,0) -> 0.51483141 | K55: =IFERROR(K49/K12,0) -> 0.54215603 | ... O55: =IFERROR(O49/O12,0) -> 0.54106257 | Q55: =IFERROR(Q49/Q12,0) -> 0.55179623 | S55: =IFERROR(S49/S12,0) -> 0.57278807 | T55: =IFERROR(T49/T12,0) -> 0.5661763 | U55: =IFERROR(U49/U12,0) -> 0.56461212 | V55: =IFERROR(V49/V12,0) -> 0.569148 | W55: =IFERROR(W49/W12,0) -> 0.57675738 | X55: =IFERROR(X49/X12,0) -> 0.56324214 | Y55: =IFERROR(Y49/Y12,0) -> 0.57957051 | Z55: =IFERROR(Z49/Z12,0) -> 0.60388858 | ... AD55: =IFERROR(AD49/AD12,0) -> 0.58280145 | AF55: =IFERROR(AF49/AF12,0) -> 0.5758923 | AH55: =IFERROR(AH49/AH12,0) -> 0.59583974 | AI55: =IFERROR(AI49/AI12,0) -> 0.58099966 | AJ55: =IFERROR(AJ49/AJ12,0) -> 0.58054225 | AK55: =IFERROR(AK49/AK12,0) -> 0.58690259 | AL55: =IFERROR(AL49/AL12,0) -> 0.59194694 | AM55: =IFERROR(AM49/AM12,0) -> 0.58005968 | AN55: =IFERROR(AN49/AN12,0) -> 0.59487409 | AO55: =IFERROR(AO49/AO12,0) -> 0.60978108 | ... AS55: =IFERROR(AS49/AS12,0) -> 0.60064438 | AU55: =IFERROR(AU49/AU12,0) -> 0.59168214
B57: Marketing
B59: D2C Model Marketing | D59: - | E59: - | F59: -12713 | G59: -5066 | H59: -9981 | I59: -9624 | J59: -14918 | K59: -6184 | L59: -14908 | M59: -14051 | N59: -8128 | O59: -6511 | Q59: =SUM(D59:O59) -> -102084 | S59: ='UK P&L'!S59+'CE P&L'!S59+'EE P&L'!S59+'ROW P&L'!S60 -> -185992.65 | T59: ='UK P&L'!T59+'CE P&L'!T59+'EE P&L'!T59+'ROW P&L'!T60 -> -323604.4 | U59: ='UK P&L'!U59+'CE P&L'!U59+'EE P&L'!U59+'ROW P&L'!U60 -> -325113.2 | V59: ='UK P&L'!V59+'CE P&L'!V59+'EE P&L'!V59+'ROW P&L'!V60 -> -253120.5 | W59: ='UK P&L'!W59+'CE P&L'!W59+'EE P&L'!W59+'ROW P&L'!W60 -> -268047 | X59: ='UK P&L'!X59+'CE P&L'!X59+'EE P&L'!X59+'ROW P&L'!X60 -> -420211.6 | Y59: ='UK P&L'!Y59+'CE P&L'!Y59+'EE P&L'!Y59+'ROW P&L'!Y60 -> -297916.37 | Z59: ='UK P&L'!Z59+'CE P&L'!Z59+'EE P&L'!Z59+'ROW P&L'!Z60 -> -296979.31 | ... AD59: ='UK P&L'!AD59+'CE P&L'!AD59+'EE P&L'!AD59+'ROW P&L'!AD60 -> -340671.88 | AF59: =SUM(S59:AD59) -> -4105670.9 | AH59: ='UK P&L'!AH59+'CE P&L'!AH59+'EE P&L'!AH59+'ROW P&L'!AH60 -> -349776.07 | AI59: ='UK P&L'!AI59+'CE P&L'!AI59+'EE P&L'!AI59+'ROW P&L'!AI60 -> -560188.36 | AJ59: ='UK P&L'!AJ59+'CE P&L'!AJ59+'EE P&L'!AJ59+'ROW P&L'!AJ60 -> -521396.66 | AK59: ='UK P&L'!AK59+'CE P&L'!AK59+'EE P&L'!AK59+'ROW P&L'!AK60 -> -420396.52 | AL59: ='UK P&L'!AL59+'CE P&L'!AL59+'EE P&L'!AL59+'ROW P&L'!AL60 -> -448584.82 | AM59: ='UK P&L'!AM59+'CE P&L'!AM59+'EE P&L'!AM59+'ROW P&L'!AM60 -> -684131.18 | AN59: ='UK P&L'!AN59+'CE P&L'!AN59+'EE P&L'!AN59+'ROW P&L'!AN60 -> -435270.59 | AO59: ='UK P&L'!AO59+'CE P&L'!AO59+'EE P&L'!AO59+'ROW P&L'!AO60 -> -477248.6 | ... AS59: ='UK P&L'!AS59+'CE P&L'!AS59+'EE P&L'!AS59+'ROW P&L'!AS60 -> -547205.91 | AU59: =SUM(AH59:AS59) -> -6536376.2
B60: D2C Model Brand | D60: -1674 | E60: -2640 | F60: -31540 | G60: -13835 | H60: -33155 | I60: -1701 | J60: -27530 | K60: -17939 | L60: -20222 | M60: -30300 | N60: -29200 | O60: -28300 | Q60: =SUM(D60:O60) -> -238036 | S60: ='UK P&L'!S60+'CE P&L'!S60+'EE P&L'!S60+'ROW P&L'!S61 -> -49500 | T60: ='UK P&L'!T60+'CE P&L'!T60+'EE P&L'!T60+'ROW P&L'!T61 -> -40500 | U60: ='UK P&L'!U60+'CE P&L'!U60+'EE P&L'!U60+'ROW P&L'!U61 -> -41000 | V60: ='UK P&L'!V60+'CE P&L'!V60+'EE P&L'!V60+'ROW P&L'!V61 -> -34500 | W60: ='UK P&L'!W60+'CE P&L'!W60+'EE P&L'!W60+'ROW P&L'!W61 -> -34000 | X60: ='UK P&L'!X60+'CE P&L'!X60+'EE P&L'!X60+'ROW P&L'!X61 -> -40500 | Y60: ='UK P&L'!Y60+'CE P&L'!Y60+'EE P&L'!Y60+'ROW P&L'!Y61 -> -35000 | Z60: ='UK P&L'!Z60+'CE P&L'!Z60+'EE P&L'!Z60+'ROW P&L'!Z61 -> -40000 | ... AD60: ='UK P&L'!AD60+'CE P&L'!AD60+'EE P&L'!AD60+'ROW P&L'!AD61 -> -32000 | AF60: =SUM(S60:AD60) -> -462500 | AG60: =AF60/AF8 -> -0.061114207 | AH60: ='UK P&L'!AH60+'CE P&L'!AH60+'EE P&L'!AH60+'ROW P&L'!AH61 -> -38500 | AI60: ='UK P&L'!AI60+'CE P&L'!AI60+'EE P&L'!AI60+'ROW P&L'!AI61 -> -34500 | AJ60: ='UK P&L'!AJ60+'CE P&L'!AJ60+'EE P&L'!AJ60+'ROW P&L'!AJ61 -> -34500 | AK60: ='UK P&L'!AK60+'CE P&L'!AK60+'EE P&L'!AK60+'ROW P&L'!AK61 -> -31000 | AL60: ='UK P&L'!AL60+'CE P&L'!AL60+'EE P&L'!AL60+'ROW P&L'!AL61 -> -30500 | AM60: ='UK P&L'!AM60+'CE P&L'!AM60+'EE P&L'!AM60+'ROW P&L'!AM61 -> -34500 | AN60: ='UK P&L'!AN60+'CE P&L'!AN60+'EE P&L'!AN60+'ROW P&L'!AN61 -> -31500 | AO60: ='UK P&L'!AO60+'CE P&L'!AO60+'EE P&L'!AO60+'ROW P&L'!AO61 -> -33500 | ... AS60: ='UK P&L'!AS60+'CE P&L'!AS60+'EE P&L'!AS60+'ROW P&L'!AS61 -> -31000 | AU60: =SUM(AH60:AS60) -> -397500
B61: Influencers | D61: -45733 | E61: -105781 | F61: -94756 | G61: -112698 | H61: -65047 | I61: -125239 | J61: -95269 | K61: -75437 | L61: -181121 | M61: -222170 | N61: -99371 | O61: -68900 | Q61: =SUM(D61:O61) -> -1291522 | S61: ='UK P&L'!S61+'CE P&L'!S61+'EE P&L'!S61+'ROW P&L'!S62 -> 0 | T61: ='UK P&L'!T61+'CE P&L'!T61+'EE P&L'!T61+'ROW P&L'!T62 -> 0 | U61: ='UK P&L'!U61+'CE P&L'!U61+'EE P&L'!U61+'ROW P&L'!U62 -> 0 | V61: ='UK P&L'!V61+'CE P&L'!V61+'EE P&L'!V61+'ROW P&L'!V62 -> 0 | W61: ='UK P&L'!W61+'CE P&L'!W61+'EE P&L'!W61+'ROW P&L'!W62 -> 0 | X61: ='UK P&L'!X61+'CE P&L'!X61+'EE P&L'!X61+'ROW P&L'!X62 -> 0 | Y61: ='UK P&L'!Y61+'CE P&L'!Y61+'EE P&L'!Y61+'ROW P&L'!Y62 -> 0 | Z61: ='UK P&L'!Z61+'CE P&L'!Z61+'EE P&L'!Z61+'ROW P&L'!Z62 -> 0 | ... AD61: ='UK P&L'!AD61+'CE P&L'!AD61+'EE P&L'!AD61+'ROW P&L'!AD62 -> 0 | AF61: =SUM(S61:AD61) -> 0 | AH61: ='UK P&L'!AH61+'CE P&L'!AH61+'EE P&L'!AH61+'ROW P&L'!AH62 -> 0 | AI61: ='UK P&L'!AI61+'CE P&L'!AI61+'EE P&L'!AI61+'ROW P&L'!AI62 -> 0 | AJ61: ='UK P&L'!AJ61+'CE P&L'!AJ61+'EE P&L'!AJ61+'ROW P&L'!AJ62 -> 0 | AK61: ='UK P&L'!AK61+'CE P&L'!AK61+'EE P&L'!AK61+'ROW P&L'!AK62 -> 0 | AL61: ='UK P&L'!AL61+'CE P&L'!AL61+'EE P&L'!AL61+'ROW P&L'!AL62 -> 0 | AM61: ='UK P&L'!AM61+'CE P&L'!AM61+'EE P&L'!AM61+'ROW P&L'!AM62 -> 0 | AN61: ='UK P&L'!AN61+'CE P&L'!AN61+'EE P&L'!AN61+'ROW P&L'!AN62 -> 0 | AO61: ='UK P&L'!AO61+'CE P&L'!AO61+'EE P&L'!AO61+'ROW P&L'!AO62 -> 0 | ... AS61: ='UK P&L'!AS61+'CE P&L'!AS61+'EE P&L'!AS61+'ROW P&L'!AS62 -> 0 | AU61: =SUM(AH61:AS61) -> 0
B62: PPC | D62: -8953 | E62: -20428 | F62: -25773 | G62: -32659 | H62: -19672 | I62: -34056 | J62: -39340 | K62: -27582 | L62: -67047 | M62: -65480 | N62: -31386 | O62: -18482 | Q62: =SUM(D62:O62) -> -390858 | S62: ='UK P&L'!S62+'CE P&L'!S62+'EE P&L'!S62+'ROW P&L'!S63 -> 0 | T62: ='UK P&L'!T62+'CE P&L'!T62+'EE P&L'!T62+'ROW P&L'!T63 -> 0 | U62: ='UK P&L'!U62+'CE P&L'!U62+'EE P&L'!U62+'ROW P&L'!U63 -> 0 | V62: ='UK P&L'!V62+'CE P&L'!V62+'EE P&L'!V62+'ROW P&L'!V63 -> 0 | W62: ='UK P&L'!W62+'CE P&L'!W62+'EE P&L'!W62+'ROW P&L'!W63 -> 0 | X62: ='UK P&L'!X62+'CE P&L'!X62+'EE P&L'!X62+'ROW P&L'!X63 -> 0 | Y62: ='UK P&L'!Y62+'CE P&L'!Y62+'EE P&L'!Y62+'ROW P&L'!Y63 -> 0 | Z62: ='UK P&L'!Z62+'CE P&L'!Z62+'EE P&L'!Z62+'ROW P&L'!Z63 -> 0 | ... AD62: ='UK P&L'!AD62+'CE P&L'!AD62+'EE P&L'!AD62+'ROW P&L'!AD63 -> 0 | AF62: =SUM(S62:AD62) -> 0 | AH62: ='UK P&L'!AH62+'CE P&L'!AH62+'EE P&L'!AH62+'ROW P&L'!AH63 -> 0 | AI62: ='UK P&L'!AI62+'CE P&L'!AI62+'EE P&L'!AI62+'ROW P&L'!AI63 -> 0 | AJ62: ='UK P&L'!AJ62+'CE P&L'!AJ62+'EE P&L'!AJ62+'ROW P&L'!AJ63 -> 0 | AK62: ='UK P&L'!AK62+'CE P&L'!AK62+'EE P&L'!AK62+'ROW P&L'!AK63 -> 0 | AL62: ='UK P&L'!AL62+'CE P&L'!AL62+'EE P&L'!AL62+'ROW P&L'!AL63 -> 0 | AM62: ='UK P&L'!AM62+'CE P&L'!AM62+'EE P&L'!AM62+'ROW P&L'!AM63 -> 0 | AN62: ='UK P&L'!AN62+'CE P&L'!AN62+'EE P&L'!AN62+'ROW P&L'!AN63 -> 0 | AO62: ='UK P&L'!AO62+'CE P&L'!AO62+'EE P&L'!AO62+'ROW P&L'!AO63 -> 0 | ... AS62: ='UK P&L'!AS62+'CE P&L'!AS62+'EE P&L'!AS62+'ROW P&L'!AS63 -> 0 | AU62: =SUM(AH62:AS62) -> 0
B63: Paid Social | D63: -17768 | E63: -56223 | F63: -78366 | G63: -45773 | H63: -33767 | I63: -85384 | J63: -110608 | K63: -87600 | L63: -207099 | M63: -145864 | N63: -86182 | O63: -83038 | Q63: =SUM(D63:O63) -> -1037672 | S63: ='UK P&L'!S63+'CE P&L'!S63+'EE P&L'!S63+'ROW P&L'!S64 -> 0 | T63: ='UK P&L'!T63+'CE P&L'!T63+'EE P&L'!T63+'ROW P&L'!T64 -> 0 | U63: ='UK P&L'!U63+'CE P&L'!U63+'EE P&L'!U63+'ROW P&L'!U64 -> 0 | V63: ='UK P&L'!V63+'CE P&L'!V63+'EE P&L'!V63+'ROW P&L'!V64 -> 0 | W63: ='UK P&L'!W63+'CE P&L'!W63+'EE P&L'!W63+'ROW P&L'!W64 -> 0 | X63: ='UK P&L'!X63+'CE P&L'!X63+'EE P&L'!X63+'ROW P&L'!X64 -> 0 | Y63: ='UK P&L'!Y63+'CE P&L'!Y63+'EE P&L'!Y63+'ROW P&L'!Y64 -> 0 | Z63: ='UK P&L'!Z63+'CE P&L'!Z63+'EE P&L'!Z63+'ROW P&L'!Z64 -> 0 | ... AD63: ='UK P&L'!AD63+'CE P&L'!AD63+'EE P&L'!AD63+'ROW P&L'!AD64 -> 0 | AF63: =SUM(S63:AD63) -> 0 | AH63: ='UK P&L'!AH63+'CE P&L'!AH63+'EE P&L'!AH63+'ROW P&L'!AH64 -> 0 | AI63: ='UK P&L'!AI63+'CE P&L'!AI63+'EE P&L'!AI63+'ROW P&L'!AI64 -> 0 | AJ63: ='UK P&L'!AJ63+'CE P&L'!AJ63+'EE P&L'!AJ63+'ROW P&L'!AJ64 -> 0 | AK63: ='UK P&L'!AK63+'CE P&L'!AK63+'EE P&L'!AK63+'ROW P&L'!AK64 -> 0 | AL63: ='UK P&L'!AL63+'CE P&L'!AL63+'EE P&L'!AL63+'ROW P&L'!AL64 -> 0 | AM63: ='UK P&L'!AM63+'CE P&L'!AM63+'EE P&L'!AM63+'ROW P&L'!AM64 -> 0 | AN63: ='UK P&L'!AN63+'CE P&L'!AN63+'EE P&L'!AN63+'ROW P&L'!AN64 -> 0 | AO63: ='UK P&L'!AO63+'CE P&L'!AO63+'EE P&L'!AO63+'ROW P&L'!AO64 -> 0 | ... AS63: ='UK P&L'!AS63+'CE P&L'!AS63+'EE P&L'!AS63+'ROW P&L'!AS64 -> 0 | AU63: =SUM(AH63:AS63) -> 0
B64: Retail Partnerships | D64: -39042 | E64: -49117 | F64: -35557 | G64: -34117 | H64: -39824 | I64: -34894 | J64: -34148 | K64: -34117 | L64: -45450 | M64: -18625 | N64: -18899 | O64: -15293 | Q64: =SUM(D64:O64) -> -399083 | S64: ='UK P&L'!S64+'CE P&L'!S64+'EE P&L'!S64+'ROW P&L'!S65 -> -37355.035 | T64: ='UK P&L'!T64+'CE P&L'!T64+'EE P&L'!T64+'ROW P&L'!T65 -> -47391.544 | U64: ='UK P&L'!U64+'CE P&L'!U64+'EE P&L'!U64+'ROW P&L'!U65 -> -35764.263 | V64: ='UK P&L'!V64+'CE P&L'!V64+'EE P&L'!V64+'ROW P&L'!V65 -> -40815.921 | W64: ='UK P&L'!W64+'CE P&L'!W64+'EE P&L'!W64+'ROW P&L'!W65 -> -43932.088 | X64: ='UK P&L'!X64+'CE P&L'!X64+'EE P&L'!X64+'ROW P&L'!X65 -> -34053.339 | Y64: ='UK P&L'!Y64+'CE P&L'!Y64+'EE P&L'!Y64+'ROW P&L'!Y65 -> -47017.509 | Z64: ='UK P&L'!Z64+'CE P&L'!Z64+'EE P&L'!Z64+'ROW P&L'!Z65 -> -87773.305 | ... AD64: ='UK P&L'!AD64+'CE P&L'!AD64+'EE P&L'!AD64+'ROW P&L'!AD65 -> -38321.143 | AF64: =SUM(S64:AD64) -> -548259.09 | AH64: ='UK P&L'!AH64+'CE P&L'!AH64+'EE P&L'!AH64+'ROW P&L'!AH65 -> -54646.57 | AI64: ='UK P&L'!AI64+'CE P&L'!AI64+'EE P&L'!AI64+'ROW P&L'!AI65 -> -53458.04 | AJ64: ='UK P&L'!AJ64+'CE P&L'!AJ64+'EE P&L'!AJ64+'ROW P&L'!AJ65 -> -57144.964 | AK64: ='UK P&L'!AK64+'CE P&L'!AK64+'EE P&L'!AK64+'ROW P&L'!AK65 -> -56896.674 | AL64: ='UK P&L'!AL64+'CE P&L'!AL64+'EE P&L'!AL64+'ROW P&L'!AL65 -> -62667.649 | AM64: ='UK P&L'!AM64+'CE P&L'!AM64+'EE P&L'!AM64+'ROW P&L'!AM65 -> -47882.642 | AN64: ='UK P&L'!AN64+'CE P&L'!AN64+'EE P&L'!AN64+'ROW P&L'!AN65 -> -67325.782 | AO64: ='UK P&L'!AO64+'CE P&L'!AO64+'EE P&L'!AO64+'ROW P&L'!AO65 -> -123812.83 | ... AS64: ='UK P&L'!AS64+'CE P&L'!AS64+'EE P&L'!AS64+'ROW P&L'!AS65 -> -56094.282 | AU64: =SUM(AH64:AS64) -> -797205.4
B65: Retros | D65: -93880 | E65: -42740 | F65: -67600 | G65: -77284 | H65: -120500 | I65: -65983 | J65: -28104 | K65: -70278 | L65: -146884 | M65: -150857 | N65: -121316 | O65: -111483 | Q65: =SUM(D65:O65) -> -1096909 | S65: ='UK P&L'!S65+'CE P&L'!S65+'EE P&L'!S65+'ROW P&L'!S66 -> -106001.27 | T65: ='UK P&L'!T65+'CE P&L'!T65+'EE P&L'!T65+'ROW P&L'!T66 -> -86860.732 | U65: ='UK P&L'!U65+'CE P&L'!U65+'EE P&L'!U65+'ROW P&L'!U66 -> -68706.689 | V65: ='UK P&L'!V65+'CE P&L'!V65+'EE P&L'!V65+'ROW P&L'!V66 -> -78663.158 | W65: ='UK P&L'!W65+'CE P&L'!W65+'EE P&L'!W65+'ROW P&L'!W66 -> -102745.89 | X65: ='UK P&L'!X65+'CE P&L'!X65+'EE P&L'!X65+'ROW P&L'!X66 -> -70343.512 | Y65: ='UK P&L'!Y65+'CE P&L'!Y65+'EE P&L'!Y65+'ROW P&L'!Y66 -> -96072.765 | Z65: ='UK P&L'!Z65+'CE P&L'!Z65+'EE P&L'!Z65+'ROW P&L'!Z66 -> -208822 | ... AD65: ='UK P&L'!AD65+'CE P&L'!AD65+'EE P&L'!AD65+'ROW P&L'!AD66 -> -104177.35 | AF65: =SUM(S65:AD65) -> -1297117.4 | AH65: ='UK P&L'!AH65+'CE P&L'!AH65+'EE P&L'!AH65+'ROW P&L'!AH66 -> -100867.39 | AI65: ='UK P&L'!AI65+'CE P&L'!AI65+'EE P&L'!AI65+'ROW P&L'!AI66 -> -76589.33 | AJ65: ='UK P&L'!AJ65+'CE P&L'!AJ65+'EE P&L'!AJ65+'ROW P&L'!AJ66 -> -75732.133 | AK65: ='UK P&L'!AK65+'CE P&L'!AK65+'EE P&L'!AK65+'ROW P&L'!AK66 -> -80382.677 | AL65: ='UK P&L'!AL65+'CE P&L'!AL65+'EE P&L'!AL65+'ROW P&L'!AL66 -> -99502.718 | AM65: ='UK P&L'!AM65+'CE P&L'!AM65+'EE P&L'!AM65+'ROW P&L'!AM66 -> -71995.824 | AN65: ='UK P&L'!AN65+'CE P&L'!AN65+'EE P&L'!AN65+'ROW P&L'!AN66 -> -97478.076 | AO65: ='UK P&L'!AO65+'CE P&L'!AO65+'EE P&L'!AO65+'ROW P&L'!AO66 -> -196013.88 | ... AS65: ='UK P&L'!AS65+'CE P&L'!AS65+'EE P&L'!AS65+'ROW P&L'!AS66 -> -98484.826 | AU65: =SUM(AH65:AS65) -> -1256094.3
B66: Promo Funding | M66: - | N66: - | O66: - | S66: ='UK P&L'!S66+'CE P&L'!S66+'EE P&L'!S66+'ROW P&L'!S67 -> -4979.09 | T66: ='UK P&L'!T66+'CE P&L'!T66+'EE P&L'!T66+'ROW P&L'!T67 -> -20661.333 | U66: ='UK P&L'!U66+'CE P&L'!U66+'EE P&L'!U66+'ROW P&L'!U67 -> -10014.075 | V66: ='UK P&L'!V66+'CE P&L'!V66+'EE P&L'!V66+'ROW P&L'!V67 -> -26089.963 | W66: ='UK P&L'!W66+'CE P&L'!W66+'EE P&L'!W66+'ROW P&L'!W67 -> -11821.891 | X66: ='UK P&L'!X66+'CE P&L'!X66+'EE P&L'!X66+'ROW P&L'!X67 -> -6869.1495 | Y66: ='UK P&L'!Y66+'CE P&L'!Y66+'EE P&L'!Y66+'ROW P&L'!Y67 -> -13383.985 | Z66: ='UK P&L'!Z66+'CE P&L'!Z66+'EE P&L'!Z66+'ROW P&L'!Z67 -> -10109.056 | ... AD66: ='UK P&L'!AD66+'CE P&L'!AD66+'EE P&L'!AD66+'ROW P&L'!AD67 -> -7481.289 | AF66: =SUM(S66:AD66) -> -145568.86 | AH66: ='UK P&L'!AH66+'CE P&L'!AH66+'EE P&L'!AH66+'ROW P&L'!AH67 -> -23860.206 | AI66: ='UK P&L'!AI66+'CE P&L'!AI66+'EE P&L'!AI66+'ROW P&L'!AI67 -> -21428.605 | AJ66: ='UK P&L'!AJ66+'CE P&L'!AJ66+'EE P&L'!AJ66+'ROW P&L'!AJ67 -> -20964.951 | AK66: ='UK P&L'!AK66+'CE P&L'!AK66+'EE P&L'!AK66+'ROW P&L'!AK67 -> -31698.662 | AL66: ='UK P&L'!AL66+'CE P&L'!AL66+'EE P&L'!AL66+'ROW P&L'!AL67 -> -28102.763 | AM66: ='UK P&L'!AM66+'CE P&L'!AM66+'EE P&L'!AM66+'ROW P&L'!AM67 -> -18475.357 | AN66: ='UK P&L'!AN66+'CE P&L'!AN66+'EE P&L'!AN66+'ROW P&L'!AN67 -> -26651.981 | AO66: ='UK P&L'!AO66+'CE P&L'!AO66+'EE P&L'!AO66+'ROW P&L'!AO67 -> -53424.412 | ... AS66: ='UK P&L'!AS66+'CE P&L'!AS66+'EE P&L'!AS66+'ROW P&L'!AS67 -> -23813.969 | AU66: =SUM(AH66:AS66) -> -340078.83
B67: Exhibitions | D67: -12537 | E67: -7106 | F67: - | G67: -16579 | H67: -60 | I67: 198 | J67: - | K67: - | L67: -11249 | M67: - | N67: - | O67: - | Q67: =SUM(D67:O67) -> -47333 | S67: ='UK P&L'!S67+'CE P&L'!S67+'EE P&L'!S67+'ROW P&L'!S68 -> -8500 | T67: ='UK P&L'!T67+'CE P&L'!T67+'EE P&L'!T67+'ROW P&L'!T68 -> -17000 | U67: ='UK P&L'!U67+'CE P&L'!U67+'EE P&L'!U67+'ROW P&L'!U68 -> 0 | V67: ='UK P&L'!V67+'CE P&L'!V67+'EE P&L'!V67+'ROW P&L'!V68 -> -14000 | W67: ='UK P&L'!W67+'CE P&L'!W67+'EE P&L'!W67+'ROW P&L'!W68 -> 0 | X67: ='UK P&L'!X67+'CE P&L'!X67+'EE P&L'!X67+'ROW P&L'!X68 -> 0 | Y67: ='UK P&L'!Y67+'CE P&L'!Y67+'EE P&L'!Y67+'ROW P&L'!Y68 -> 0 | Z67: ='UK P&L'!Z67+'CE P&L'!Z67+'EE P&L'!Z67+'ROW P&L'!Z68 -> 0 | ... AD67: ='UK P&L'!AD67+'CE P&L'!AD67+'EE P&L'!AD67+'ROW P&L'!AD68 -> 0 | AF67: =SUM(S67:AD67) -> -54500 | AH67: ='UK P&L'!AH67+'CE P&L'!AH67+'EE P&L'!AH67+'ROW P&L'!AH68 -> -8500 | AI67: ='UK P&L'!AI67+'CE P&L'!AI67+'EE P&L'!AI67+'ROW P&L'!AI68 -> -17000 | AJ67: ='UK P&L'!AJ67+'CE P&L'!AJ67+'EE P&L'!AJ67+'ROW P&L'!AJ68 -> 0 | AK67: ='UK P&L'!AK67+'CE P&L'!AK67+'EE P&L'!AK67+'ROW P&L'!AK68 -> -14000 | AL67: ='UK P&L'!AL67+'CE P&L'!AL67+'EE P&L'!AL67+'ROW P&L'!AL68 -> 0 | AM67: ='UK P&L'!AM67+'CE P&L'!AM67+'EE P&L'!AM67+'ROW P&L'!AM68 -> 0 | AN67: ='UK P&L'!AN67+'CE P&L'!AN67+'EE P&L'!AN67+'ROW P&L'!AN68 -> 0 | AO67: ='UK P&L'!AO67+'CE P&L'!AO67+'EE P&L'!AO67+'ROW P&L'!AO68 -> 0 | ... AS67: ='UK P&L'!AS67+'CE P&L'!AS67+'EE P&L'!AS67+'ROW P&L'!AS68 -> 0 | AU67: =SUM(AH67:AS67) -> -54500
